{"name": "kernel4a3b468030 ", "full_name": " h1 \u041e\u043f\u0440\u0435\u0434\u0435\u043b\u0435\u043d\u0438\u0435 \u0441\u0442\u0430\u0434\u0438\u0438 \u0440\u0430\u043a\u0430 \u043f\u0440\u043e\u0441\u0442\u0430\u0442\u044b \u043f\u043e \u0446\u0438\u0444\u0440\u043e\u0432\u043e\u0439 \u043f\u0430\u0442\u043e\u043b\u043e\u0433\u0438\u0438 \u0431\u0438\u043e\u043f\u0441\u0438\u0438 h3 1 \u0427\u0442\u043e \u0442\u0430\u043a\u043e\u0435 \u0440\u0430\u043a \u043f\u0440\u043e\u0441\u0442\u0430\u0442\u044b h3 2 \u0414\u0438\u0430\u0433\u043d\u043e\u0441\u0442\u0438\u043a\u0430 \u0438 \u0441\u0442\u0430\u0434\u0438\u0438 \u0440\u0430\u043a\u0430 \u043f\u0440\u043e\u0441\u0442\u0430\u0442\u044b h3 3 \u0420\u0435\u0448\u0435\u043d\u0438\u0435 \u043c\u0435\u0434\u0438\u0446\u0438\u043d\u0441\u043a\u0438\u0445 \u0437\u0430\u0434\u0430\u0447 \u0441 \u043f\u043e\u043c\u043e\u0449\u044c\u044e \u043d\u0435\u0439\u0440\u043e\u0441\u0435\u0442\u0435\u0439 h3 4 \u0421\u0432\u044f\u0437\u044c \u0431\u0438\u043e\u043f\u0441\u0438\u0438 \u0438 \u0448\u043a\u0430\u043b\u044b \u0413\u043b\u0438\u0441\u043e\u043d\u0430 h3 5 \u0427\u0442\u043e \u0442\u0430\u043a\u043e\u0435 ISUP h3 6 \u041a\u0430\u043a \u0432\u044b\u0433\u043b\u044f\u0434\u0438\u0442 \u0448\u043a\u0430\u043b\u0430 \u0413\u043b\u0438\u0441\u043e\u043d \u0432 \u043d\u0430\u0448\u0435\u043c \u0434\u0430\u0442\u0430\u0441\u0435\u0442\u0435 h1 \u041e\u0441\u043e\u0431\u0435\u043d\u043d\u043e\u0441\u0442\u0438 \u0434\u0430\u043d\u043d\u044b\u0445 \u043f\u0440\u0438\u0441\u0432\u043e\u0435\u043d\u0438\u0435 \u0431\u0430\u043b\u043b\u043e\u0432 \u043f\u043e \u0448\u043a\u0430\u043b\u0435 \u0413\u043b\u0438\u0441\u043e\u043d h1 EDA \u043f\u0440\u0435\u0434\u043e\u0431\u0440\u0430\u0431\u043e\u0442\u043a\u0430 \u0434\u0430\u043d\u043d\u044b\u0445 h2 \u041a\u043b\u0430\u0441\u0441 \u043a\u043e\u043d\u0444\u0438\u0433\u0443\u0440\u0430\u0442\u043e\u0440 h3 \u041f\u043e\u0441\u043c\u043e\u0442\u0440\u0438\u043c \u0442\u0435\u043f\u0435\u0440\u044c \u0447\u0442\u043e \u043b\u0435\u0436\u0438\u0442 \u0432 \u0434\u0430\u0442\u0430\u0441\u0435\u0442\u0435 test csv h1 EDA \u0430\u043d\u0430\u043b\u0438\u0437 h1 Image EDA h2 1 \u041a\u0430\u043a\u043e\u0439 \u0444\u043e\u0440\u043c\u0430\u0442 \u0438\u0437\u043e\u0431\u0440\u0430\u0436\u0435\u043d\u0438\u0439 \u043d\u0430\u043c \u043f\u0440\u0435\u0434\u043e\u0441\u0442\u0430\u0432\u043b\u0435\u043d \u0438 \u043a\u0430\u043a \u0441 \u043d\u0438\u043c \u0440\u0430\u0431\u043e\u0442\u0430\u0442\u044c h2 2 \u0417\u0430\u0447\u0435\u043c \u043d\u0430\u043c \u0443\u0440\u043e\u0432\u043d\u0438 levels \u0438\u0437\u043e\u0431\u0440\u0430\u0436\u0435\u043d\u0438\u044f h2 3 \u0427\u0442\u043e \u0442\u0430\u043a\u043e\u0435 \u043f\u043e\u043d\u0438\u0436\u0430\u044e\u0449\u0430\u044f Downsampling \u0438 \u043f\u043e\u0432\u044b\u0448\u0430\u044e\u0449\u0430\u044f Upsampling \u0434\u0438\u0441\u043a\u0440\u0435\u0442\u0438\u0437\u0430\u0446\u0438\u044f \u043f\u0440\u0438 \u043e\u0431\u0440\u0430\u0431\u043e\u0442\u043a\u0435 \u0438\u0437\u043e\u0431\u0440\u0430\u0436\u0435\u043d\u0438\u0439 h1 \u0422\u0435\u043f\u0435\u0440\u044c \u043f\u043e\u0441\u043c\u043e\u0442\u0440\u0438\u043c \u043a\u0430\u043a\u0443\u044e \u0438\u043d\u0444\u043e\u0440\u043c\u0430\u0446\u0438\u044e \u043c\u044b \u043c\u043e\u0436\u0435\u043c \u043f\u043e\u043b\u0443\u0447\u0438\u0442\u044c \u0438\u0437 \u0438\u0437\u043e\u0431\u0440\u0430\u0436\u0435\u043d\u0438\u044f \u043f\u043e\u0441\u043b\u0435 \u0441\u043e\u0437\u0434\u0430\u043d\u0438\u044f \u043e\u0431\u044a\u0435\u043a\u0442\u0430 Openslide h3 \u0412\u044b\u0432\u0435\u0434\u0435\u043c \u0441\u0440\u0430\u0437\u0443 \u043d\u0435\u0441\u043a\u043e\u043b\u044c\u043a\u043e \u0438\u0437\u043e\u0431\u0440\u0430\u0436\u0435\u043d\u0438\u0439 \u0441 \u0440\u0430\u0437\u043d\u044b\u043c\u0438 ISUP \u0438 gleason score h2 train laibel masks h3 1 \u0417\u0430\u0447\u0435\u043c \u043d\u0443\u0436\u043d\u0430 \u043c\u0430\u0441\u043a\u0430 \u0434\u043b\u044f \u0438\u0437\u043e\u0431\u0440\u0430\u0436\u0435\u043d\u0438\u044f h2 \u0420\u0430\u0437\u043b\u0438\u0447\u0435\u043d\u0438\u0435 \u0437\u043b\u043e\u043a\u0430\u0447\u0435\u0441\u0442\u0432\u0435\u043d\u043d\u044b\u0445 \u0438 \u043d\u0435\u0437\u043b\u043e\u043a\u0430\u0447\u0435\u0441\u0442\u0432\u0435\u043d\u043d\u044b\u0445 \u043e\u0431\u043b\u0430\u0441\u0442\u0435\u0439 \u0441 \u043f\u043e\u043c\u043e\u0449\u044c\u044e \u041c\u0410\u0421\u041a\u0418 h2 \u041d\u0430\u043b\u043e\u0436\u0435\u043d\u0438\u0435 \u043c\u0430\u0441\u043e\u043a \u043d\u0430 \u0441\u043b\u0430\u0439\u0434\u044b h1 \u0422\u0440\u0435\u043d\u0438\u0440\u043e\u0432\u043a\u0430 \u043c\u043e\u0434\u0435\u043b\u0438 h2 EfficientNet B3 Model h1 \u041f\u0440\u0435\u043e\u0431\u0440\u0430\u0437\u043e\u0432\u0430\u043d\u0438\u0435 \u0438\u0437\u043e\u0431\u0440\u0430\u0436\u0435\u043d\u0438\u044f \u0441 \u043f\u043e\u043c\u043e\u0449\u044c\u044e \u0441\u0432\u0435\u0440\u0442\u043a\u0438 \u043a\u0430\u0440\u0442\u044b \u0444\u0440\u0430\u0433\u043c\u0435\u043d\u0442\u043e\u0432 h1 \u041c\u0435\u0442\u0440\u0438\u043a\u0430 \u043a\u0430\u0447\u0435\u0441\u0442\u0432\u0430 \u043c\u043e\u0434\u0435\u043b\u0438 ", "stargazers_count": 0, "forks_count": 0, "description": "train_images \u0426\u0438\u0444\u0440\u043e\u0432\u0430\u044f \u043f\u0430\u0442\u043e\u043b\u043e\u0433\u0438\u044f \u0438\u0437\u043e\u0431\u0440\u0430\u0436\u0435\u043d\u0438\u044f \u043f\u043e\u043b\u0443\u0447\u0435\u043d\u043d\u044b\u0435 \u043d\u0430 \u0431\u0438\u043e\u043f\u0441\u0438\u0438 \u0441 \u0434\u0432\u0443\u0445 \u0443\u0447\u0430\u0441\u0442\u043a\u043e\u0432 \u043e\u043f\u0443\u0445\u043e\u043b\u0438. com c prostate cancer grade assessment overview additional resources EDA \u043f\u0440\u0435\u0434\u043e\u0431\u0440\u0430\u0431\u043e\u0442\u043a\u0430 \u0434\u0430\u043d\u043d\u044b\u0445. ReLU inplace True else layer0_modules conv1 nn. \u0421\u043b\u0435\u0434\u043e\u0432\u0430\u0442\u0435\u043b\u044c\u043d\u043e \u043c\u044b \u043c\u043e\u0436\u0435\u043c \u0437\u0430\u043c\u0435\u043d\u0438\u0442\u044c \u0437\u043d\u0430\u0447\u0435\u043d\u0438\u0435 negative \u043d\u0430 0 0 \u041a\u0430\u043a \u0443\u0436\u0435 \u0443\u043a\u0430\u0437\u044b\u0432\u0430\u043b\u043e\u0441\u044c \u0440\u0430\u043d\u0435\u0435 \u0432 \u0440\u0430\u0437\u0434\u0435\u043b\u0435 \u043f\u043e \u043f\u0440\u043e\u0431\u043b\u0435\u043c\u0430\u043c \u0434\u0430\u043d\u043d\u044b\u0445 \u0448\u043a\u0430\u043b\u0430 \u0413\u043b\u0438\u0441\u043e\u043d \u043f\u0440\u0438 \u0443\u0447\u0430\u0441\u0442\u043a\u0430\u0445 3 4 \u0438 4 3 \u0438\u043c\u0435\u0435\u0442 \u0440\u0430\u0437\u043d\u044b\u0435 \u0437\u043d\u0430\u0447\u0435\u043d\u0438\u044f \u0431\u0430\u043b\u043b\u0430\u043c \u043f\u043e ISUP \u0432 \u0442\u043e \u0432\u0440\u0435\u043c\u044f \u043a\u0430\u043a 3 5 \u0438 5 3 \u0430 \u0442\u0430\u043a\u0436\u0435 4 5 \u0438 5 4 \u043e\u0434\u0438\u043d\u0430\u043a\u043e\u0432\u044b\u0435. ImageNet Large Scale Visual Recognition Challenge \u041a\u0430\u043c\u043f\u0430\u043d\u0438\u044f \u043f\u043e \u0448\u0438\u0440\u043e\u043a\u043e\u043c\u0430\u0441\u0448\u0442\u0430\u0431\u043d\u043e\u043c\u0443 \u0440\u0430\u0441\u043f\u043e\u0437\u043d\u0430\u0432\u0430\u043d\u0438\u044e \u043e\u0431\u0440\u0430\u0437\u043e\u0432 \u0432 ImageNet \u0432 \u0440\u0430\u043c\u043a\u0430\u0445 \u043a\u043e\u0442\u043e\u0440\u043e\u0433\u043e \u0440\u0430\u0437\u043b\u0438\u0447\u043d\u044b\u0435 \u043f\u0440\u043e\u0433\u0440\u0430\u043c\u043c\u043d\u044b\u0435 \u043f\u0440\u043e\u0434\u0443\u043a\u0442\u044b \u0435\u0436\u0435\u0433\u043e\u0434\u043d\u043e \u0441\u043e\u0440\u0435\u0432\u043d\u0443\u044e\u0442\u0441\u044f \u0432 \u043a\u043b\u0430\u0441\u0441\u0438\u0444\u0438\u043a\u0430\u0446\u0438\u0438 \u0438 \u0440\u0430\u0441\u043f\u043e\u0437\u043d\u0430\u0432\u0430\u043d\u0438\u0438 \u043e\u0431\u044a\u0435\u043a\u0442\u043e\u0432 \u0438 \u0441\u0446\u0435\u043d \u0432 \u0431\u0430\u0437\u0435 \u0434\u0430\u043d\u043d\u044b\u0445 ImageNet. \u0414\u043e\u0431\u0440\u043e\u043a\u0430\u0447\u0435\u0441\u0442\u0432\u0435\u043d\u043d\u044b\u0435 \u043f\u0440\u0435\u0434\u0441\u0442\u0430\u0442\u0435\u043b\u044c\u043d\u044b\u0435 \u0436\u0435\u043b\u0435\u0437\u044b \u0441\u043e \u0441\u043a\u043b\u0430\u0434\u0447\u0430\u0442\u044b\u043c \u044d\u043f\u0438\u0442\u0435\u043b\u0438\u0435\u043c. Downsampling \u044d\u0442\u043e \u0441\u043d\u0438\u0436\u0435\u043d\u0438\u0435 \u043f\u0440\u043e\u0441\u0442\u0440\u0430\u043d\u0441\u0442\u0432\u0435\u043d\u043d\u043e\u0433\u043e \u0440\u0430\u0437\u0440\u0435\u0448\u0435\u043d\u0438\u044f \u043f\u0440\u0438 \u0441\u043e\u0445\u0440\u0430\u043d\u0435\u043d\u0438\u0438 \u0442\u043e\u0433\u043e \u0436\u0435 \u0434\u0432\u0443\u0445\u043c\u0435\u0440\u043d\u043e\u0433\u043e 2D \u043f\u0440\u0435\u0434\u0441\u0442\u0430\u0432\u043b\u0435\u043d\u0438\u044f. fc1 x x self. pth ensemble_weight 1 ensemble model_name se_resnext50_32x4d model_weight. \u0418\u0441\u043f\u043e\u043b\u044c\u0437\u0443\u0435\u043c \u0438\u0437\u043e\u0431\u0440\u0430\u0436\u0435\u043d\u0438\u044f \u043a\u043e\u0442\u043e\u0440\u044b\u0435 \u043c\u044b \u0440\u0430\u0441\u0441\u043c\u043e\u0442\u0440\u0435\u043b\u0438 \u0440\u0430\u043d\u0435\u0435 \u0441 \u0440\u0430\u0437\u043d\u044b\u043c\u0438 \u0431\u0430\u043b\u043b\u0430\u043c\u0438 \u0438 \u0441\u0442\u0430\u0434\u0438\u044f\u043c\u0438 \u0440\u0430\u043a\u0430 \u0442\u0430\u043a\u0436\u0435 \u043d\u043e\u0440\u043c\u0430\u043b\u044c\u043d\u0443\u044e \u0442\u043a\u0430\u043d\u044c \u0414\u043e\u0431\u0430\u0432\u0438\u043c \u0443\u0441\u043b\u043e\u0432\u0438\u0435 \u0432\u0438\u0437\u0443\u0430\u043b\u0438\u0437\u0438\u0440\u043e\u0432\u0430\u0442\u044c \u043c\u0430\u0441\u043a\u0443 \u0435\u0441\u043b\u0438 \u043e\u043d\u0430 \u0435\u0441\u0442\u044c \u0420\u0430\u0437\u043b\u0438\u0447\u0435\u043d\u0438\u0435 \u0437\u043b\u043e\u043a\u0430\u0447\u0435\u0441\u0442\u0432\u0435\u043d\u043d\u044b\u0445 \u0438 \u043d\u0435\u0437\u043b\u043e\u043a\u0430\u0447\u0435\u0441\u0442\u0432\u0435\u043d\u043d\u044b\u0445 \u043e\u0431\u043b\u0430\u0441\u0442\u0435\u0439 \u0441 \u043f\u043e\u043c\u043e\u0449\u044c\u044e \u041c\u0410\u0421\u041a\u0418\u041f\u0440\u0438 \u0432\u0438\u0437\u0443\u0430\u043b\u0438\u0437\u0430\u0446\u0438\u0438 \u043c\u0430\u0441\u043a\u0438 \u043d\u0435\u043e\u0431\u0445\u043e\u0434\u0438\u043c\u043e \u0443\u0447\u0438\u0442\u044b\u0432\u0430\u0442\u044c \u0447\u0442\u043e \u043c\u0430\u0441\u043a\u0438 \u0440\u0430\u0437\u043d\u044b\u0435 \u0434\u043b\u044f \u0440\u0430\u0437\u043d\u044b\u0445 \u043f\u043e\u0441\u0442\u0430\u0432\u0449\u0438\u043a\u043e\u0432 \u0434\u0430\u043d\u043d\u044b\u0445\u0422\u0435\u043f\u0435\u0440\u044c \u043a\u043e\u0433\u0434\u0430 \u0443 \u043d\u0430\u0441 \u0435\u0441\u0442\u044c \u0444\u0443\u043d\u043a\u0446\u0438\u044f \u0434\u0430\u0432\u0430\u0439\u0442\u0435 \u0432\u0438\u0437\u0443\u0430\u043b\u0438\u0437\u0438\u0440\u0443\u0435\u043c \u041d\u0430\u043b\u043e\u0436\u0435\u043d\u0438\u0435 \u043c\u0430\u0441\u043e\u043a \u043d\u0430 \u0441\u043b\u0430\u0439\u0434\u044b\u0422\u0435\u043f\u0435\u0440\u044c \u043a\u043e\u0433\u0434\u0430 \u043c\u044b \u0443\u0437\u043d\u0430\u043b\u0438 \u043a\u0430\u043a \u0432\u0438\u0437\u0443\u0430\u043b\u0438\u0437\u0438\u0440\u043e\u0432\u0430\u0442\u044c \u043c\u0430\u0441\u043a\u0438 \u0438 \u043e\u0442\u043e\u0431\u0440\u0430\u0436\u0430\u0442\u044c \u0438\u0445 \u0440\u044f\u0434\u043e\u043c \u0434\u0430\u0432\u0430\u0439\u0442\u0435 \u043d\u0430\u043b\u043e\u0436\u0438\u043c \u0438\u0445 \u0434\u0440\u0443\u0433 \u043d\u0430 \u0434\u0440\u0443\u0433\u0430. bn2 out out self. load ensemble model_weight map_location device model. \u0412 \u043d\u0430\u0448\u0435\u043c \u0434\u0430\u0442\u0430\u0441\u0435\u0442\u0435 train. relu out return out class SEBottleneck Bottleneck Bottleneck for SENet154. \u042d\u0442\u0438 \u043c\u0430\u0441\u043a\u0438 \u043f\u0440\u044f\u043c\u043e \u0443\u043a\u0430\u0437\u044b\u0432\u0430\u044e\u0442 \u043a\u0430\u043a\u0438\u0435 \u0447\u0430\u0441\u0442\u0438 \u0442\u043a\u0430\u043d\u0438 \u044f\u0432\u043b\u044f\u044e\u0442\u0441\u044f \u0437\u0434\u043e\u0440\u043e\u0432\u044b\u043c\u0438 \u0430 \u043a\u0430\u043a\u0438\u0435 \u0437\u043b\u043e\u043a\u0430\u0447\u0435\u0441\u0442\u0432\u0435\u043d\u043d\u044b\u043c\u0438. \u0417\u043d\u0430\u0447\u0435\u043d\u0438\u044f \u043c\u0430\u0441\u043a\u0438 \u0437\u0430\u0432\u0438\u0441\u044f\u0442 \u043e\u0442 \u043f\u043e\u0441\u0442\u0430\u0432\u0449\u0438\u043a\u0430 \u0434\u0430\u043d\u043d\u044b\u0445 Radboud \u0436\u0435\u043b\u0435\u0437\u044b \u043f\u0440\u0435\u0434\u0441\u0442\u0430\u0442\u0435\u043b\u044c\u043d\u043e\u0439 \u0436\u0435\u043b\u0435\u0437\u044b \u0438\u043c\u0435\u044e\u0442 \u0438\u043d\u0434\u0438\u0432\u0438\u0434\u0443\u0430\u043b\u044c\u043d\u0443\u044e \u043c\u0430\u0440\u043a\u0438\u0440\u043e\u0432\u043a\u0443. sigmoid x return module_input x class Bottleneck nn. \u0414\u043b\u044f \u0432\u0438\u0437\u0443\u0430\u043b\u0438\u0437\u0430\u0446\u0438\u0438 \u043a\u043e\u043d\u0442\u0443\u0440\u043e\u0432 \u0436\u0435\u043b\u0435\u0437\u0438\u0441\u0442\u043e\u0439 \u0442\u043a\u0430\u043d\u0438 \u043c\u0430\u0442\u0435\u0440\u0438\u0430\u043b \u043f\u0430\u0446\u0438\u0435\u043d\u0442\u0430 \u043e\u043a\u0440\u0430\u0448\u0438\u0432\u0430\u044e\u0442 \u0433\u0435\u043c\u0430\u0442\u043e\u043a\u0441\u0438\u043b\u0438\u043d\u043e\u043c \u0438 \u044d\u043e\u0437\u0438\u043d\u043e\u043c H E \u0421\u043e\u0435\u0434\u0438\u043d\u0438\u0442\u0435\u043b\u044c\u043d\u0430\u044f \u0442\u043a\u0430\u043d\u044c \u043f\u0440\u0438\u043e\u0431\u0440\u0435\u0442\u0430\u0435\u0442 \u043e\u0442\u0442\u0435\u043d\u043a\u0438 \u0446\u0432\u0435\u0442\u0430 \u0430 \u0436\u0435\u043b\u0435\u0437\u0438\u0441\u0442\u0430\u044f \u043e\u0441\u0442\u0430\u0435\u0442\u0441\u044f \u0431\u0435\u043b\u044b\u043c\u0438 \u0438 \u043f\u043e\u043b\u0443\u043f\u0440\u043e\u0437\u0440\u0430\u0447\u043d\u044b\u043c\u0438 \u043f\u0440\u043e\u0441\u0432\u0435\u0442\u0430\u043c\u0438 \u0434\u044b\u0440\u0430\u043c\u0438 \u0430 \u0442\u0430\u043a\u0436\u0435 \u0440\u0430\u0437\u0432\u0435\u0442\u0432\u043b\u0435\u043d\u043d\u044b\u043c\u0438 \u043f\u043e\u043b\u043e\u0441\u0442\u044f\u043c\u0438. \u041c\u0435\u0436\u0434\u0443 \u0431\u0438\u043e\u043f\u0441\u0438\u044f\u043c\u0438 \u043d\u0430\u0431\u043b\u044e\u0434\u0430\u044e\u0442\u0441\u044f \u0437\u0430\u043c\u0435\u0442\u043d\u044b\u0435 \u0440\u0430\u0437\u043b\u0438\u0447\u0438\u044f \u0432 \u0446\u0432\u0435\u0442\u0435 \u0412\u044b\u0432\u0435\u0434\u0435\u043c \u0441\u0440\u0430\u0437\u0443 \u043d\u0435\u0441\u043a\u043e\u043b\u044c\u043a\u043e \u0438\u0437\u043e\u0431\u0440\u0430\u0436\u0435\u043d\u0438\u0439 \u0441 \u0440\u0430\u0437\u043d\u044b\u043c\u0438 ISUP \u0438 gleason_score train_laibel_masks 1. layer1 x x self. stride stride class SEResNetBottleneck Bottleneck ResNet bottleneck with a Squeeze and Excitation module. Conv2d inplanes planes kernel_size 1 bias False stride stride self. Conv2d planes planes 4 kernel_size 1 bias False self. \u041c\u043d\u043e\u0433\u0438\u0435 \u043f\u0440\u0438\u043b\u043e\u0436\u0435\u043d\u0438\u044f \u0432\u043a\u043b\u044e\u0447\u0430\u044e\u0442 \u0432 \u0441\u0435\u0431\u044f \u0441\u043e\u0431\u0441\u0442\u0432\u0435\u043d\u043d\u044b\u0435 \u0440\u0430\u0441\u0448\u0438\u0440\u0435\u043d\u0438\u044f \u043d\u043e \u0440\u044f\u0434 \u043d\u0435\u0437\u0430\u0432\u0438\u0441\u0438\u043c\u044b\u0445 \u043e\u0442 \u043f\u0440\u0438\u043b\u043e\u0436\u0435\u043d\u0438\u0439 \u0440\u0430\u0441\u0448\u0438\u0440\u0435\u043d\u0438\u0439 \u0440\u0430\u0441\u043f\u043e\u0437\u043d\u0430\u0435\u0442\u0441\u044f \u0431\u043e\u043b\u044c\u0448\u0438\u043d\u0441\u0442\u0432\u043e\u043c \u043f\u0440\u043e\u0433\u0440\u0430\u043c\u043c. \u0412 \u043d\u0435\u043a\u043e\u0442\u043e\u0440\u044b\u0445 \u0444\u043e\u0440\u043c\u0430\u0442\u0430\u0445 \u0438\u0437\u043e\u0431\u0440\u0430\u0436\u0435\u043d\u0438\u0439 \u0434\u0430\u043d\u043d\u044b\u0435 \u0438\u0437\u043e\u0431\u0440\u0430\u0436\u0435\u043d\u0438\u044f \u0438\u043c\u0435\u044e\u0442 \u0444\u0438\u043a\u0441\u0438\u0440\u043e\u0432\u0430\u043d\u043d\u043e\u0435 \u043a\u043e\u043b\u0438\u0447\u0435\u0441\u0442\u0432\u043e \u0432\u043e\u0437\u043c\u043e\u0436\u043d\u044b\u0445 \u0437\u043d\u0430\u0447\u0435\u043d\u0438\u0439 \u0438\u043d\u0442\u0435\u043d\u0441\u0438\u0432\u043d\u043e\u0441\u0442\u0438. Sequential nn. input panda open models resnext50_0. csv \u0438\u0437\u043d\u0430\u0447\u0430\u043b\u044c\u043d\u043e \u0440\u0430\u0441\u043f\u043e\u043b\u043e\u0436\u0435\u043d\u044b \u0432 \u043e\u0434\u043d\u043e\u043c \u0444\u0430\u0439\u043b\u0435 train. \u0426\u0435\u043b\u0435\u0432\u0443\u044e \u043f\u0435\u0440\u0435\u043c\u0435\u043d\u043d\u0443\u044e \u0438\u043c\u0435\u0435\u0442 \u0442\u043e\u043b\u044c\u043a\u043e \u0444\u0430\u0439\u043b train_images. \u0410 \u0438\u043c\u0435\u043d\u043d\u043e 3 4 2 \u0441\u0442\u0430\u0434\u0438\u044f \u0440\u0430\u043a\u0430 4 3 3 \u0441\u0442\u0430\u0434\u0438\u044f \u0440\u0430\u043a\u0430. CLASSES def forward self x x self. Conv2d 64 inplanes 3 stride 1 padding 1 bias False bn3 nn. conv2 out out self. com qubvel efficientnet blob master efficientnet weights. Conv2d width width kernel_size 3 stride stride padding 1 groups groups bias False self. Module def __init__ self block layers groups reduction dropout_p 0. ReLU inplace True conv3 nn. \u0423 \u043f\u0430\u0446\u0438\u0435\u043d\u0442\u0430 \u0445\u0438\u0440\u0443\u0440\u0433\u0438\u0447\u0435\u0441\u043a\u0438\u043c \u043f\u0443\u0442\u0435\u043c \u0438\u0437\u0432\u043b\u0435\u043a\u0430\u044e\u0442\u0441\u044f \u0434\u0432\u0430 \u043d\u0430\u0438\u0431\u043e\u043b\u0435\u0435 \u0445\u0430\u0440\u0430\u043a\u0442\u0435\u0440\u043d\u044b\u0445 \u0444\u0440\u0430\u0433\u043c\u0435\u043d\u0442\u0430 \u043f\u0440\u0435\u0434\u043f\u043e\u043b\u0430\u0433\u0430\u0435\u043c\u043e\u0439 \u043e\u043f\u0443\u0445\u043e\u043b\u0438. \u042d\u043a\u0441\u043f\u0435\u0440\u0442\u043d\u0430\u044f \u043e\u0446\u0435\u043d\u043a\u0430 \u0432\u0440\u0430\u0447\u0430 \u043e\u0441\u0442\u0430\u0435\u0442\u0441\u044f \u0441\u0442\u0430\u043d\u0434\u0430\u0440\u0442\u043e\u043c \u0434\u043b\u044f \u0442\u043e\u0433\u043e \u0447\u0442\u043e\u0431\u044b \u043f\u043e\u0441\u0442\u0430\u0432\u0438\u0442\u044c \u043e\u043a\u043e\u043d\u0447\u0430\u0442\u0435\u043b\u044c\u043d\u044b\u0439 \u0434\u0438\u0430\u0433\u043d\u043e\u0437 \u043e\u0434\u043d\u0430\u043a\u043e \u043a\u043e\u043c\u043f\u044c\u044e\u0442\u0435\u0440\u044b \u0443\u0436\u0435 \u0441\u0435\u0439\u0447\u0430\u0441 \u0441\u043f\u043e\u0441\u043e\u0431\u043d\u044b \u043f\u043e\u043c\u043e\u0433\u0430\u0442\u044c \u0432 \u0440\u0435\u0448\u0435\u043d\u0438\u0438 \u044d\u0442\u0438\u0445 \u0437\u0430\u0434\u0430\u0447 \u043e\u0442\u043c\u0435\u0442\u0438\u043b \u043f\u0440\u0435\u0434\u0441\u0442\u0430\u0432\u0438\u0442\u0435\u043b\u044c \u043c\u0435\u0436\u0434\u0443\u043d\u0430\u0440\u043e\u0434\u043d\u043e\u0433\u043e \u043a\u043e\u043b\u043b\u0435\u043a\u0442\u0438\u0432\u0430 \u0443\u0447\u0435\u043d\u044b\u0445 \u0432\u0435\u0434\u0443\u0449\u0438\u0439 \u0441\u043f\u0435\u0446\u0438\u0430\u043b\u0438\u0441\u0442 \u0415\u0432\u0440\u043e\u043f\u0435\u0439\u0441\u043a\u043e\u0433\u043e \u0438\u043d\u0441\u0442\u0438\u0442\u0443\u0442\u0430 \u0431\u0438\u043e\u0438\u043d\u0444\u043e\u0440\u043c\u0430\u0442\u0438\u043a\u0438 EMBL EBI \u041c\u043e\u0440\u0438\u0446 \u0413\u0435\u0440\u0448\u0442\u0443\u043d\u0433. \u0414\u043e\u043f\u0443\u0441\u0442\u0438\u043c\u044b\u0435 \u0437\u043d\u0430\u0447\u0435\u043d\u0438\u044f 1 \u0444\u043e\u043d \u043d\u0435 \u0442\u043a\u0430\u043d\u044c \u0438\u043b\u0438 \u043d\u0435\u0438\u0437\u0432\u0435\u0441\u0442\u043d\u043e 2 \u0434\u043e\u0431\u0440\u043e\u043a\u0430\u0447\u0435\u0441\u0442\u0432\u0435\u043d\u043d\u0430\u044f \u0442\u043a\u0430\u043d\u044c \u0441\u0442\u0440\u043e\u043c\u0430 \u0438 \u044d\u043f\u0438\u0442\u0435\u043b\u0438\u0439 \u0432\u043c\u0435\u0441\u0442\u0435 3 \u0437\u043b\u043e\u043a\u0430\u0447\u0435\u0441\u0442\u0432\u0435\u043d\u043d\u0430\u044f \u0442\u043a\u0430\u043d\u044c \u0441\u0442\u0440\u043e\u043c\u0430 \u0438 \u044d\u043f\u0438\u0442\u0435\u043b\u0438\u0439 \u0432\u043c\u0435\u0441\u0442\u0435 \u043f\u043e\u0441\u043c\u043e\u0442\u0440\u0438\u043c \u043d\u0430 \u043a\u0430\u043a\u0443\u044e \u043d\u0438\u0431\u0443\u0434\u044c \u043c\u0430\u0441\u043a\u0443 \u0418\u043d\u0444\u043e\u0440\u043c\u0430\u0446\u0438\u044f \u043c\u0435\u0442\u043a\u0438 \u0445\u0440\u0430\u043d\u0438\u0442\u0441\u044f \u0432 \u043a\u0440\u0430\u0441\u043d\u043e\u043c R \u043a\u0430\u043d\u0430\u043b\u0435 \u0434\u0440\u0443\u0433\u0438\u0435 \u043a\u0430\u043d\u0430\u043b\u044b \u0443\u0441\u0442\u0430\u043d\u043e\u0432\u043b\u0435\u043d\u044b \u043d\u0430 \u043d\u043e\u043b\u044c \u0438 \u043c\u043e\u0433\u0443\u0442 \u0438\u0433\u043d\u043e\u0440\u0438\u0440\u043e\u0432\u0430\u0442\u044c\u0441\u044f. \u041a \u0440\u0430\u043a\u043e\u0432\u044b\u043c \u043e\u0442\u043d\u043e\u0441\u044f\u0442\u0441\u044f \u0442\u043a\u0430\u043d\u0438 \u043f\u0440\u043e\u0441\u0442\u0430\u0442\u044b \u0438\u043c\u0435\u044e\u0449\u0438\u0435 \u0441\u0443\u043c\u043c\u0443 \u0413\u043b\u0438\u0441\u043e\u043d\u0430 \u0432\u044b\u0448\u0435 6. se_module SEModule planes 4 reduction reduction self. _make_layer block planes 512 blocks layers 3 stride 2 groups groups reduction reduction downsample_kernel_size downsample_kernel_size downsample_padding downsample_padding self. downsample is not None residual self. expansion layers layers. pretrained_settings se_resnext101_32x4d pretrained initialize_pretrained_model model num_classes settings return model class CustomSEResNeXt nn. model x return x model_name se_resnext50_32x4d model_weight. inplanes planes groups reduction return nn. Sigmoid def forward self x module_input x x self. \u0427\u0442\u043e \u0442\u0430\u043a\u043e\u0435 \u0440\u0430\u043a \u043f\u0440\u043e\u0441\u0442\u0430\u0442\u044b\u0420\u0430\u043a \u043f\u0440\u043e\u0441\u0442\u0430\u0442\u044b \u043a\u0430\u0440\u0446\u0438\u043d\u043e\u043c\u0430 \u043f\u0440\u043e\u0441\u0442\u0430\u0442\u044b \u043e\u0434\u0438\u043d \u0438\u0437 \u0441\u0430\u043c\u044b\u0445 \u0440\u0430\u0441\u043f\u0440\u043e\u0441\u0442\u0440\u0430\u043d\u0435\u043d\u043d\u044b\u0445 \u0432\u0438\u0434\u043e\u0432 \u0437\u043b\u043e\u043a\u0430\u0447\u0435\u0441\u0442\u0432\u0435\u043d\u043d\u044b\u0445 \u043e\u043f\u0443\u0445\u043e\u043b\u0435\u0439 \u0443 \u043c\u0443\u0436\u0447\u0438\u043d \u043a\u043e\u0442\u043e\u0440\u044b\u0439 \u0440\u0430\u0437\u0432\u0438\u0432\u0430\u0435\u0442\u0441\u044f \u0438\u0437 \u043a\u043b\u0435\u0442\u043e\u043a \u043f\u0440\u0435\u0434\u0441\u0442\u0430\u0442\u0435\u043b\u044c\u043d\u043e\u0439 \u0436\u0435\u043b\u0435\u0437\u044b. \u0417\u0430\u0433\u0440\u0443\u0437\u0438\u043c \u043d\u0435\u043e\u0431\u0445\u043e\u0434\u0438\u043c\u044b\u0435 \u0431\u0438\u0431\u043b\u0438\u043e\u0442\u0435\u043a\u0438 \u0438 \u0438\u0441\u043f\u043e\u043b\u044c\u0437\u0443\u0435\u043c \u043f\u0440\u044f\u043c\u0443\u044e \u0437\u0430\u0433\u0440\u0443\u0437\u043a\u0443 \u0432\u0441\u0435\u0445 \u043d\u0435\u043e\u0431\u0445\u043e\u0434\u0438\u043c\u044b\u0445 \u0434\u0430\u043d\u043d\u044b\u0445 \u0434\u043b\u044f \u0437\u0430\u0434\u0430\u0447\u0438 \u043d\u0430\u043f\u0440\u044f\u043c\u0443\u044e \u0441 kaggle \u041a\u043b\u0430\u0441\u0441 \u043a\u043e\u043d\u0444\u0438\u0433\u0443\u0440\u0430\u0442\u043e\u0440\u0421\u043e\u0437\u0434\u0430\u0434\u0438\u043c \u043e\u0442\u0434\u0435\u043b\u044c\u043d\u044b\u0439 \u043a\u043b\u0430\u0441\u0441 config \u043a\u043e\u0442\u043e\u0440\u044b\u0439 \u0437\u0430\u0434\u0430\u0435\u0442 \u043f\u0430\u0440\u0430\u043c\u0435\u0442\u0440\u044b \u0434\u043b\u044f 1 device \u0432\u0438\u0440\u0442\u0443\u0430\u043b\u044c\u043d\u043e\u0435 \u0443\u0441\u0442\u0440\u043e\u0439\u0441\u0442\u0432\u043e \u0438\u0437 \u0438\u043d\u0444\u0440\u0430\u0441\u0442\u0440\u0443\u043a\u0442\u0443\u0440\u044b kaggle \u0447\u0442\u043e\u0431\u044b \u0438\u0441\u043f\u043e\u043b\u044c\u0437\u043e\u0432\u0430\u0442\u044c \u044d\u0442\u043e \u0443\u0441\u0442\u0440\u043e\u0439\u0441\u0442\u0432\u043e \u0432 \u043a\u0430\u0447\u0435\u0441\u0442\u0432\u0435 \u0438\u0441\u043f\u043e\u043b\u043d\u044f\u0435\u043c\u043e\u0433\u043e 2 \u0448\u0438\u0440\u0438\u043d\u044b \u0438 \u0432\u044b\u0441\u043e\u0442\u044b \u0438\u0437\u043e\u0431\u0440\u0430\u0436\u0435\u043d\u0438\u044f3 \u043a\u043e\u043b\u0438\u0447\u0435\u0441\u0442\u0432\u043e \u0444\u0440\u0430\u0433\u043c\u0435\u043d\u0442\u043e\u0432 \u0438\u0437\u043e\u0431\u0440\u0430\u0436\u0435\u043d\u0438\u044f4 \u043a\u043e\u043b\u0438\u0447\u0435\u0441\u0442\u0432\u043e \u0444\u0438\u0447 \u043f\u043e\u043b\u0443\u0447\u0430\u0435\u043c\u044b\u0445 \u043d\u0430 \u0432\u044b\u0445\u043e\u0434\u0435 \u043f\u043e\u0441\u043b\u0435 \u0441\u0432\u0435\u0440\u0442\u043a\u0438 \u043a\u0430\u0436\u0434\u043e\u0433\u043e \u0441\u043b\u043e\u044f 6 5 \u0440\u0435\u0436\u0438\u043c \u0434\u0435\u0431\u0430\u0433\u0430 \u0434\u043b\u044f \u043f\u0440\u043e\u0432\u0435\u0434\u0435\u043d\u0438\u044f \u043e\u0442\u043b\u0430\u0434\u043a\u0438 \u041f\u043e\u0441\u043c\u043e\u0442\u0440\u0438\u043c \u043d\u0430 \u043e\u0441\u043d\u043e\u0432\u043d\u043e\u0439 \u0434\u0430\u0442\u0430\u0441\u0435\u0442 train. com c prostate cancer grade assessment overview additional resources \u041e\u0441\u043e\u0431\u0435\u043d\u043d\u043e\u0441\u0442\u0438 \u0434\u0430\u043d\u043d\u044b\u0445 \u043f\u0440\u0438\u0441\u0432\u043e\u0435\u043d\u0438\u0435 \u0431\u0430\u043b\u043b\u043e\u0432 \u043f\u043e \u0448\u043a\u0430\u043b\u0435 \u0413\u043b\u0438\u0441\u043e\u043d. \u0414\u0438\u0430\u0433\u043d\u043e\u0441\u0442\u0438\u043a\u0430 \u0438 \u0441\u0442\u0430\u0434\u0438\u0438 \u0440\u0430\u043a\u0430 \u043f\u0440\u043e\u0441\u0442\u0430\u0442\u044b\u0414\u043b\u044f \u0442\u043e\u0433\u043e \u0447\u0442\u043e\u0431\u044b \u0443\u0441\u0442\u0430\u043d\u043e\u0432\u0438\u0442\u044c \u043d\u0430\u043b\u0438\u0447\u0438\u0435 \u0440\u0430\u043a\u0430 \u043f\u0440\u043e\u0441\u0442\u0430\u0442\u044b \u0438 \u043e\u043f\u0440\u0435\u0434\u0435\u043b\u0438\u0442\u044c \u0435\u0433\u043e \u0441\u0442\u0430\u0434\u0438\u044e \u043f\u0430\u0446\u0438\u0435\u043d\u0442\u0443 \u043d\u0435\u043e\u0431\u0445\u043e\u0434\u0438\u043c\u043e \u043f\u0440\u043e\u0432\u0435\u0441\u0442\u0438 \u0434\u0438\u0430\u0433\u043d\u043e\u0441\u0442\u0438\u043a\u0443 \u0432\u043a\u043b\u044e\u0447\u0430\u044e\u0449\u0443\u044e \u0432 \u0441\u0435\u0431\u044f \u0441\u0434\u0430\u0447\u0443 \u043a\u0440\u043e\u0432\u0438 \u0438\u0437 \u0432\u0435\u043d\u044b \u043d\u0430 \u041f\u0421\u0410 \u043f\u0440\u043e\u0441\u0442\u0430\u0442\u043e \u0441\u043f\u0435\u0446\u0438\u0444\u0438\u0447\u0435\u0441\u043a\u0438\u0439 \u0430\u043d\u0442\u0438\u0433\u0435\u043d \u0430 \u0435\u0441\u043b\u0438 \u043d\u0435\u0433\u0430\u0442\u0438\u0432\u043d\u044b\u0435 \u0440\u0435\u0437\u0443\u043b\u044c\u0442\u044b \u0432 \u0430\u043d\u0430\u043b\u0438\u0437\u0430\u0445 \u043f\u043e\u0434\u0442\u0432\u0435\u0440\u0436\u0434\u0430\u044e\u0442\u0441\u044f \u0434\u0430\u043b\u0435\u0435 \u043f\u0440\u043e\u0432\u043e\u0434\u0438\u0442\u0441\u044f \u0423\u0417\u0418 \u0423\u043b\u044c\u0442\u0440\u0430\u0437\u0432\u0443\u043a\u043e\u0432\u043e\u0435 \u0438\u0441\u0441\u043b\u0435\u0434\u043e\u0432\u0430\u043d\u0438\u0435 \u043f\u0440\u043e\u0441\u0442\u0430\u0442\u044b \u0411\u0418\u041e\u041f\u0421\u0418\u042f \u0437\u0430\u0431\u043e\u0440\u0430 \u0442\u043a\u0430\u043d\u0435\u0439 \u043f\u0440\u043e\u0441\u0442\u0430\u0442\u044b\u0411\u0438\u043e\u043f\u0441\u0438\u044f \u043f\u0440\u043e\u0432\u043e\u0434\u0438\u0442\u0441\u044f \u043f\u043e \u043f\u043e\u043a\u0430\u0437\u0430\u043d\u0438\u044f\u043c \u043f\u043e\u0441\u043b\u0435 \u041f\u0421\u0410 \u0438 \u0423\u0417\u0418. \u041f\u043e\u044d\u0442\u043e\u043c\u0443 \u043a\u043e\u0433\u0434\u0430 \u0432\u044b \u043f\u044b\u0442\u0430\u0435\u0442\u0435\u0441\u044c \u0432\u0438\u0437\u0443\u0430\u043b\u0438\u0437\u0438\u0440\u043e\u0432\u0430\u0442\u044c \u043c\u0430\u0441\u043a\u0443 \u043e\u043d\u0430 \u0431\u0443\u0434\u0435\u0442 \u043a\u0430\u0437\u0430\u0442\u044c\u0441\u044f \u043e\u0447\u0435\u043d\u044c \u0442\u0435\u043c\u043d\u043e\u0439 \u043f\u043e\u0441\u043a\u043e\u043b\u044c\u043a\u0443 \u043a\u0430\u0436\u0434\u043e\u0435 \u0437\u043d\u0430\u0447\u0435\u043d\u0438\u0435 \u0431\u043b\u0438\u0437\u043a\u043e \u043a 0. \u042d\u0442\u0438 \u043c\u0430\u0441\u043a\u0438 \u043f\u0440\u0435\u0434\u043d\u0430\u0437\u043d\u0430\u0447\u0435\u043d\u044b \u0434\u043b\u044f \u043f\u043e\u043c\u043e\u0449\u0438 \u0432 \u0440\u0430\u0437\u0440\u0430\u0431\u043e\u0442\u043a\u0435 \u0441\u0442\u0440\u0430\u0442\u0435\u0433\u0438\u0439 \u0434\u043b\u044f \u0432\u044b\u0431\u043e\u0440\u0430 \u043d\u0430\u0438\u0431\u043e\u043b\u0435\u0435 \u043f\u043e\u043b\u0435\u0437\u043d\u044b\u0445 \u043f\u043e\u0434\u0432\u044b\u0431\u043e\u0440\u043e\u043a \u0438\u0437\u043e\u0431\u0440\u0430\u0436\u0435\u043d\u0438\u0439. \u0421\u0441\u044b\u043b\u043a\u0438 \u043d\u0430 \u0441\u0442\u0430\u0442\u044c\u0438 \u0438 \u0440\u0435\u043f\u043e\u0437\u0438\u0442\u043e\u0440\u0438\u0439 https habr. loc image data_provider karolinska ax 0. input_range settings input_range model. \u0411\u0430\u0437\u0430 \u0434\u0430\u043d\u043d\u044b\u0445 \u0441 \u0430\u043d\u043d\u043e\u0442\u0430\u0446\u0438\u0435\u0439 \u0438 URL \u0438\u0437\u043e\u0431\u0440\u0430\u0436\u0435\u043d\u0438\u0439 \u043e\u0442 \u0442\u0440\u0435\u0442\u044c\u0438\u0445 \u043b\u0438\u0446 \u0434\u043e\u0441\u0442\u0443\u043f\u043d\u0430 \u043d\u0435\u043f\u043e\u0441\u0440\u0435\u0434\u0441\u0442\u0432\u0435\u043d\u043d\u043e \u0447\u0435\u0440\u0435\u0437 ImageNet \u043d\u043e \u043f\u0440\u0438 \u044d\u0442\u043e\u043c \u0441\u0430\u043c\u0438 \u0438\u0437\u043e\u0431\u0440\u0430\u0436\u0435\u043d\u0438\u044f \u043d\u0435 \u043f\u0440\u0438\u043d\u0430\u0434\u043b\u0435\u0436\u0430\u0442 \u043f\u0440\u043e\u0435\u043a\u0442\u0443. load_state_dict model_zoo. \u0418\u0437\u043e\u0431\u0440\u0430\u0436\u0435\u043d\u0438\u044f \u043d\u0430\u0437\u044b\u0432\u0430\u044e\u0442 \u0446\u0438\u0444\u0440\u043e\u0432\u043e\u0439 \u043f\u0430\u0442\u043e\u043b\u043e\u0433\u0438\u0435\u0439. \u0412 \u0434\u0430\u043d\u043d\u043e\u043c \u0444\u0430\u0439\u043b\u0435 \u0434\u043e\u0441\u0442\u0443\u043f\u043d\u0430 \u0438\u043d\u0444\u043e\u0440\u043c\u0430\u0446\u0438\u044f \u043f\u043e \u043d\u0430\u0438\u043c\u0435\u043d\u043e\u0432\u0430\u043d\u0438\u044e \u0438\u0437\u043e\u0431\u0440\u0430\u0436\u0435\u043d\u0438\u044f \u0431\u0438\u043e\u043f\u0441\u0438\u0438 \u043e\u0446\u0435\u043d\u043a\u0435 \u043f\u043e \u0448\u043a\u0430\u043b\u0435 \u0413\u043b\u0438\u0441\u043e\u043d \u0438 \u0441\u0442\u0430\u0434\u0438\u0438 \u0440\u0430\u043a\u0430 \u043f\u043e ISUP. \u0412 \u043d\u0430\u0448\u0435\u043c \u0434\u0430\u0442\u0430\u0441\u0435\u0442\u0435 \u0443\u0447\u0442\u0435\u043d\u044b \u043d\u0435\u043a\u043e\u0442\u043e\u0440\u044b\u0435 \u043e\u0441\u043e\u0431\u0435\u043d\u043d\u043e\u0441\u0442\u0438 \u043e\u0446\u0435\u043d\u043a\u0438 \u043f\u043e \u0448\u043a\u0430\u043b\u0435 \u0413\u043b\u0438\u0441\u043e\u043d \u043f\u043e \u0434\u043e\u043c\u0438\u043d\u0438\u0440\u0443\u044e\u0449\u0435\u043c\u0443 \u0438 \u0432\u0442\u043e\u0440\u0438\u0447\u043d\u043e\u043c\u0443 \u0442\u0438\u043f\u0443 \u043e\u043f\u0443\u0445\u043e\u043b\u0435\u0439 \u0434\u0432\u0430 \u0444\u0440\u0430\u0433\u043c\u0435\u043d\u0442\u0430 \u0441 \u0431\u0438\u043e\u043f\u0441\u0438\u0438 1. AdaptiveAvgPool2d 1 self. fc2 x x self. downsample x out self. load_url settings url model. py\u0421\u043e\u0437\u0434\u0430\u0434\u0438\u043c \u043e\u0442\u0434\u0435\u043b\u044c\u043d\u044b\u0435 \u043a\u043b\u0430\u0441\u0441\u044b EfficientNet \u0432 \u043a\u043e\u0442\u043e\u0440\u044b\u0445 \u0431\u0443\u0434\u0435\u043c \u043e\u0431\u0440\u0430\u0449\u0430\u0442\u044c\u0441\u044f \u043f\u043e \u0441\u0441\u044b\u043b\u043a\u0430\u043c \u043a \u043f\u0440\u0438\u043b\u043e\u0436\u0435\u043d\u043d\u044b\u043c \u043f\u0440\u0435\u0434\u043e\u0431\u0443\u0447\u0435\u043d\u043d\u044b\u043c \u044d\u043a\u0437\u0435\u043c\u043f\u043b\u044f\u0440\u0430\u043c \u043c\u043e\u0434\u0435\u043b\u0435\u0439 \u0434\u0430\u043d\u043d\u043e\u0439 \u0442\u0440\u0430\u043d\u0441\u0444\u0435\u0440\u043d\u043e\u0439 \u0441\u0435\u0442\u0438. expansion 4 def __init__ self inplanes planes groups reduction stride 1 downsample None super SEBottleneck self. pth ensemble_weight 1 model CustomSEResNeXt model_name ensemble model_name model. \u0412\u044b\u0432\u043e\u0434\u0438\u043c \u0438\u0437\u043e\u0431\u0440\u0430\u0436\u0435\u043d\u0438\u044f \u043d\u0430 \u044d\u043a\u0440\u0430\u043d \u043f\u043e\u0434\u043f\u0438\u0441\u044b\u0432\u0430\u0435\u043c \u0441\u0432\u043e\u0438 \u0438\u0437\u043e\u0431\u0440\u0430\u0436\u0435\u043d\u0438\u044f Here we compute the pixel spacing the physical size of a pixel in the image. \u0417\u0430\u0433\u0440\u0443\u0437\u0438\u043c \u0442\u0430\u043a\u0436\u0435 \u0432\u0441\u0435 \u043e\u0441\u0442\u0430\u043b\u044c\u043d\u044b\u0435 \u0441\u0442\u0430\u0434\u0438\u0438 \u0440\u0430\u043a\u0430 \u041a\u0430\u0436\u0434\u044b\u0439 \u0441\u043b\u0430\u0439\u0434 \u0438\u043c\u0435\u0435\u0442 3 \u0441\u043b\u043e\u044f \u043a\u043e\u0442\u043e\u0440\u044b\u0435 \u0432\u044b \u043c\u043e\u0436\u0435\u0442\u0435 \u0437\u0430\u0433\u0440\u0443\u0437\u0438\u0442\u044c \u0447\u0442\u043e \u0441\u043e\u043e\u0442\u0432\u0435\u0442\u0441\u0442\u0432\u0443\u0435\u0442 \u043f\u043e\u043d\u0438\u0436\u0435\u043d\u0438\u044e \u0434\u0438\u0441\u043a\u0440\u0435\u0442\u0438\u0437\u0430\u0446\u0438\u0438 \u043d\u0430 1 4 \u0438 16. \u0427\u0442\u043e \u0442\u0430\u043a\u043e\u0435 \u043f\u043e\u043d\u0438\u0436\u0430\u044e\u0449\u0430\u044f Downsampling \u0438 \u043f\u043e\u0432\u044b\u0448\u0430\u044e\u0449\u0430\u044f Upsampling \u0434\u0438\u0441\u043a\u0440\u0435\u0442\u0438\u0437\u0430\u0446\u0438\u044f \u043f\u0440\u0438 \u043e\u0431\u0440\u0430\u0431\u043e\u0442\u043a\u0435 \u0438\u0437\u043e\u0431\u0440\u0430\u0436\u0435\u043d\u0438\u0439 \u041f\u043e\u043d\u0438\u0436\u0435\u043d\u0438\u0435 \u0447\u0430\u0441\u0442\u043e\u0442\u044b \u0434\u0438\u0441\u043a\u0440\u0435\u0442\u0438\u0437\u0430\u0446\u0438\u0438 \u0438 \u043f\u043e\u0432\u044b\u0448\u0435\u043d\u0438\u0435 \u0447\u0430\u0441\u0442\u043e\u0442\u044b \u0434\u0438\u0441\u043a\u0440\u0435\u0442\u0438\u0437\u0430\u0446\u0438\u0438 \u0434\u0432\u0435 \u0444\u0443\u043d\u0434\u0430\u043c\u0435\u043d\u0442\u0430\u043b\u044c\u043d\u044b\u0435 \u0438 \u0448\u0438\u0440\u043e\u043a\u043e \u0438\u0441\u043f\u043e\u043b\u044c\u0437\u0443\u0435\u043c\u044b\u0435 \u043e\u043f\u0435\u0440\u0430\u0446\u0438\u0438 \u0441 \u0438\u0437\u043e\u0431\u0440\u0430\u0436\u0435\u043d\u0438\u044f\u043c\u0438. Conv2d planes 4 planes 4 kernel_size 1 bias False self. \u0410\u0432\u0442\u043e\u0440\u044b \u0441\u0442\u0430\u0442\u044c\u0438 \u043f\u0440\u0435\u0434\u043b\u0430\u0433\u0430\u044e\u0442 \u043d\u043e\u0432\u044b\u0439 \u043c\u0435\u0442\u043e\u0434 \u0441\u043e\u0441\u0442\u0430\u0432\u043d\u043e\u0433\u043e \u043c\u0430\u0441\u0448\u0442\u0430\u0431\u0438\u0440\u043e\u0432\u0430\u043d\u0438\u044f compound scaling method \u043a\u043e\u0442\u043e\u0440\u044b\u0439 \u0440\u0430\u0432\u043d\u043e\u043c\u0435\u0440\u043d\u043e \u043c\u0430\u0441\u0448\u0442\u0430\u0431\u0438\u0440\u0443\u0435\u0442 \u0433\u043b\u0443\u0431\u0438\u043d\u0443 \u0448\u0438\u0440\u0438\u043d\u0443 \u0440\u0430\u0437\u0440\u0435\u0448\u0435\u043d\u0438\u0435 \u0441 \u0444\u0438\u043a\u0441\u0438\u0440\u043e\u0432\u0430\u043d\u043d\u044b\u043c\u0438 \u043f\u0440\u043e\u043f\u043e\u0440\u0446\u0438\u044f\u043c\u0438 \u043c\u0435\u0436\u0434\u0443 \u043d\u0438\u043c\u0438. \u0426\u0438\u0442\u043e\u043f\u043b\u0430\u0437\u043c\u0430 \u0431\u043b\u0435\u0434\u043d\u0430\u044f \u044f\u0434\u0440\u0430 \u043c\u0430\u043b\u0435\u043d\u044c\u043a\u0438\u0435 \u0438 \u043f\u0440\u0430\u0432\u0438\u043b\u044c\u043d\u044b\u0435. org api python \u044f\u0432\u043b\u044f\u0435\u0442\u0441\u044f \u043e\u0447\u0435\u043d\u044c \u0443\u0434\u043e\u0431\u043d\u044b\u043c \u0438\u043d\u0441\u0442\u0440\u0443\u043c\u0435\u043d\u0442\u043e\u043c \u0434\u043b\u044f \u0440\u0430\u0431\u043e\u0442\u044b \u0441 \u0442\u0430\u043a\u0438\u043c\u0438 \u0438\u0437\u043e\u0431\u0440\u0430\u0436\u0435\u043d\u0438\u044f\u043c\u0438 \u041f\u0440\u0435\u0438\u043c\u0443\u0449\u0435\u0441\u0442\u0432\u043e OpenSlide \u0432 \u0442\u043e\u043c \u0447\u0442\u043e \u043c\u044b \u043c\u043e\u0436\u0435\u043c \u0437\u0430\u0433\u0440\u0443\u0436\u0430\u0442\u044c \u043f\u0440\u043e\u0438\u0437\u0432\u043e\u043b\u044c\u043d\u044b\u0435 \u043e\u0431\u043b\u0430\u0441\u0442\u0438 \u0441\u043b\u0430\u0439\u0434\u0430 \u043d\u0435 \u0437\u0430\u0433\u0440\u0443\u0436\u0430\u044f \u0432 \u043f\u0430\u043c\u044f\u0442\u044c \u0432\u0441\u0435 \u0438\u0437\u043e\u0431\u0440\u0430\u0436\u0435\u043d\u0438\u0435. \u041c\u0430\u0441\u043a\u0438 \u043d\u0435 \u044f\u0432\u043b\u044f\u044e\u0442\u0441\u044f \u0434\u0430\u043d\u043d\u044b\u043c\u0438 \u0438\u0437\u043e\u0431\u0440\u0430\u0436\u0435\u043d\u0438\u044f \u043a\u0430\u043a WSI. \u041e\u043f\u0440\u0435\u0434\u0435\u043b\u0435\u043d\u0438\u0435 \u0441\u0442\u0430\u0434\u0438\u0438 \u0440\u0430\u043a\u0430 \u043f\u0440\u043e\u0441\u0442\u0430\u0442\u044b \u043f\u043e \u0446\u0438\u0444\u0440\u043e\u0432\u043e\u0439 \u043f\u0430\u0442\u043e\u043b\u043e\u0433\u0438\u0438 \u0431\u0438\u043e\u043f\u0441\u0438\u0438. \u0411\u0430\u0437\u0430 \u0434\u0430\u043d\u043d\u044b\u0445 ImageNet \u043f\u0440\u043e\u0435\u043a\u0442 \u043f\u043e \u0441\u043e\u0437\u0434\u0430\u043d\u0438\u044e \u0438 \u0441\u043e\u043f\u0440\u043e\u0432\u043e\u0436\u0434\u0435\u043d\u0438\u044e \u043c\u0430\u0441\u0441\u0438\u0432\u043d\u043e\u0439 \u0431\u0430\u0437\u044b \u0434\u0430\u043d\u043d\u044b\u0445 \u0430\u043d\u043d\u043e\u0442\u0438\u0440\u043e\u0432\u0430\u043d\u043d\u044b\u0445 \u0438\u0437\u043e\u0431\u0440\u0430\u0436\u0435\u043d\u0438\u0439 \u043f\u0440\u0435\u0434\u043d\u0430\u0437\u043d\u0430\u0447\u0435\u043d\u043d\u0430\u044f \u0434\u043b\u044f \u043e\u0442\u0440\u0430\u0431\u043e\u0442\u043a\u0438 \u0438 \u0442\u0435\u0441\u0442\u0438\u0440\u043e\u0432\u0430\u043d\u0438\u044f \u043c\u0435\u0442\u043e\u0434\u043e\u0432 \u0440\u0430\u0441\u043f\u043e\u0437\u043d\u0430\u0432\u0430\u043d\u0438\u044f \u043e\u0431\u0440\u0430\u0437\u043e\u0432 \u0438 \u043c\u0430\u0448\u0438\u043d\u043d\u043e\u0433\u043e \u0437\u0440\u0435\u043d\u0438\u044f. \u0422\u043a\u0430\u043d\u044c \u043f\u0440\u043e\u0441\u0442\u0430\u0442\u044b \u043f\u0440\u0435\u0438\u043c\u0443\u0449\u0435\u0441\u0442\u0432\u0435\u043d\u043d\u043e \u0441\u043e\u0441\u0442\u043e\u0438\u0442 \u0438\u0437 \u043c\u044b\u0448\u0435\u0447\u043d\u044b\u0445 \u0438 \u0436\u0435\u043b\u0435\u0437\u0438\u0441\u0442\u044b\u0445 \u043a\u043b\u0435\u0442\u043e\u043a \u0430 \u0442\u0430\u043a\u0436\u0435 \u0438\u0437 \u0441\u043e\u0435\u0434\u0438\u043d\u0438\u0442\u0435\u043b\u044c\u043d\u043e\u0439 \u0442\u043a\u0430\u043d\u0438. Conv2d inplanes width kernel_size 1 bias False stride 1 self. \u041e\u0431\u044b\u0447\u043d\u043e \u043e\u043d\u0430 \u0438\u0441\u043f\u043e\u043b\u044c\u0437\u0443\u0435\u0442\u0441\u044f \u0434\u043b\u044f \u0443\u0432\u0435\u043b\u0438\u0447\u0435\u043d\u0438\u044f \u043d\u0435\u0431\u043e\u043b\u044c\u0448\u043e\u0439 \u043e\u0431\u043b\u0430\u0441\u0442\u0438 \u0438\u0437\u043e\u0431\u0440\u0430\u0436\u0435\u043d\u0438\u044f \u0438 \u0434\u043b\u044f \u0443\u0441\u0442\u0440\u0430\u043d\u0435\u043d\u0438\u044f \u044d\u0444\u0444\u0435\u043a\u0442\u0430 \u043f\u0438\u043a\u0441\u0435\u043b\u0438\u0437\u0430\u0446\u0438\u0438 \u043a\u043e\u0442\u043e\u0440\u044b\u0439 \u0432\u043e\u0437\u043d\u0438\u043a\u0430\u0435\u0442 \u043a\u043e\u0433\u0434\u0430 \u0438\u0437\u043e\u0431\u0440\u0430\u0436\u0435\u043d\u0438\u0435 \u0441 \u043d\u0438\u0437\u043a\u0438\u043c \u0440\u0430\u0437\u0440\u0435\u0448\u0435\u043d\u0438\u0435\u043c \u043e\u0442\u043e\u0431\u0440\u0430\u0436\u0430\u0435\u0442\u0441\u044f \u043d\u0430 \u043e\u0442\u043d\u043e\u0441\u0438\u0442\u0435\u043b\u044c\u043d\u043e \u0431\u043e\u043b\u044c\u0448\u043e\u043c \u043a\u0430\u0434\u0440\u0435. BatchNorm2d planes 4 self. \u0421 2010 \u0433\u043e\u0434\u0430 \u0432\u0435\u0434\u0451\u0442\u0441\u044f \u043f\u0440\u043e\u0435\u043a\u0442 ILSVRC \u0430\u043d\u0433\u043b. \u041f\u043e \u0441\u043e\u0441\u0442\u043e\u044f\u043d\u0438\u044e \u043d\u0430 2016 \u0433\u043e\u0434 \u0432 \u0431\u0430\u0437\u0443 \u0434\u0430\u043d\u043d\u044b\u0445 \u0431\u044b\u043b\u043e \u0437\u0430\u043f\u0438\u0441\u0430\u043d\u043e \u043e\u043a\u043e\u043b\u043e \u0434\u0435\u0441\u044f\u0442\u0438 \u043c\u0438\u043b\u043b\u0438\u043e\u043d\u043e\u0432 URL \u0441 \u0438\u0437\u043e\u0431\u0440\u0430\u0436\u0435\u043d\u0438\u044f\u043c\u0438 \u043a\u043e\u0442\u043e\u0440\u044b\u0435 \u043f\u0440\u043e\u0448\u043b\u0438 \u0440\u0443\u0447\u043d\u0443\u044e \u0430\u043d\u043d\u043e\u0442\u0430\u0446\u0438\u044e \u0434\u043b\u044f ImageNet \u0432 \u0430\u043d\u043d\u043e\u0442\u0430\u0446\u0438\u044f\u0445 \u043f\u0435\u0440\u0435\u0447\u0438\u0441\u043b\u044f\u043b\u0438\u0441\u044c \u043e\u0431\u044a\u0435\u043a\u0442\u044b \u043f\u043e\u043f\u0430\u0432\u0448\u0438\u0435 \u043d\u0430 \u0438\u0437\u043e\u0431\u0440\u0430\u0436\u0435\u043d\u0438\u0435 \u0438 \u043f\u0440\u044f\u043c\u043e\u0443\u0433\u043e\u043b\u044c\u043d\u0438\u043a\u0438 \u0441 \u0438\u0445 \u043a\u043e\u043e\u0440\u0434\u0438\u043d\u0430\u0442\u0430\u043c\u0438. \u0410\u0434\u0435\u043d\u043e\u043a\u0430\u0440\u0446\u0438\u043d\u043e\u043c\u0430 \u043f\u0440\u0435\u0434\u0441\u0442\u0430\u0442\u0435\u043b\u044c\u043d\u043e\u0439 \u0436\u0435\u043b\u0435\u0437\u044b 4 \u0431\u0430\u043b\u043b\u0430 \u043f\u043e \u0448\u043a\u0430\u043b\u0435 \u0413\u043b\u0438\u0441\u043e\u043d\u0430. BatchNorm2d width self. \u041a\u0430\u0436\u0434\u043e\u0435 \u0438\u043c\u0435\u0435\u0442 \u0440\u0430\u0441\u0448\u0438\u0440\u0435\u043d\u0438\u0435 tiff file. \u0421\u043e\u043e\u0442\u0432\u0435\u0442\u0441\u0442\u0432\u0435\u043d\u043d\u043e \u043e\u0446\u0435\u043d\u043a\u0438 \u043f\u043e ISUP \u043c\u043e\u0433\u0443\u0442 \u0432\u0430\u0440\u044c\u0438\u0440\u043e\u0432\u0430\u0442\u044c\u0441\u044f \u043e\u0442 6 3 3 1 \u0441\u0442\u0430\u0434\u0438\u044f \u0440\u0430\u043a\u0430 \u0434\u043e 10 5 5 5 \u0441\u0442\u0430\u0434\u0438\u044f \u0440\u0430\u043a\u0430. com c prostate cancer grade assessment overview additional resources. \u041f\u043e\u0434\u0440\u043e\u0431\u043d\u043e\u0435 \u043e\u043f\u0438\u0441\u0430\u043d\u0438\u0435 \u043f\u043e \u0441\u0441\u044b\u043b\u043a\u0435 https www. BatchNorm2d 64 relu2 nn. \u042d\u0442\u043e \u0441\u044f\u0437\u0430\u043d\u043e \u0441 \u043b\u0430\u0431\u043e\u0440\u0430\u0442\u043e\u0440\u043d\u044b\u043c\u0438 \u043f\u0440\u043e\u0446\u0435\u0434\u0443\u0440\u0430\u043c\u0438. \u0421\u0438\u0441\u0442\u0435\u043c\u0430 \u0434\u0438\u0430\u0433\u043d\u043e\u0441\u0442\u0438\u0440\u043e\u0432\u0430\u043d\u0438\u044f \u0440\u0430\u043a\u0430 \u043f\u043e \u0444\u043e\u0442\u043e\u0441\u043d\u0438\u043c\u043a\u0430\u043c \u043d\u0430 \u043e\u0441\u043d\u043e\u0432\u0435 \u043e\u0431\u0443\u0447\u0435\u043d\u043d\u043e\u0439 \u043d\u0435\u0439\u0440\u043e\u0441\u0435\u0442\u0438 \u0432 \u043d\u0435\u043a\u043e\u0442\u043e\u0440\u044b\u0445 \u0441\u043b\u0443\u0447\u0430\u044f\u0445 \u043f\u043e\u043a\u0430\u0437\u0430\u043b\u0430 \u043b\u0443\u0447\u0448\u0438\u0435 \u0440\u0435\u0437\u0443\u043b\u044c\u0442\u0430\u0442\u044b \u043f\u043e \u0441\u0440\u0430\u0432\u043d\u0435\u043d\u0438\u044e \u0441 \u0442\u0440\u0430\u0434\u0438\u0446\u0438\u043e\u043d\u043d\u044b\u043c\u0438 \u0441\u043f\u043e\u0441\u043e\u0431\u0430\u043c\u0438 \u0434\u0438\u0430\u0433\u043d\u043e\u0441\u0442\u0438\u043a\u0438 \u0441\u043e\u043e\u0431\u0449\u0438\u043b\u0430 \u043f\u0440\u0435\u0441\u0441 \u0441\u043b\u0443\u0436\u0431\u0430 \u041c\u0413\u0423 \u0438\u043c\u0435\u043d\u0438 \u041b\u043e\u043c\u043e\u043d\u043e\u0441\u043e\u0432\u0430 28 \u0438\u044e\u043b\u044f \u0441\u043e \u0441\u0441\u044b\u043b\u043a\u043e\u0439 \u043d\u0430 \u0441\u0442\u0430\u0442\u044c\u044e \u0432 \u043d\u0430\u0443\u0447\u043d\u043e\u043c \u0436\u0443\u0440\u043d\u0430\u043b\u0435 Nature Cancer. features x x self. \u041f\u0440\u0435\u0434\u043b\u043e\u0436\u0435\u043d\u043d\u044b\u0439 \u043d\u0430\u043c\u0438 \u043c\u0435\u0442\u043e\u0434 \u043f\u043e\u043a\u0430\u0437\u044b\u0432\u0430\u0435\u0442 \u0447\u0442\u043e \u043a\u043e\u043c\u043f\u044c\u044e\u0442\u0435\u0440\u043d\u043e\u0435 \u0437\u0440\u0435\u043d\u0438\u0435 \u043d\u0430\u0440\u044f\u0434\u0443 \u0441 \u043c\u043e\u043b\u0435\u043a\u0443\u043b\u044f\u0440\u043d\u044b\u043c \u043f\u0440\u043e\u0444\u0438\u043b\u0438\u0440\u043e\u0432\u0430\u043d\u0438\u0435\u043c \u043c\u043e\u0436\u043d\u043e \u0438\u0441\u043f\u043e\u043b\u044c\u0437\u043e\u0432\u0430\u0442\u044c \u043f\u0440\u0438 \u0434\u0438\u0430\u0433\u043d\u043e\u0441\u0442\u0438\u043a\u0435 \u0440\u0430\u043a\u0430. \u0428\u0430\u0431\u043b\u043e\u043d \u0413\u043b\u0438\u0441\u043e\u043d\u0430 5 \u0431\u0430\u043b\u043b\u043e\u0432 \u043c\u043e\u0436\u0435\u0442 \u0442\u0430\u043a\u0436\u0435 \u0441\u043e\u0434\u0435\u0440\u0436\u0430\u0442\u044c \u0442\u0432\u0435\u0440\u0434\u044b\u0435 \u043b\u0438\u0441\u0442\u044b \u0438\u043b\u0438 \u043d\u0438\u0442\u0438 \u0440\u0430\u043a\u043e\u0432\u044b\u0445 \u043a\u043b\u0435\u0442\u043e\u043a. expansion num_classes def _make_layer self block planes blocks groups reduction stride 1 downsample_kernel_size 1 downsample_padding 0 downsample None if stride 1 or self. \u0418\u0441\u043f\u043e\u043b\u044c\u0437\u0443\u0435\u043c \u0441\u0430\u043c\u0443\u044e \u0440\u0430\u0441\u043f\u0440\u043e\u0441\u0442\u0440\u0430\u043d\u0435\u043d\u043d\u0443\u044e \u0431\u0430\u0437\u043e\u0432\u0443\u044e \u043c\u0435\u0442\u0440\u0438\u043a\u0443 \u043a\u043b\u0430\u0441\u0441\u0438\u0444\u0438\u043a\u0430\u0446\u0438\u0438 Accuracy Metric \u0442\u0430\u043a \u043a\u0430\u043a \u043e\u043d\u0430 \u0438\u043d\u0442\u0443\u0438\u0442\u0438\u0432\u043d\u043e \u043f\u043e\u043d\u044f\u0442\u043d\u0430 \u0438 \u043e\u0447\u0435\u0432\u0438\u0434\u043d\u0430 \u0434\u043e\u043b\u044f \u043f\u0440\u0430\u0432\u0438\u043b\u044c\u043d\u044b\u0445 \u043e\u0442\u0432\u0435\u0442\u043e\u0432 \u0441\u043e\u0437\u0434\u0430\u043d\u043d\u043e\u0433\u043e \u043d\u0430\u043c\u0438 \u0430\u043b\u0433\u043e\u0440\u0438\u0442\u043c\u0430. conv1 x out self. layer3 x x self. csv \u0432\u0441\u0435\u0433\u043e 10616 \u043f\u0430\u0446\u0438\u0435\u043d\u0442\u043e\u0432 \u043f\u0443\u0441\u0442\u044b\u0435 \u0437\u043d\u0430\u0447\u0435\u043d\u0438\u044f \u043e\u0442\u0441\u0443\u0442\u0441\u0442\u0432\u0443\u044e\u0442 \u0434\u0443\u0431\u043b\u0438\u0440\u043e\u0432\u0430\u043d\u043d\u044b\u0435 \u0437\u0430\u043f\u0438\u0441\u0438 \u043f\u043e \u043f\u0430\u0446\u0438\u0435\u043d\u0442\u0430\u043c \u043e\u0442\u0441\u0443\u0442\u0441\u0442\u0432\u0443\u044e\u0442 \u0443 \u043a\u0430\u0436\u0434\u043e\u0433\u043e \u0441\u0432\u043e\u0439 id\u043a\u0430\u043a \u0438 \u0431\u044b\u043b\u043e \u043e\u043f\u0438\u0441\u0430\u043d\u043e \u0432\u0441\u0435\u0433\u043e \u0434\u0432\u0430 \u0443\u043d\u0438\u0432\u0435\u0440\u0441\u0438\u0442\u0435\u0442\u0430 \u043f\u043e\u0441\u0442\u0430\u0432\u0449\u0438\u043a\u0430 \u0438\u043d\u0444\u043e\u0440\u043c\u0430\u0446\u0438\u0438 \u043f\u043e \u0434\u0430\u043d\u043d\u044b\u043c2892 \u0437\u0434\u043e\u0440\u043e\u0432\u044b\u0445 \u043f\u0430\u0446\u0438\u0435\u043d\u0442\u0430 \u043e\u0441\u0442\u0430\u043b\u044c\u043d\u044b\u0435 \u0441 \u0437\u0430\u044e\u043e\u043b\u0435\u0432\u0430\u043d\u0438\u044f\u043c\u0438 \u043e\u0442 1 \u0434\u043e 5 \u0441\u0442\u0430\u0434\u0438\u0438 \u0440\u0430\u043a\u0430 \u0432 \u0441\u043e\u043e\u0442\u0432\u0435\u0442\u0441\u0442\u0432\u0438\u0438 \u0441 \u0431\u0430\u043b\u043b\u0430\u043c\u0438 \u043f\u043e ISUP \u0421\u0442\u043e\u0438\u0442 \u043e\u0431\u0440\u0430\u0442\u0438\u0442\u044c \u0432\u043d\u0438\u043c\u0430\u043d\u0438\u0435 \u0447\u0442\u043e 3 4 \u0438 4 3 \u0440\u0430\u0432\u043d\u043e \u043a\u0430\u043a \u0438 3 5 \u0438 5 3 \u044d\u0442\u043e \u0440\u0430\u0437\u043d\u044b\u0435 \u0437\u043d\u0430\u0447\u0435\u043d\u0438\u044f \u043f\u043e\u0442\u043e\u043c\u0443 \u0447\u0442\u043e \u043f\u0435\u0440\u0432\u0430\u044f \u043e\u0446\u0435\u043d\u043a\u0430 \u043f\u0440\u0438\u0441\u0432\u0430\u0438\u0432\u0430\u0435\u0442\u0441\u044f \u0444\u0440\u0430\u0433\u043c\u0435\u043d\u0442\u0443 \u0434\u043e\u043c\u0438\u043d\u0438\u0440\u0443\u044e\u0449\u0435\u0433\u043e \u0442\u0438\u043f\u0430 \u0440\u0430\u043a\u043e\u0432\u044b\u0445 \u043a\u043b\u0435\u0442\u043e\u043a \u0432\u0442\u043e\u0440\u0430\u044f \u0432\u0442\u043e\u0440\u0438\u0447\u043d\u043e\u043c\u0443 \u0438\u043c\u0435\u044e\u0442 \u0440\u0430\u0437\u043d\u044b\u0435 \u043f\u043b\u043e\u0449\u0430\u0434\u0438 \u0441\u043e\u0441\u0440\u0435\u0434\u043e\u0442\u043e\u0447\u0435\u043d\u0438\u044f 0 0 \u043e\u0442\u0441\u0443\u0442\u0441\u0442\u0432\u0438\u0435 \u0440\u0430\u043a\u0430. Precision \u043c\u043e\u0436\u043d\u043e \u0438\u043d\u0442\u0435\u0440\u043f\u0440\u0435\u0442\u0438\u0440\u043e\u0432\u0430\u0442\u044c \u043a\u0430\u043a \u0434\u043e\u043b\u044e \u043e\u0431\u044a\u0435\u043a\u0442\u043e\u0432 \u043d\u0430\u0437\u0432\u0430\u043d\u043d\u044b\u0445 \u043a\u043b\u0430\u0441\u0441\u0438\u0444\u0438\u043a\u0430\u0442\u043e\u0440\u043e\u043c \u043f\u043e\u043b\u043e\u0436\u0438\u0442\u0435\u043b\u044c\u043d\u044b\u043c\u0438 \u0438 \u043f\u0440\u0438 \u044d\u0442\u043e\u043c \u0434\u0435\u0439\u0441\u0442\u0432\u0438\u0442\u0435\u043b\u044c\u043d\u043e \u044f\u0432\u043b\u044f\u044e\u0449\u0438\u043c\u0438\u0441\u044f \u043f\u043e\u043b\u043e\u0436\u0438\u0442\u0435\u043b\u044c\u043d\u044b\u043c\u0438 \u0430 recall \u043f\u043e\u043a\u0430\u0437\u044b\u0432\u0430\u0435\u0442 \u043a\u0430\u043a\u0443\u044e \u0434\u043e\u043b\u044e \u043e\u0431\u044a\u0435\u043a\u0442\u043e\u0432 \u043f\u043e\u043b\u043e\u0436\u0438\u0442\u0435\u043b\u044c\u043d\u043e\u0433\u043e \u043a\u043b\u0430\u0441\u0441\u0430 \u0438\u0437 \u0432\u0441\u0435\u0445 \u043e\u0431\u044a\u0435\u043a\u0442\u043e\u0432 \u043f\u043e\u043b\u043e\u0436\u0438\u0442\u0435\u043b\u044c\u043d\u043e\u0433\u043e \u043a\u043b\u0430\u0441\u0441\u0430 \u043d\u0430\u0448\u0435\u043b \u0430\u043b\u0433\u043e\u0440\u0438\u0442\u043c. Module Base class for bottlenecks that implements forward method. \u041d\u0430 \u044d\u0442\u043e\u0439 \u043c\u0438\u043a\u0440\u043e\u0444\u043e\u0442\u043e\u0433\u0440\u0430\u0444\u0438\u0438 \u0432\u0438\u0434\u0435\u043d \u043d\u0435\u043f\u0440\u0430\u0432\u0438\u043b\u044c\u043d\u044b\u0439 \u0440\u0435\u0448\u0435\u0442\u0447\u0430\u0442\u044b\u0439 \u0440\u0430\u043a \u0442\u043e \u0435\u0441\u0442\u044c \u044d\u043f\u0438\u0442\u0435\u043b\u0438\u0430\u043b\u044c\u043d\u044b\u0435 \u043f\u043b\u0430\u0441\u0442\u044b \u0441 \u043c\u043d\u043e\u0436\u0435\u0441\u0442\u0432\u0435\u043d\u043d\u044b\u043c\u0438 \u043f\u0440\u043e\u0441\u0432\u0435\u0442\u0430\u043c\u0438. set_title background data_provider train. conv3 out out self. Conv2d width planes 4 kernel_size 1 bias False self. TIFF \u043e\u0447\u0435\u043d\u044c \u0440\u0430\u0441\u043f\u0440\u043e\u0441\u0442\u0440\u0430\u043d\u0435\u043d \u0434\u043b\u044f \u043f\u0435\u0440\u0435\u0434\u0430\u0447\u0438 \u0446\u0432\u0435\u0442\u043d\u044b\u0445 \u0438\u043b\u0438 \u043f\u043e\u043b\u0443\u0442\u043e\u043d\u043e\u0432\u044b\u0445 \u0438\u0437\u043e\u0431\u0440\u0430\u0436\u0435\u043d\u0438\u0439 \u0432 \u043f\u0440\u0438\u043b\u043e\u0436\u0435\u043d\u0438\u044f \u0434\u043b\u044f \u043c\u0430\u043a\u0435\u0442\u0430 \u0441\u0442\u0440\u0430\u043d\u0438\u0446\u044b \u043d\u043e \u043e\u043d \u043c\u0435\u043d\u0435\u0435 \u043f\u043e\u0434\u0445\u043e\u0434\u0438\u0442 \u0434\u043b\u044f \u0434\u043e\u0441\u0442\u0430\u0432\u043a\u0438 \u0432\u0435\u0431 \u043a\u043e\u043d\u0442\u0435\u043d\u0442. ReLU inplace True conv2 nn. OpenSlide \u0434\u0430\u0435\u0442 \u0440\u0430\u0437\u0440\u0435\u0448\u0435\u043d\u0438\u0435 \u0432 \u0441\u0430\u043d\u0442\u0438\u043c\u0435\u0442\u0440\u0430\u0445 \u043f\u043e\u044d\u0442\u043e\u043c\u0443 \u043c\u044b \u043a\u043e\u043d\u0432\u0435\u0440\u0442\u0438\u0440\u0443\u0435\u043c \u0435\u0433\u043e \u0432 \u043c\u0438\u043a\u0440\u043e\u043d\u044b \u0412\u044b\u0432\u0435\u0434\u0435\u043c \u043d\u0430 \u044d\u043a\u0440\u0430\u043d \u0443\u0432\u0435\u043b\u0438\u0447\u0435\u043d\u043d\u043e\u0435 \u0438\u0437\u043e\u0431\u0440\u0430\u0436\u0435\u043d\u0438\u0435 \u043d\u0435 \u0443\u0432\u0435\u043b\u0438\u0447\u0435\u043d\u043d\u043e\u0435 \u0438\u0437\u043e\u0431\u0440\u0430\u0436\u0435\u043d\u0438\u0435 0005f7aaab2800f6170c399693a96917 1 7000 15000 image_info ffb16f062dfe8fd1161eb29ad1bd80ab 0 2800 17500 0005f7aaab2800f6170c399693a96917 0 7000 15000 image_info 003046e27c8ead3e3db155780dc5498e 0 17000 5600 image_info ffb16f062dfe8fd1161eb29ad1bd80ab 0 2800 17500 0005f7aaab2800f6170c399693a96917 0 7000 15000 image_info ff3667b139539475d4de2aa1b2325c82 0 15000 2500 image_info 003046e27c8ead3e3db155780dc5498e 0 17000 5600 image_info ffb16f062dfe8fd1161eb29ad1bd80ab 0 2800 17500 0005f7aaab2800f6170c399693a96917 0 7000 15000 image_info 00bbc1482301d16de3ff63238cfd0b34 0 3000 8000 image_info ff3667b139539475d4de2aa1b2325c82 0 15000 2500 image_info 003046e27c8ead3e3db155780dc5498e 0 17000 5600 image_info ffb16f062dfe8fd1161eb29ad1bd80ab 0 2800 17500 0005f7aaab2800f6170c399693a96917 0 7000 15000 image_info 0068d4c7529e34fd4c9da863ce01a161 0 4000 8500 image_info 00bbc1482301d16de3ff63238cfd0b34 0 3000 8000 image_info ff3667b139539475d4de2aa1b2325c82 0 15000 2500 image_info 003046e27c8ead3e3db155780dc5498e 0 17000 5600 image_info ffb16f062dfe8fd1161eb29ad1bd80ab 0 2800 17500 0005f7aaab2800f6170c399693a96917 0 7000 15000 image_info 0018ae58b01bdadc8e347995b69f99aa 0 1000 8000 image_info 0068d4c7529e34fd4c9da863ce01a161 0 4000 8500 image_info 00bbc1482301d16de3ff63238cfd0b34 0 3000 8000 image_info ff3667b139539475d4de2aa1b2325c82 0 15000 2500 image_info 003046e27c8ead3e3db155780dc5498e 0 17000 5600 image_info ffb16f062dfe8fd1161eb29ad1bd80ab 0 2800 17500 0005f7aaab2800f6170c399693a96917 0 7000 15000 \u0417\u0434\u0435\u0441\u044c \u043c\u044b \u0432\u044b\u0447\u0438\u0441\u043b\u044f\u0435\u043c \u0438\u043d\u0442\u0435\u0440\u0432\u0430\u043b \u043c\u0435\u0436\u0434\u0443 \u043f\u0438\u043a\u0441\u0435\u043b\u044f\u043c\u0438 \u0444\u0438\u0437\u0438\u0447\u0435\u0441\u043a\u0438\u0439 \u0440\u0430\u0437\u043c\u0435\u0440 \u043f\u0438\u043a\u0441\u0435\u043b\u044f \u0432 \u0438\u0437\u043e\u0431\u0440\u0430\u0436\u0435\u043d\u0438\u0438 OpenSlide \u0434\u0430\u0435\u0442 \u0440\u0430\u0437\u0440\u0435\u0448\u0435\u043d\u0438\u0435 \u0432 \u0441\u0430\u043d\u0442\u0438\u043c\u0435\u0442\u0440\u0430\u0445 \u043f\u043e\u044d\u0442\u043e\u043c\u0443 \u043c\u044b \u043f\u0440\u0435\u043e\u0431\u0440\u0430\u0437\u0443\u0435\u043c \u0435\u0433\u043e \u0432 \u043c\u0438\u043a\u0440\u043e\u043d\u044b. csv \u0441\u043e\u0434\u0435\u0440\u0436\u0438\u0442\u0441\u044f \u0438\u043d\u0444\u043e\u0440\u043c\u0430\u0446\u0438\u044f \u0441\u0440\u0430\u0437\u0443 \u043f\u043e \u0434\u0432\u0443\u043c \u043e\u0446\u0435\u043d\u0435\u043d\u043d\u044b\u043c \u043f\u043e \u0448\u043a\u0430\u043b\u0435 \u0413\u043b\u0438\u0441\u043e\u043d \u0443\u0447\u0430\u0441\u0442\u043a\u0430\u043c \u043a\u043e\u0442\u043e\u0440\u0430\u044f \u043f\u0440\u0435\u0434\u0441\u0442\u0430\u0432\u043b\u044f\u0435\u0442\u0441\u044f \u0432 \u0432\u0438\u0434\u0435 \u0441\u0443\u043c\u043c\u044b \u0431\u0430\u043b\u043b\u043b\u043e\u0432. \u0417\u0430\u0447\u0435\u043c \u043d\u0443\u0436\u043d\u0430 \u043c\u0430\u0441\u043a\u0430 \u0434\u043b\u044f \u0438\u0437\u043e\u0431\u0440\u0430\u0436\u0435\u043d\u0438\u044f\u041f\u043e\u043c\u0438\u043c\u043e \u043c\u0435\u0442\u043a\u0438 \u0443\u0440\u043e\u0432\u043d\u044f \u0441\u043b\u0430\u0439\u0434\u0430 \u043f\u0440\u0438\u0441\u0443\u0442\u0441\u0442\u0432\u0443\u044e\u0449\u0435\u0439 \u0432 \u0444\u0430\u0439\u043b\u0435 csv \u043f\u043e\u0447\u0442\u0438 \u0432\u0441\u0435 \u0441\u043b\u0430\u0439\u0434\u044b \u0432 \u043e\u0431\u0443\u0447\u0430\u044e\u0449\u0435\u043c \u043d\u0430\u0431\u043e\u0440\u0435 \u0438\u043c\u0435\u044e\u0442 \u0441\u0432\u044f\u0437\u0430\u043d\u043d\u0443\u044e \u043c\u0430\u0441\u043a\u0443 \u0441 \u0434\u043e\u043f\u043e\u043b\u043d\u0438\u0442\u0435\u043b\u044c\u043d\u043e\u0439 \u0438\u043d\u0444\u043e\u0440\u043c\u0430\u0446\u0438\u0435\u0439 \u043c\u0435\u0442\u043a\u0438. com hmendonca efficientnet pytorch https www. stride stride class SEResNeXtBottleneck Bottleneck ResNeXt bottleneck type C with a Squeeze and Excitation module. \u041a\u0430\u043a\u043e\u0439 \u0444\u043e\u0440\u043c\u0430\u0442 \u0438\u0437\u043e\u0431\u0440\u0430\u0436\u0435\u043d\u0438\u0439 \u043d\u0430\u043c \u043f\u0440\u0435\u0434\u043e\u0441\u0442\u0430\u0432\u043b\u0435\u043d \u0438 \u043a\u0430\u043a \u0441 \u043d\u0438\u043c \u0440\u0430\u0431\u043e\u0442\u0430\u0442\u044c Tagged Image File Format TIFF \u044d\u0442\u043e \u0444\u043e\u0440\u043c\u0430\u0442 \u0440\u0430\u0441\u0442\u0440\u043e\u0432\u043e\u0433\u043e \u0438\u0437\u043e\u0431\u0440\u0430\u0436\u0435\u043d\u0438\u044f \u0441 \u043f\u0435\u0440\u0435\u043c\u0435\u043d\u043d\u044b\u043c \u0440\u0430\u0437\u0440\u0435\u0448\u0435\u043d\u0438\u0435\u043c \u0440\u0430\u0437\u0440\u0430\u0431\u043e\u0442\u0430\u043d\u043d\u044b\u0439 Aldus \u043d\u044b\u043d\u0435 \u044f\u0432\u043b\u044f\u044e\u0449\u0438\u0439\u0441\u044f \u0447\u0430\u0441\u0442\u044c\u044e Adobe \u0432 1986 \u0433\u043e\u0434\u0443. \u042d\u0442\u043e \u043d\u0430\u043b\u043e\u0436\u0435\u043d\u0438\u0435 \u043f\u043e\u043c\u043e\u0436\u0435\u0442 \u043d\u0430\u043c \u043e\u043f\u0440\u0435\u0434\u0435\u043b\u0438\u0442\u044c \u0440\u0430\u0437\u043b\u0438\u0447\u043d\u044b\u0435 \u043c\u043e\u0434\u0435\u043b\u0438 \u0440\u043e\u0441\u0442\u0430. _make_layer block planes 256 blocks layers 2 stride 2 groups groups reduction reduction downsample_kernel_size downsample_kernel_size downsample_padding downsample_padding self. \u0416\u0435\u043b\u0435\u0437\u044b \u0441\u0433\u0440\u0443\u043f\u043f\u0438\u0440\u043e\u0432\u0430\u043d\u044b \u0432\u043c\u0435\u0441\u0442\u0435. layer4 x return x def logits self x x self. \u0414\u043b\u044f \u043a\u0430\u0436\u0434\u043e\u0433\u043e \u043f\u0438\u043a\u0441\u0435\u043b\u044f \u043e\u043f\u0440\u0435\u0434\u0435\u043b\u0435\u043d\u044b 3 \u0443\u0440\u043e\u0432\u043d\u044f \u0438\u043d\u0442\u0435\u043d\u0441\u0438\u0432\u043d\u043e\u0441\u0442\u0438 \u043f\u043e 1 \u0434\u043b\u044f \u043a\u0430\u0436\u0434\u043e\u0433\u043e \u0446\u0432\u0435\u0442\u0430 \u0438 \u0432\u043c\u0435\u0441\u0442\u0435 \u0438\u0441\u043f\u043e\u043b\u044c\u0437\u0443\u044f \u0441\u0432\u043e\u0435\u0433\u043e \u0440\u043e\u0434\u0430 \u0441\u043c\u0435\u0448\u0438\u0432\u0430\u043d\u0438\u0435 \u0446\u0432\u0435\u0442\u043e\u0432 \u043e\u043d\u0438 \u043e\u043f\u0440\u0435\u0434\u0435\u043b\u044f\u044e\u0442 \u0446\u0432\u0435\u0442 \u044d\u0442\u0438\u0445 \u043f\u0438\u043a\u0441\u0435\u043b\u0435\u0439. __init__ width math. \u041d\u0435 \u0438\u043c\u0435\u0435\u0442 \u043f\u043e\u0442\u0435\u0440\u0438 \u0436\u0435\u043b\u0435\u0437\u0438\u0441\u0442\u043e\u0439 \u0434\u0438\u0444\u0444\u0435\u0440\u0435\u043d\u0446\u0438\u0440\u043e\u0432\u043a\u0438. \u0422\u043e\u0447\u043d\u043e \u0442\u0430\u043a \u0436\u0435 \u0434\u043b\u044f \u0448\u043a\u0430\u043b\u044b \u0441\u0435\u0440\u043e\u0433\u043e \u043c\u043e\u0436\u0435\u0442 \u0431\u044b\u0442\u044c \u0434\u0432\u0430 \u0443\u0440\u043e\u0432\u043d\u044f \u0447\u0435\u0440\u043d\u044b\u0439 \u0438 \u0431\u0435\u043b\u044b\u0439. com ru company ods blog 328372 Accuracy Metric. \u0412\u043d\u0435\u0448\u043d\u0438\u0439 \u0432\u0438\u0434 \u0436\u0435\u043b\u0435\u0437 \u0441\u043e\u0441\u0442\u0430\u0432\u043b\u044f\u0435\u0442 \u043e\u0441\u043d\u043e\u0432\u0443 \u0441\u0438\u0441\u0442\u0435\u043c\u044b \u043e\u0446\u0435\u043d\u043e\u043a \u0413\u043b\u0438\u0441\u043e\u043d\u0430. loc image_mask data_provider karolinska SELECTING CANCEROUS LABELS elif train. pretrained_settings se_resnext50_32x4d pretrained initialize_pretrained_model model num_classes settings return model def se_resnext101_32x4d num_classes 1000 pretrained imagenet model SENet SEResNeXtBottleneck 3 4 23 3 groups 32 reduction 16 dropout_p None inplanes 64 input_3x3 False downsample_kernel_size 1 downsample_padding 0 num_classes num_classes if pretrained is not None settings config. \u0418\u043c\u0435\u0435\u0442 \u0447\u0430\u0441\u0442\u0438\u0447\u043d\u0443\u044e \u043f\u043e\u0442\u0435\u0440\u044e \u0436\u0435\u043b\u0435\u0437\u0438\u0441\u0442\u043e\u0439 \u0434\u0438\u0444\u0444\u0435\u0440\u0435\u043d\u0446\u0438\u0440\u043e\u0432\u043a\u0438. \u041f\u0440\u0438\u043c\u0435\u043d\u0435\u043d\u0438\u0435 \u0446\u0432\u0435\u0442\u043e\u0432\u043e\u0439 \u043a\u0430\u0440\u0442\u044b \u0443\u0441\u0442\u0440\u0430\u043d\u044f\u0435\u0442 \u043f\u0440\u043e\u0431\u043b\u0435\u043c\u0443 \u043d\u0430\u0437\u043d\u0430\u0447\u0430\u044f \u043a\u0430\u0436\u0434\u043e\u0439 \u043c\u0435\u0442\u043a\u0435 \u043e\u0442 0 \u0434\u043e 6 \u043e\u0442\u0434\u0435\u043b\u044c\u043d\u044b\u0439 \u0446\u0432\u0435\u0442. last_linear x return x def forward self x x self. \u0418\u0437\u043e\u0431\u0440\u0430\u0436\u0435\u043d\u0438\u044f RGB \u043c\u043e\u0433\u0443\u0442 \u0441\u043e\u0434\u0435\u0440\u0436\u0430\u0442\u044c \u0434\u043e 16 7 \u043c\u0438\u043b\u043b\u0438\u043e\u043d\u0430 \u0446\u0432\u0435\u0442\u043e\u0432. \u0415\u0441\u0442\u044c \u0442\u0430\u043a\u0436\u0435 \u043d\u0435\u043a\u043e\u0442\u043e\u0440\u044b\u0435 \u043f\u043b\u043e\u0445\u043e \u0441\u0444\u043e\u0440\u043c\u0438\u0440\u043e\u0432\u0430\u043d\u043d\u044b\u0435 \u043c\u0430\u043b\u0435\u043d\u044c\u043a\u0438\u0435 \u0436\u0435\u043b\u0435\u0437\u044b \u0438 \u043d\u0435\u043a\u043e\u0442\u043e\u0440\u044b\u0435 \u0441\u0440\u043e\u0441\u0448\u0438\u0435\u0441\u044f \u0436\u0435\u043b\u0435\u0437\u044b. \u0417\u0430\u0447\u0435\u043c \u043d\u0430\u043c \u0443\u0440\u043e\u0432\u043d\u0438 levels \u0438\u0437\u043e\u0431\u0440\u0430\u0436\u0435\u043d\u0438\u044f \u0420\u0430\u0437\u043c\u0435\u0440\u044b \u0438\u0437\u043e\u0431\u0440\u0430\u0436\u0435\u043d\u0438\u044f \u0431\u0438\u043e\u043f\u0441\u0438\u0438 \u0434\u043e\u0432\u043e\u043b\u044c\u043d\u043e \u0432\u0435\u043b\u0438\u043a\u0438 \u043e\u0431\u044b\u0447\u043d\u043e \u043e\u0442 5. dropout x x x. \u0414\u043e\u043f\u0443\u0441\u0442\u0438\u043c\u044b\u0435 \u0437\u043d\u0430\u0447\u0435\u043d\u0438\u044f 0 \u0444\u043e\u043d \u043d\u0435 \u0442\u043a\u0430\u043d\u044c \u0438\u043b\u0438 \u043d\u0435\u0438\u0437\u0432\u0435\u0441\u0442\u043d\u043e 1 \u0441\u0442\u0440\u043e\u043c\u0430 \u0441\u043e\u0435\u0434\u0438\u043d\u0438\u0442\u0435\u043b\u044c\u043d\u0430\u044f \u0442\u043a\u0430\u043d\u044c \u043d\u0435\u044d\u043f\u0438\u0442\u0435\u043b\u0438\u0430\u043b\u044c\u043d\u0430\u044f \u0442\u043a\u0430\u043d\u044c 2 \u0437\u0434\u043e\u0440\u043e\u0432\u044b\u0439 \u0434\u043e\u0431\u0440\u043e\u043a\u0430\u0447\u0435\u0441\u0442\u0432\u0435\u043d\u043d\u044b\u0439 \u044d\u043f\u0438\u0442\u0435\u043b\u0438\u0439 3 \u0437\u043b\u043e\u043a\u0430\u0447\u0435\u0441\u0442\u0432\u0435\u043d\u043d\u044b\u0439 \u044d\u043f\u0438\u0442\u0435\u043b\u0438\u0439 \u0413\u043b\u0438\u0441\u043e\u043d 3 4 \u0437\u043b\u043e\u043a\u0430\u0447\u0435\u0441\u0442\u0432\u0435\u043d\u043d\u044b\u0439 \u044d\u043f\u0438\u0442\u0435\u043b\u0438\u0439 \u0413\u043b\u0438\u0441\u043e\u043d 4 5 \u0437\u043b\u043e\u043a\u0430\u0447\u0435\u0441\u0442\u0432\u0435\u043d\u043d\u044b\u0439 \u044d\u043f\u0438\u0442\u0435\u043b\u0438\u0439 \u0413\u043b\u0438\u0441\u043e\u043d 5 Karolinska \u0440\u0435\u0433\u0438\u043e\u043d\u044b \u043f\u043e\u043c\u0435\u0447\u0435\u043d\u044b. \u041f\u0440\u043e\u0432\u0435\u0440\u0438\u043c \u0435\u0449\u0435 \u0440\u0430\u0437 \u043d\u0430 \u0434\u0430\u043d\u043d\u044b\u0445 \u0420\u0430\u0441\u0441\u043c\u043e\u0442\u0440\u0438\u043c \u0435\u0449\u0435 \u0440\u0430\u0437 \u043f\u043e\u0434\u0440\u043e\u0431\u043d\u043e \u0432\u0430\u0440\u0438\u0430\u043d\u0442\u044b \u043f\u0440\u0438\u0441\u0432\u043e\u0435\u043d\u0438\u044f \u0431\u0430\u043b\u043b\u043e\u0432 \u043f\u043e \u0432\u0430\u0440\u0438\u0430\u043d\u0442\u0430\u043c 3 4 \u0438 4 3 \u0412\u0438\u0434\u0438\u043c\u043e \u043f\u043e \u043a\u0430\u043a\u043e\u0439 \u0442\u043e \u043f\u0440\u0438\u0447\u0438\u043d\u0435 \u0432 \u0434\u0430\u043d\u043d\u044b\u0445 \u0441\u0443\u0449\u0435\u0441\u0442\u0432\u0443\u0435\u0442 \u043e\u0448\u0438\u0431\u043a\u0430 \u043d\u0435 \u043c\u043e\u0436\u0435\u0442 \u0431\u044b\u0442\u044c 4 3 \u043e\u0446\u0435\u043d\u0435\u043d \u0432\u043e \u0432\u0442\u043e\u0440\u0443\u044e \u0441\u0442\u0430\u0434\u0438\u044e \u0440\u0430\u043a\u0430. BatchNorm2d planes 2 self. format settings num_classes num_classes model. \u0421\u0435\u0439\u0447\u0430\u0441 \u0432 \u0437\u0434\u0440\u0430\u0432\u043e\u043e\u0445\u0440\u0430\u043d\u0435\u043d\u0438\u0438 \u043d\u0430\u0447\u0438\u043d\u0430\u044e\u0442 \u0432\u0441\u0435 \u0448\u0438\u0440\u0435 \u0438\u0441\u043f\u043e\u043b\u044c\u0437\u043e\u0432\u0430\u0442\u044c\u0441\u044f \u0442\u0435\u0445\u043d\u043e\u043b\u043e\u0433\u0438\u0438 \u0438\u0441\u043a\u0443\u0441\u0441\u0442\u0432\u0435\u043d\u043d\u043e\u0433\u043e \u0438\u043d\u0442\u0435\u043b\u043b\u0435\u043a\u0442\u0430 \u0432 \u043f\u0435\u0440\u0432\u0443\u044e \u043e\u0447\u0435\u0440\u0435\u0434\u044c \u0432 \u0441\u0444\u0435\u0440\u0435 \u0434\u0438\u0430\u0433\u043d\u043e\u0441\u0442\u0438\u043a\u0438 \u043f\u043e \u043c\u0435\u0434\u0438\u0446\u0438\u043d\u0441\u043a\u0438\u043c \u0438\u0437\u043e\u0431\u0440\u0430\u0436\u0435\u043d\u0438\u044f\u043c. \u041f\u0440\u0438 \u044d\u0442\u043e\u043c isup 0 \u0438 \u0434\u0430\u043d\u043d\u044b\u0435 train \u043f\u0440\u043e\u0432\u0435\u0440\u0435\u043d\u044b \u043f\u0430\u0442\u043e\u043b\u043e\u0433\u0430\u043c\u0438 \u0441\u043b\u0435\u0434\u043e\u0432\u0430\u0442\u0435\u043b\u044c\u043d\u043e 0 0 \u0438 negative \u043d\u0438\u0447\u0442\u043e \u0438\u043d\u043e\u0435 \u043a\u0430\u043a \u043e\u0442\u0441\u0443\u0442\u0441\u0442\u0432\u0438\u0435 \u0440\u0430\u043a\u0430 https www. inplanes planes groups reduction stride downsample self. \u0420\u0435\u0448\u0435\u043d\u0438\u0435 \u043c\u0435\u0434\u0438\u0446\u0438\u043d\u0441\u043a\u0438\u0445 \u0437\u0430\u0434\u0430\u0447 \u0441 \u043f\u043e\u043c\u043e\u0449\u044c\u044e \u043d\u0435\u0439\u0440\u043e\u0441\u0435\u0442\u0435\u0439. \u0422\u043e \u0435\u0441\u0442\u044c 3 \u0441\u0442\u0430\u0434\u0438\u044f \u0440\u0430\u043a\u0430 \u043f\u043e ISUP 4 3 \u0433\u0434\u0435 \u0441 4 \u0431\u0430\u043b\u043b\u0430 \u043f\u0435\u0440\u0432\u044b\u0439 \u0444\u0440\u0430\u0433\u043c\u0435\u043d\u0442 3 \u0431\u0430\u043b\u043b\u0430 \u0432\u0442\u043e\u0440\u043e\u0439 \u0444\u0440\u0430\u0433\u043c\u0435\u043d\u0442 \u043c\u0435\u043d\u044f\u0435\u0442\u0441\u044f \u043d\u0430 4 4 \u0438 \u0430\u0432\u0442\u043e\u043c\u0430\u0442\u0438\u0447\u0435\u0441\u043a\u0438 \u0437\u0430\u0447\u0438\u0441\u043b\u044f\u0435\u0442\u0441\u044f \u0432 4 \u0441\u0442\u0430\u0434\u0438\u044e \u0440\u0430\u043a\u0430 \u043f\u043e ISUP. floor planes base_width 64 groups self. \u041e\u043d\u0438 \u043f\u0440\u0435\u0434\u0441\u0442\u0430\u0432\u043b\u044f\u044e\u0442 \u0441\u043e\u0431\u043e\u0439 \u043f\u0440\u043e\u0441\u0442\u043e \u043c\u0430\u0442\u0440\u0438\u0446\u044b \u0441\u043e \u0437\u043d\u0430\u0447\u0435\u043d\u0438\u044f\u043c\u0438 \u043e\u0441\u043d\u043e\u0432\u0430\u043d\u043d\u044b\u043c\u0438 \u043d\u0430 \u0438\u043d\u0444\u043e\u0440\u043c\u0430\u0446\u0438\u0438 \u043f\u043e\u0441\u0442\u0430\u0432\u0449\u0438\u043a\u0430 \u0434\u0430\u043d\u043d\u044b\u0445 \u043f\u0440\u0435\u0434\u0441\u0442\u0430\u0432\u043b\u0435\u043d\u043d\u043e\u0439 \u0432\u044b\u0448\u0435 \u0432\u043c\u0435\u0441\u0442\u043e \u0442\u043e\u0433\u043e \u0447\u0442\u043e\u0431\u044b \u0441\u043e\u0434\u0435\u0440\u0436\u0430\u0442\u044c \u0434\u0438\u0430\u043f\u0430\u0437\u043e\u043d \u0437\u043d\u0430\u0447\u0435\u043d\u0438\u0439 \u043e\u0442 0 \u0434\u043e 255 \u043e\u043d\u0438 \u0443\u0432\u0435\u043b\u0438\u0447\u0438\u0432\u0430\u044e\u0442\u0441\u044f \u0442\u043e\u043b\u044c\u043a\u043e \u0434\u043e \u043c\u0430\u043a\u0441\u0438\u043c\u0443\u043c\u0430 6 \u043f\u0440\u0435\u0434\u0441\u0442\u0430\u0432\u043b\u044f\u044f \u0440\u0430\u0437\u043b\u0438\u0447\u043d\u044b\u0435 \u043c\u0435\u0442\u043a\u0438 \u043a\u043b\u0430\u0441\u0441\u043e\u0432 \u043f\u043e\u0434\u0440\u043e\u0431\u043d\u043e\u0441\u0442\u0438 \u043e \u043c\u0435\u0442\u043a\u0430\u0445 \u043c\u0430\u0441\u043e\u043a \u0441\u043c. input_space settings input_space model. \u0424\u0430\u0439\u043b\u044b TIFF \u043c\u043e\u0433\u0443\u0442 \u0431\u044b\u0442\u044c \u0441\u0436\u0430\u0442\u044b \u0430 \u043c\u043e\u0433\u0443\u0442 \u0438 \u043d\u0435 \u0431\u044b\u0442\u044c. \u0421\u0435\u0433\u043e\u0434\u043d\u044f \u043f\u043e\u0441\u043a\u043e\u043b\u044c\u043a\u0443 \u0446\u0438\u0444\u0440\u043e\u0432\u044b\u0435 \u0442\u0435\u0445\u043d\u043e\u043b\u043e\u0433\u0438\u0438 \u043d\u0430\u0447\u0438\u043d\u0430\u044e\u0442 \u043f\u0440\u0435\u0434\u043b\u0430\u0433\u0430\u0442\u044c \u043d\u043e\u0432\u044b\u0435 \u0438 \u043c\u0435\u043d\u0435\u0435 \u0438\u043d\u0432\u0430\u0437\u0438\u0432\u043d\u044b\u0435 \u0441\u0442\u0440\u0430\u0442\u0435\u0433\u0438\u0438 \u0431\u043e\u0440\u044c\u0431\u044b \u0441 \u0440\u0430\u043a\u043e\u043c \u0435\u0441\u0442\u044c \u043d\u0430\u0434\u0435\u0436\u0434\u0430 \u0447\u0442\u043e \u0443\u0436\u0435 \u0432 \u043e\u0431\u043e\u0437\u0440\u0438\u043c\u043e\u043c \u0431\u0443\u0434\u0443\u0449\u0435\u043c \u043b\u0435\u0447\u0435\u043d\u0438\u0435 \u0440\u0430\u043a\u0430 \u043f\u0435\u0440\u0435\u0439\u0434\u0435\u0442 \u043d\u0430 \u043d\u043e\u0432\u0443\u044e \u0441\u0442\u0430\u0434\u0438\u044e \u0440\u0430\u0437\u0432\u0438\u0442\u0438\u044f \u0438 \u044d\u0442\u043e \u043a\u043e\u0441\u043d\u0435\u0442\u0441\u044f \u0432\u0441\u0435\u0433\u043e \u043d\u0430\u0441\u0435\u043b\u0435\u043d\u0438\u044f \u0430 \u043d\u0435 \u0442\u043e\u043b\u044c\u043a\u043e \u043b\u044e\u0434\u0435\u0439 \u043e\u0431\u043b\u0430\u0434\u0430\u044e\u0449\u0438\u0445 \u0437\u043d\u0430\u0447\u0438\u0442\u0435\u043b\u044c\u043d\u044b\u043c\u0438 \u0440\u0435\u0441\u0443\u0440\u0441\u0430\u043c\u0438. \u0418 \u043f\u0440\u0438 \u044d\u0442\u043e\u043c \u0435\u0441\u043b\u0438 \u0447\u0435\u043b\u043e\u0432\u0435\u043a \u0431\u043e\u043b\u0435\u043d \u0442\u043e \u043a\u0430\u0440\u0442\u0438\u043d\u043a\u0430 \u0438\u043c\u0435\u0435\u0442 \u0432\u0430 \u043d\u0430\u0438\u0431\u0431\u043e\u043b\u0435\u0435 \u0432\u044b\u0440\u0430\u0436\u0435\u043d\u043d\u044b\u0445 \u0443\u0447\u0430\u0441\u0442\u043a\u0430 \u0438\u0437\u043c\u0435\u043d\u0435\u043d\u043d\u043e\u0439 \u0436\u0435\u043b\u0435\u0437\u0438\u0441\u0442\u043e\u0439 \u0438 \u0441\u043e\u0435\u0434\u0438\u043d\u0438\u0442\u0435\u043b\u044c\u043d\u043e\u0439 \u0442\u043a\u0430\u043d\u0435\u0439 \u0431\u043e\u043b\u044c\u0448\u0438\u0439 \u0438 \u043c\u0435\u043d\u044c\u0448\u0438\u0439 \u043f\u043e \u043f\u043b\u043e\u0449\u0430\u0434\u0438 \u0441\u043e\u043e\u0442\u0432\u0435\u0442\u0441\u0442\u0432\u0435\u043d\u043d\u043e \u0431\u043e\u043b\u044c\u0448\u0438\u0439 \u043f\u043e \u043f\u043b\u043e\u0449\u0430\u0434\u0438 \u0441\u0447\u0438\u0442\u0430\u0435\u0442\u0441\u044f \u043f\u0435\u0440\u0432\u0438\u0447\u043d\u044b\u043c \u0443\u0447\u0430\u0441\u0442\u043a\u043e\u043c \u0438 \u0431\u0430\u043b\u043b \u043f\u043e \u043d\u0435\u043c\u0443 \u0432 \u0448\u043a\u0430\u043b\u0435 \u0437\u0430\u043f\u0438\u0441\u0430\u043d \u043f\u0435\u0440\u0432\u044b\u043c \u0430 \u0432\u0442\u043e\u0440\u0438\u0447\u043d\u044b\u0439 \u043c\u0435\u043d\u044c\u0448\u0438\u0439 \u0431\u0430\u043b\u043b \u043f\u043e \u043d\u0435\u043c\u0443 \u0438\u0434\u0435\u0442 \u043f\u043e\u0441\u043b\u0435 \u0441\u0438\u043c\u0432\u043e\u043b\u0430 \u0432\u0442\u043e\u0440\u044b\u043c. std settings std def se_resnext50_32x4d num_classes 1000 pretrained imagenet model SENet SEResNeXtBottleneck 3 4 6 3 groups 32 reduction 16 dropout_p None inplanes 64 input_3x3 False downsample_kernel_size 1 downsample_padding 0 num_classes num_classes if pretrained is not None settings config. load_state_dict torch. \u0414\u043b\u044f \u044d\u0442\u043e\u0433\u043e \u0441\u043e\u0437\u0434\u0430\u0434\u0438\u043c \u0444\u0443\u043d\u043a\u0446\u0438\u044e \u043a\u043e\u0442\u043e\u0440\u0430\u044f \u043f\u043e\u0437\u0432\u043e\u043b\u044f\u0435\u0442 \u043f\u0435\u0447\u0430\u0442\u0430\u0442\u044c \u0443\u0432\u0435\u043b\u0438\u0447\u0435\u043d\u043d\u044b\u0435 \u0438 \u043d\u0435 \u043c\u0430\u0441\u0448\u0442\u0430\u0431\u0438\u0440\u043e\u0432\u0430\u043d\u043d\u044b\u0435 \u0438\u0437\u043e\u0431\u0440\u0430\u0436\u0435\u043d\u0438\u044f \u0440\u044f\u0434\u043e\u043c \u0430 \u0442\u0430\u043a\u0436\u0435 \u0432\u0441\u044e \u0438\u043d\u0444\u043e\u0440\u043c\u0430\u0446\u0438\u044e \u043a\u043e\u0442\u043e\u0440\u0430\u044f \u043c\u043e\u0436\u0435\u0442 \u0431\u044b\u0442\u044c \u043f\u043e\u043b\u0443\u0447\u0435\u043d\u0430 \u0438\u0437 \u043d\u0438\u0445. \u0420\u0430\u0441\u0441\u043c\u043e\u0442\u0440\u0438\u043c \u0441\u043b\u0430\u0439\u0434\u044b \u0441 \u043d\u043e\u0440\u043c\u0430\u043b\u044c\u043d\u043e\u0439 \u0436\u0435\u043b\u0435\u0437\u0438\u0441\u0442\u043e\u0439 \u0442\u043a\u0430\u043d\u044c\u044e \u0431\u0435\u0437 \u0440\u0430\u043a\u0430 \u043f\u043e \u0434\u0432\u0443\u043c \u0443\u043d\u0438\u0432\u0435\u0440\u0441\u0438\u0442\u0435\u0442\u0430\u043c\u0426\u0432\u0435\u0442\u0430 \u0438 \u0441\u0442\u0440\u0443\u043a\u0442\u0443\u0440\u0430 \u043f\u043e \u0434\u0432\u0443\u043c \u0443\u043d\u0438\u0432\u0435\u0440\u0441\u0438\u0442\u0435\u0442\u0430\u043c \u0442\u043a\u0430\u043d\u0435\u0439 \u043e\u0442\u043b\u0438\u0447\u0430\u044e\u0442\u0441\u044f. \u0415\u0441\u0442\u044c \u043f\u043e\u043f\u044b\u0442\u043a\u0430 \u0441\u0444\u043e\u0440\u043c\u0438\u0440\u043e\u0432\u0430\u0442\u044c \u043f\u0440\u043e\u0441\u0432\u0435\u0442 \u043d\u043e \u043e\u043f\u0443\u0445\u043e\u043b\u044c \u043d\u0435 \u043c\u043e\u0436\u0435\u0442 \u0441\u0444\u043e\u0440\u043c\u0438\u0440\u043e\u0432\u0430\u0442\u044c \u043f\u043e\u043b\u043d\u043e\u0446\u0435\u043d\u043d\u044b\u0435 \u0445\u043e\u0440\u043e\u0448\u043e \u0440\u0430\u0437\u0432\u0438\u0442\u044b\u0435 \u0436\u0435\u043b\u0435\u0437\u044b. \u041f\u043e\u043f\u0440\u043e\u0431\u0443\u0435\u043c \u0437\u0430\u0433\u0440\u0443\u0437\u0438\u0442\u044c \u0438 \u0440\u0430\u0441\u0441\u043c\u043e\u0442\u0440\u0435\u0442\u044c \u043e\u0434\u043d\u0443 \u0438\u0437 \u0431\u0438\u043e\u043f\u0441\u0438\u0439 image_id \u0447\u0435\u0440\u0435\u0437 OpenSlide. append model \u0440\u0430\u0437\u0431\u0438\u0432\u0430\u0435\u043c \u0438\u0437\u043e\u0431\u0440\u0430\u0436\u0435\u043d\u0438\u0435 \u0431\u0438\u043e\u043f\u0441\u0438\u0438 \u043d\u0430 16 \u0447\u0430\u0441\u0442\u0435\u0439. expansion downsample nn. \u0415\u0441\u043b\u0438 \u0436\u0435 \u0441\u0438\u0442\u0443\u0430\u0446\u0438\u044f \u043e\u0431\u0440\u0430\u0442\u043d\u0430\u044f \u0438 \u0432\u0442\u043e\u0440\u0438\u0447\u043d\u0430\u044f \u043e\u043f\u0443\u0445\u043e\u043b\u044c \u0438\u043c\u0435\u0435\u0442 \u043e\u0435\u043d\u043a\u0443 3 \u0430 \u0431\u043e\u043b\u044c\u0448\u0430\u044f \u043f\u043e \u043f\u043b\u043b\u043e\u0449\u0430\u0434\u0438 \u043f\u0435\u0440\u0432\u0430\u044f 4 \u044d\u0442\u043e 2 \u0441\u0442\u0430\u0434\u0438\u044f \u0440\u0430\u043a\u0430\u041f\u043e\u0434\u0440\u043e\u0431\u043d\u043e\u0435 \u043e\u043f\u0438\u0441\u0430\u043d\u0438\u0435 \u043f\u043e \u0441\u0441\u044b\u043b\u043a\u0435 https www. loc image data_provider Create alpha mask \u041e\u0442\u043e\u0431\u0440\u0430\u0436\u0435\u043d\u0438\u0435 0 \u0444\u043e\u043d \u043d\u0435 \u0442\u043a\u0430\u043d\u044c \u0438\u043b\u0438 \u043d\u0435\u0438\u0437\u0432\u0435\u0441\u0442\u043d\u043e 1 \u0441\u043e\u0435\u0434\u0438\u043d\u0438\u0442\u0435\u043b\u044c\u043d\u0430\u044f \u0442\u043a\u0430\u043d\u044c 2 \u0437\u0434\u043e\u0440\u043e\u0432\u044b\u0439 \u044d\u043f\u0438\u0442\u0435\u043b\u0438\u0439 3 Gleason 3 4 Gleason 4 5 Gleason 5 \u041e\u0442\u043e\u0431\u0440\u0430\u0436\u0435\u043d\u0438\u0435 0 \u0444\u043e\u043d \u043d\u0435 \u0442\u043a\u0430\u043d\u044c \u0438\u043b\u0438 \u043d\u0435\u0438\u0437\u0432\u0435\u0441\u0442\u043d\u043e 1 \u0434\u043e\u0431\u0440\u043e\u043a\u0430\u0447\u0435\u0441\u0442\u0432\u0435\u043d\u043d\u0430\u044f 2 \u0440\u0430\u043a we are in validation part orig image has shape 3 1024 1024 converting to 1024 1024 3 \u0417\u0430\u0433\u0440\u0443\u0436\u043a\u0430 \u0438\u0437\u043e\u0431\u0440\u0430\u0436\u0435\u043d\u0438\u044f \u043a\u043e\u043d\u0435\u0447\u043d\u043e\u0433\u043e class SEModule nn. Conv2d inplanes planes 2 kernel_size 1 bias False self. downsample downsample self. \u0414\u0440\u0443\u0433\u043e\u0439 \u0441\u043f\u043e\u0441\u043e\u0431 \u0438\u043d\u0442\u0435\u0440\u043f\u0440\u0435\u0442\u0438\u0440\u043e\u0432\u0430\u0442\u044c \u044d\u0442\u043e \u0441\u043b\u043e\u0438. Conv2d planes planes kernel_size 3 padding 1 groups groups bias False self. \u0414\u043e\u0441\u0442\u0443\u043f\u043d\u044b \u0447\u0435\u0442\u044b\u0440\u0435 \u0442\u0438\u043f\u0430 \u0431\u0430\u0437\u043e\u0432\u044b\u0445 \u0438\u0437\u043e\u0431\u0440\u0430\u0436\u0435\u043d\u0438\u0439 TIFF \u0434\u0432\u0443\u0445\u0443\u0440\u043e\u0432\u043d\u0435\u0432\u044b\u0439 \u0447\u0435\u0440\u043d\u044b\u0439 \u0438 \u0431\u0435\u043b\u044b\u0439 \u0448\u043a\u0430\u043b\u0430 \u0441\u0435\u0440\u043e\u0433\u043e \u043f\u0430\u043b\u0438\u0442\u0440\u0430 \u0442. stride stride class SENet nn. BatchNorm2d 64 relu1 nn. BatchNorm2d inplanes relu3 nn. size 0 1 x self. ReLU inplace True layer0_modules. html 6 \u0431\u0430\u043b\u043b\u043e\u0432 \u043f\u043e \u0448\u043a\u0430\u043b\u0435 \u0413\u043b\u0438\u0441\u043e\u043d\u0430 1 \u0431\u0430\u043b\u043b ISUP 1 \u0441\u0442\u0430\u0434\u0438\u044f \u0440\u0430\u043a\u0430 7 \u0431\u0430\u043b\u043b\u043e\u0432 \u043f\u043e \u0448\u043a\u0430\u043b\u0435 \u0413\u043b\u0438\u0441\u043e\u043d\u0430 3 4 2 \u0431\u0430\u043b\u043b\u0430 \u043f\u043e \u043f\u0440\u043e\u0433\u0440\u0430\u043c\u043c\u0435 ISUP 2 \u0441\u0442\u0430\u0434\u0438\u044f \u0440\u0430\u043a\u0430 7 \u0431\u0430\u043b\u043b\u043e\u0432 \u043f\u043e \u0448\u043a\u0430\u043b\u0435 \u0413\u043b\u0438\u0441\u043e\u043d\u0430 4 3 3 \u0431\u0430\u043b\u043b\u0430 \u043f\u043e \u043f\u0440\u043e\u0433\u0440\u0430\u043c\u043c\u0435 ISUP 3 \u0441\u0442\u0430\u0434\u0438\u044f \u0440\u0430\u043a\u0430 8 \u0431\u0430\u043b\u043b\u043e\u0432 \u043f\u043e \u0448\u043a\u0430\u043b\u0435 \u0413\u043b\u0438\u0441\u043e\u043d\u0430 4 \u0431\u0430\u043b\u043b\u0430 ISUP 4 \u0441\u0442\u0430\u0434\u0438\u044f \u0440\u0430\u043a\u0430 9 10 \u0431\u0430\u043b\u043b\u043e\u0432 \u043f\u043e \u0448\u043a\u0430\u043b\u0435 \u0413\u043b\u0438\u0441\u043e\u043d\u0430 5 \u0431\u0430\u043b\u043b\u043e\u0432 ISUP 5 \u0441\u0442\u0430\u0434\u0438\u044f \u0440\u0430\u043a\u0430 \u0415\u0441\u043b\u0438 \u0440\u0430\u043a\u0430 \u043d\u0435 \u043e\u0431\u043d\u0430\u0440\u0443\u0436\u0435\u043d\u043e ISUP \u0441\u0442\u0430\u0434\u0438\u044f \u0440\u0430\u043a\u0430 \u0438\u043c\u0435\u0435\u0442 \u0437\u043d\u0430\u0447\u0435\u043d\u0438\u0435 0. \u041d\u0430\u043f\u0440\u0438\u043c\u0435\u0440 \u0431\u0438\u043e\u043f\u0441\u0438\u044f \u0441\u043e\u0434\u0435\u0440\u0436\u0430\u0449\u0430\u044f 60 \u0434\u043e\u043c\u0438\u043d\u0438\u0440\u0443\u044e\u0449\u0438\u0439 \u0442\u0438\u043f \u043f\u0435\u0440\u0432\u044b\u0439 \u0443\u0447\u0430\u0441\u0442\u043e\u043a \u043e\u0446\u0435\u043d\u0435\u043d\u043d\u044b\u0439 \u043d\u0430 4 \u0431\u0430\u043b\u043b\u0430 \u043f\u043e \u0413\u043b\u0438\u0441\u043e\u043d\u0443 37 \u0432\u0442\u043e\u0440\u0438\u0447\u043d\u044b\u0439 \u0442\u0438\u043f \u0432\u0442\u043e\u0440\u043e\u0439 \u0443\u0447\u0430\u0441\u0442\u043e\u043a \u043e\u0446\u0435\u043d\u0435\u043d\u043d\u044b\u0439 \u043d\u0430 3 \u0431\u0430\u043b\u043b\u0430 \u043f\u043e \u0413\u043b\u0438\u0441\u043e\u043d\u0443 3 \u0442\u0440\u0435\u0442\u0438\u0447\u043d\u044b\u0439 \u0442\u0438\u043f \u043e\u0446\u0435\u043d\u0435\u043d\u043d\u044b\u0439 \u043d\u0430 5 \u0431\u0430\u043b\u043b\u043e\u0432 \u043f\u043e \u0413\u043b\u0438\u0441\u043e\u043d\u0443 \u0434\u043e\u043b\u0436\u043d\u0430 \u043f\u043e\u043b\u0443\u0447\u0438\u0442\u044c \u043e\u0446\u0435\u043d\u043a\u0443 4 5 9. inplanes planes block. \u041f\u0440\u0438\u0447\u0438\u043d\u044b \u0438\u0441\u043f\u043e\u043b\u044c\u0437\u043e\u0432\u0430\u043d\u0438\u044f \u0424\u0430\u0439\u043b\u044b IFF \u0431\u043e\u043b\u044c\u0448\u0438\u0435 \u0438 \u043e\u0447\u0435\u043d\u044c \u0432\u044b\u0441\u043e\u043a\u043e\u0433\u043e \u043a\u0430\u0447\u0435\u0441\u0442\u0432\u0430. _make_layer block planes 64 blocks layers 0 groups groups reduction reduction downsample_kernel_size 1 downsample_padding 0 self. \u0424\u0440\u0430\u0433\u043c\u0435\u043d\u0442 \u043e\u043f\u0443\u0445\u043e\u043b\u0438 \u0441\u043a\u0430\u043d\u0438\u0440\u0443\u044e\u0442 \u0438 \u043e\u0446\u0438\u0444\u0440\u043e\u0432\u044b\u0432\u0430\u044e\u0442. \u0427\u0442\u043e\u0431\u044b \u0443\u043f\u0440\u043e\u0441\u0442\u0438\u0442\u044c \u043f\u0440\u043e\u0432\u0435\u0440\u043a\u0443 \u043c\u0430\u0441\u043e\u043a \u043c\u044b \u0441\u043e\u043f\u043e\u0441\u0442\u0430\u0432\u043b\u044f\u0435\u043c \u043c\u0435\u0442\u043a\u0438 int \u0441 \u0446\u0432\u0435\u0442\u0430\u043c\u0438 RGB \u0441 \u043f\u043e\u043c\u043e\u0449\u044c\u044e \u0446\u0432\u0435\u0442\u043e\u0432\u043e\u0439 \u043f\u0430\u043b\u0438\u0442\u0440\u044b. \u041d\u0430 \u0432\u0441\u0435\u0445 \u043c\u0438\u043a\u0440\u043e\u0444\u043e\u0442\u043e\u0433\u0440\u0430\u0444\u0438\u044f\u0445 \u0432\u0438\u0434\u043d\u044b \u043f\u044f\u0442\u043d\u0430 \u0433\u0435\u043c\u0430\u0442\u043e\u043a\u0441\u0438\u043b\u0438\u043d\u0430 \u0438 \u044d\u043e\u0437\u0438\u043d\u0430 \u043f\u0440\u0438 20 \u043a\u0440\u0430\u0442\u043d\u043e\u043c \u0443\u0432\u0435\u043b\u0438\u0447\u0435\u043d\u0438\u0438 \u043b\u0438\u043d\u0437\u044b. \u0421\u0442\u0435\u043f\u0435\u043d\u044c \u0438\u0437\u043c\u0435\u043d\u0435\u043d\u0438\u044f \u043a\u043b\u0435\u0442\u043e\u043a \u0434\u0432\u0443\u0445 \u0438\u0441\u0441\u043b\u0435\u0434\u0443\u0435\u043c\u044b\u0445 \u0443\u0447\u0430\u0441\u0442\u043a\u043e\u0432 \u0438\u0437\u043c\u0435\u0440\u044f\u0435\u0442\u0441\u044f \u043f\u043e \u0448\u043a\u0430\u043b\u0435 \u043e\u0442 1 \u0434\u043e 5 \u0447\u0435\u043c \u0431\u043e\u043b\u0435\u0435 \u0445\u0430\u0440\u0430\u043a\u0442\u0435\u0440\u043d\u044b \u0438\u0437\u043c\u0435\u043d\u0435\u043d\u0438\u044f \u0442\u0435\u043c \u0431\u043e\u043b\u0435\u0435 \u0430\u0433\u0440\u0435\u0441\u0441\u0438\u0432\u043d\u0430 \u0437\u043b\u043e\u043a\u0430\u0447\u0435\u0441\u0442\u0432\u0435\u043d\u043d\u0430\u044f \u043e\u043f\u0443\u0445\u043e\u043b\u044c \u0442\u0435\u043c \u0431\u043e\u043b\u044c\u0448\u0430\u044f \u0441\u0442\u0430\u0434\u0438\u044f \u0437\u0430\u0431\u043e\u043b\u0435\u0432\u0430\u043d\u0438\u044f \u0440\u0430\u043a\u043e\u043c. \u0410\u0434\u0435\u043d\u043e\u043a\u0430\u0440\u0446\u0438\u043d\u043e\u043c\u0430 \u043f\u0440\u0435\u0434\u0441\u0442\u0430\u0442\u0435\u043b\u044c\u043d\u043e\u0439 \u0436\u0435\u043b\u0435\u0437\u044b 5 \u0431\u0430\u043b\u043b\u043e\u0432 \u043f\u043e \u0448\u043a\u0430\u043b\u0435 \u0413\u043b\u0438\u0441\u043e\u043d\u0430. \u0412\u0442\u043e\u0440\u0438\u0447\u043d\u044b\u0439 \u0444\u0440\u0430\u0433\u043c\u0435\u043d\u0442 \u0434\u043e\u043b\u0436\u0435\u043d \u0441\u043e\u0441\u0442\u0430\u0432\u043b\u044f\u0442\u044c \u043e\u0442 5 \u0434\u043e 50 \u0432\u0441\u0435\u0445 \u043f\u043e\u0440\u0430\u0436\u0435\u043d\u043d\u044b\u0445 \u043a\u043b\u0435\u0442\u043e\u043a \u0438 \u0435\u0441\u043b\u0438 \u0443\u0441\u043b\u043e\u0432\u0438\u0435 \u043f\u043e \u043a\u0430\u043a\u0438\u043c \u043e \u043f\u0440\u0438\u0447\u0438\u043d\u0430\u043c \u043d\u0435 \u0441\u043e\u0431\u043b\u044e\u0434\u0430\u0435\u0442\u0441\u044f \u0438 \u0443\u0447\u0430\u0441\u0442\u043e\u043a \u0441\u043e\u0441\u0442\u0430\u0432\u043b\u044f\u0435\u0442 \u043c\u0435\u043d\u0435\u0435 5 \u043e\u0446\u0435\u043d\u043a\u0430 \u043f\u043e \u0432\u0442\u043e\u0440\u043e\u043c\u0443 \u0444\u0440\u0430\u0433\u043c\u0435\u043d\u0442\u0443 \u0443\u0432\u0435\u043b\u0438\u0447\u0438\u0432\u0430\u0435\u0442\u0441\u044f \u043d\u0430 \u043e\u0434\u0438\u043d \u0431\u0430\u043b\u043b. \u0414\u0432\u0430 \u0434\u0430\u0442\u0430\u0441\u0435\u0442\u0430 \u043e\u0431\u0443\u0447\u0430\u044e\u0449\u0438\u0439 \u0438 \u0442\u0435\u0441\u0442\u043e\u0432\u044b\u0439 train. \u0418\u0437\u043e\u0431\u0440\u0430\u0436\u0435\u043d\u0438\u0435 \u0442\u0438\u043f\u0430 RGB \u043a\u0440\u0430\u0441\u043d\u044b\u0439 \u0437\u0435\u043b\u0435\u043d\u044b\u0439 \u0441\u0438\u043d\u0438\u0439 \u0438\u0441\u043f\u043e\u043b\u044c\u0437\u0443\u0435\u0442 \u0442\u0440\u0438 \u0441\u043b\u043e\u044f \u0434\u043b\u044f \u043e\u043f\u0440\u0435\u0434\u0435\u043b\u0435\u043d\u0438\u044f \u0446\u0432\u0435\u0442\u0430 \u043e\u0434\u0438\u043d \u0441\u043b\u043e\u0439 \u043e\u043f\u0440\u0435\u0434\u0435\u043b\u044f\u0435\u0442 \u043a\u0440\u0443\u043f\u043d\u043e\u043c\u0430\u0441\u0448\u0442\u0430\u0431\u043d\u043e\u0435 \u0438\u0437\u043e\u0431\u0440\u0430\u0436\u0435\u043d\u0438\u0435 \u043d\u0435\u043a\u043e\u0442\u043e\u0440\u044b\u0435 \u0442\u0438\u043f\u044b \u0438\u0437\u043e\u0431\u0440\u0430\u0436\u0435\u043d\u0438\u0439 \u0441\u043e\u0434\u0435\u0440\u0436\u0430\u0442 \u0431\u043e\u043b\u0435\u0435 \u0442\u0440\u0435\u0445 \u0441\u043b\u043e\u0435\u0432. Conv2d 3 inplanes kernel_size 7 stride 2 padding 3 bias False bn1 nn. \u041f\u0430\u043b\u0438\u0442\u0440\u0430 \u0438 \u043f\u043e\u043b\u0443\u0442\u043e\u043d\u043e\u0432\u044b\u0435 \u0438\u0437\u043e\u0431\u0440\u0430\u0436\u0435\u043d\u0438\u044f \u043e\u0433\u0440\u0430\u043d\u0438\u0447\u0435\u043d\u044b 256 \u0446\u0432\u0435\u0442\u0430\u043c\u0438 \u0438\u043b\u0438 \u043e\u0442\u0442\u0435\u043d\u043a\u0430\u043c\u0438. OpenSlide \u0434\u043e\u043a\u0443\u043c\u0435\u043d\u0442\u0430\u0446\u0438\u044f \u043f\u043e \u0441\u0441\u044b\u043b\u043a\u0435 https openslide. \u0411\u0438\u043e\u043f\u0441\u0438\u0438 \u043c\u043e\u0433\u0443\u0442 \u0431\u044b\u0442\u044c \u043f\u0440\u0435\u0434\u0441\u0442\u0430\u0432\u043b\u0435\u043d\u0430 \u0432 \u0440\u0430\u0437\u043d\u044b\u0445 \u0440\u0430\u0441\u043f\u043e\u043b\u043e\u0436\u0435\u043d\u0438\u044f\u0445. \u0416\u0435\u043b\u0435\u0437\u0438\u0441\u0442\u0430\u044f \u0441\u0442\u0440\u0443\u043a\u0442\u0443\u0440\u0430 \u0445\u0430\u0440\u0430\u043a\u0442\u0435\u0440\u043d\u0430\u044f \u0434\u043b\u044f \u0437\u0434\u043e\u0440\u043e\u0432\u043e\u0439 \u0442\u043a\u0430\u043d\u0438 \u043f\u0440\u043e\u0441\u0442\u0430\u0442\u044b \u043f\u043e\u0441\u0442\u0435\u043f\u0435\u043d\u043d\u043e \u0443\u0442\u0440\u0430\u0447\u0438\u0432\u0430\u0435\u0442\u0441\u044f \u0441 \u0443\u0432\u0435\u043b\u0438\u0447\u0435\u043d\u0438\u0435\u043c \u0431\u0430\u043b\u043b\u043e\u0432 \u0438 \u043a\u043b\u0435\u0442\u043a\u0438 \u043f\u0440\u0438\u043e\u0431\u0440\u0435\u0442\u0430\u044e\u0442 \u043d\u0435\u0447\u0435\u0442\u043a\u0438\u0435 \u0440\u0430\u0437\u043c\u0430\u0437\u0430\u043d\u043d\u044b\u0435 \u043a\u043e\u043d\u0442\u0443\u0440\u044b. \u0414\u043b\u044f \u0432\u044b\u043f\u043e\u043b\u043d\u0435\u043d\u0438\u044f \u0437\u0430\u0434\u0430\u0447\u0438 ML \u043d\u0430\u043c \u043f\u0440\u0435\u0434\u043e\u0441\u0442\u0430\u0432\u043b\u0435\u043d\u044b \u0441\u043b\u0435\u0434\u0443\u044e\u0449\u0438\u0435 \u0444\u0430\u0439\u043b\u044b \u0441 \u0434\u0430\u043d\u043d\u044b\u043c\u0438 1. \u0422\u0435\u0441\u0442\u043e\u0432\u044b\u043c\u0438 \u0434\u0430\u043d\u043d\u044b\u043c\u0438 \u044f\u0432\u043b\u044f\u044e\u0442\u0441\u044f \u043f\u043e\u0441\u043b\u0435\u0434\u043d\u0438\u0435 500 \u0441\u0442\u0440\u043e\u043a \u0442\u0440\u0435\u043d\u0438\u0440\u043e\u0432\u043e\u0447\u043d\u044b\u043c\u0438 \u043e\u0441\u0442\u0430\u043b\u044c\u043d\u044b\u0435 \u0431\u043e\u043b\u0435\u0435 10000. \u041a\u0430\u0436\u0434\u044b\u0439 \u0441\u043b\u0430\u0439\u0434 \u043d\u0430\u0448\u0435\u0433\u043e \u0438\u0437\u043e\u0431\u0440\u0430\u0436\u0435\u043d\u0438\u044f \u0431\u0438\u043e\u043f\u0441\u0438\u0438 \u0438\u043c\u0435\u0435\u0442 3 \u0443\u0440\u043e\u0432\u043d\u044f \u043a\u043e\u0442\u043e\u0440\u044b\u0435 \u043c\u043e\u0436\u043d\u043e \u0437\u0430\u0433\u0440\u0443\u0437\u0438\u0442\u044c \u0447\u0442\u043e \u0441\u043e\u043e\u0442\u0432\u0435\u0442\u0441\u0442\u0432\u0443\u0435\u0442 \u043f\u043e\u043d\u0438\u0436\u0435\u043d\u0438\u044e \u0434\u0438\u0441\u043a\u0440\u0435\u0442\u0438\u0437\u0430\u0446\u0438\u0438 \u043d\u0430 1 4 \u0438 16. \u0432 \u043e\u043f\u0438\u0441\u0430\u043d\u0438\u0438 \u043d\u0430\u0431\u043e\u0440\u0430 \u0434\u0430\u043d\u043d\u044b\u0445. EfficientNet \u043f\u0440\u0435\u0434\u043e\u0431\u0443\u0447\u0435\u043d\u043d\u0430\u044f \u043d\u0430 ImageNet \u0441\u0435\u0442\u044c. com ru post 498168 https www. \u0421\u0430\u043c\u0430\u044f \u0432\u044b\u0441\u043e\u043a\u0430\u044f \u043e\u0446\u0435\u043d\u043a\u0430 \u0432\u0441\u0435\u0433\u0434\u0430 \u0434\u043e\u043b\u0436\u043d\u0430 \u0431\u044b\u0442\u044c \u0447\u0430\u0441\u0442\u044c\u044e \u043e\u0446\u0435\u043d\u043a\u0438. \u0418\u043c\u0435\u0435\u0442 \u043f\u043e\u0447\u0442\u0438 \u043f\u043e\u043b\u043d\u0443\u044e \u0443\u0442\u0440\u0430\u0442\u0443 \u0436\u0435\u043b\u0435\u0437\u0438\u0441\u0442\u043e\u0439 \u0434\u0438\u0444\u0444\u0435\u0440\u0435\u043d\u0446\u0438\u0440\u043e\u0432\u043a\u0438. 000 \u043f\u0438\u043a\u0441\u0435\u043b\u0435\u0439 \u043f\u043e \u043e\u0441\u044f\u043c x \u0438 y. Conv2d channels reduction channels kernel_size 1 padding 0 self. __init__ self. Sequential layers def features self x x self. bn1 out out self. It follows Caffe implementation and uses stride stride in conv1 and not in conv2 the latter is used in the torchvision implementation of ResNet. \u0411\u0430\u043b\u043b\u044b \u043f\u043e \u043a\u0430\u0436\u0434\u043e\u043c\u0443 \u0438\u0437 \u0434\u0432\u0443\u0445 \u0438\u0441\u0441\u043b\u0435\u0434\u0443\u0435\u043c\u044b\u0445 \u0443\u0447\u0430\u0441\u0442\u043a\u043e\u0432 \u043e\u043f\u0443\u0445\u043e\u043b\u0438 \u0441\u043a\u043b\u0430\u0434\u044b\u0432\u0430\u044e\u0442\u0441\u044f. layer2 x x self. loc image_mask data_provider radboud SELECTING NON CANCEROUS LABELS if train. \u042d\u0442\u043e \u0438 \u043d\u0430\u0437\u044b\u0432\u0430\u0435\u0442\u0441\u044f \u0441\u0438\u0441\u0442\u0435\u043c\u043e\u0439 \u043e\u0446\u0435\u043d\u043e\u043a \u0448\u043a\u0430\u043b\u043e\u0439 \u0413\u043b\u0438\u0441\u043e\u043d\u0430. \u0410 \u0432 \u043f\u0440\u0435\u043a\u043b\u043e\u043d\u043d\u043e\u043c \u0432\u043e\u0437\u0440\u0430\u0441\u0442\u0435 \u043f\u043e\u0441\u043b\u0435 75 \u043b\u0435\u0442 \u0440\u0430\u043a \u043f\u0440\u0435\u0434\u0441\u0442\u0430\u0442\u0435\u043b\u044c\u043d\u043e\u0439 \u0436\u0435\u043b\u0435\u0437\u044b \u043d\u0430\u0445\u043e\u0434\u044f\u0442 \u0443 \u043e\u0434\u043d\u043e\u0433\u043e \u0438\u0437 \u0432\u043e\u0441\u044c\u043c\u0438 \u043c\u0443\u0436\u0447\u0438\u043d. \u0411\u0430\u0437\u043e\u0432\u044b\u0435 \u0438\u0437\u043e\u0431\u0440\u0430\u0436\u0435\u043d\u0438\u044f TIFF \u043b\u0435\u0433\u043a\u043e \u043f\u0435\u0440\u0435\u043d\u043e\u0441\u0438\u043c\u044b \u0438\u0445 \u043f\u043e\u043d\u0438\u043c\u0430\u044e\u0442 \u0431\u043e\u043b\u044c\u0448\u0438\u043d\u0441\u0442\u0432\u043e \u0433\u0440\u0430\u0444\u0438\u0447\u0435\u0441\u043a\u0438\u0445 \u043f\u0440\u0438\u043b\u043e\u0436\u0435\u043d\u0438\u0439 \u043d\u0430\u0441\u0442\u043e\u043b\u044c\u043d\u044b\u0445 \u0438\u0437\u0434\u0430\u0442\u0435\u043b\u044c\u0441\u043a\u0438\u0445 \u0441\u0438\u0441\u0442\u0435\u043c \u0438 \u0442\u0435\u043a\u0441\u0442\u043e\u0432\u044b\u0445 \u0440\u0435\u0434\u0430\u043a\u0442\u043e\u0440\u043e\u0432. Conv2d 64 64 3 stride 1 padding 1 bias False bn2 nn. \u041a\u0430\u043a \u0432\u044b\u0433\u043b\u044f\u0434\u0438\u0442 \u0448\u043a\u0430\u043b\u0430 \u0413\u043b\u0438\u0441\u043e\u043d \u0432 \u043d\u0430\u0448\u0435\u043c \u0434\u0430\u0442\u0430\u0441\u0435\u0442\u0435 \u0422\u0430\u043a \u043a\u0430\u043a \u043a \u0440\u0430\u043a\u043e\u0432\u044b\u043c \u043e\u0442\u043d\u043e\u0441\u044f\u0442\u0441\u044f \u0442\u043a\u0430\u043d\u0438 \u043f\u0440\u043e\u0441\u0442\u0430\u0442\u044b \u0438\u043c\u0435\u044e\u0449\u0438\u0435 \u0441\u0443\u043c\u043c\u0443 \u0413\u043b\u0438\u0441\u043e\u043d\u0430 \u0432\u044b\u0448\u0435 6 \u043d\u0430\u0448 \u0434\u0430\u0442\u0430\u0441\u0435\u0442 \u0440\u0430\u0441\u043f\u043e\u0437\u043d\u0430\u0435\u0442 \u043f\u043e \u043a\u0430\u0436\u0434\u043e\u043c\u0443 \u0438\u0437 \u0434\u0432\u0443\u0445 \u0443\u0447\u0430\u0441\u0442\u043a\u043e\u0432 \u0442\u043a\u0430\u043d\u0438 \u0432\u0437\u044f\u0442\u044b\u0445 \u043d\u0430 \u0431\u0438\u043e\u043f\u0441\u0438\u0438 \u0442\u043e\u043b\u044c\u043a\u043e \u0442\u0440\u0438 \u043a\u0430\u0442\u0435\u0433\u043e\u0440\u0438\u0438 3 4 \u0438 5. Sequential OrderedDict layer0_modules self. \u041f\u043e\u0441\u043c\u043e\u0442\u0440\u0438\u043c \u0441\u043a\u043e\u043b\u044c\u043a\u043e \u043f\u0430\u0446\u0438\u0435\u043d\u0442\u043e\u0432 \u0441\u0443\u0449\u0435\u0441\u0442\u0432\u0443\u0435\u0442 \u0441 \u0442\u0430\u043a\u0438\u043c\u0438 \u043e\u0448\u0438\u0431\u043a\u0430\u043c\u0438 \u0432 \u043d\u0430\u0448\u0435\u043c \u0434\u0430\u0442\u0430\u0441\u0435\u0442\u0435\u041f\u043e\u0441\u043a\u043e\u043b\u044c\u043a\u043e \u043e\u0448\u0438\u0431\u0447\u043d\u0430 \u0432\u0441\u0435\u0433\u043e \u043b\u0438\u0448\u044c \u043e\u0434\u043d\u0430 \u0441\u0442\u0440\u043e\u043a\u0430 \u043b\u0438\u0431\u043e \u0432\u043c\u0435\u0441\u0442\u043e 3 \u0441\u0442\u0430\u0434\u0438\u0438 \u0440\u0430\u043a\u0430 \u043f\u0440\u0438\u0441\u0443\u0434\u0438\u043b\u0438 2\u044e \u043b\u0438\u0431\u043e \u043d\u0435 4 3 \u043d\u0430 \u0441\u0430\u043c\u043e\u043c \u0434\u0435\u043b\u0435 \u0443\u0434\u0430\u043b\u0438\u043c \u0434\u0430\u043d\u043d\u044b\u0435 \u0447\u0442\u043e\u0431\u044b \u043d\u0435 \u043f\u0443\u0442\u0430\u0442\u044c \u043c\u043e\u0434\u0435\u043b\u044c \u041f\u043e\u0441\u043c\u043e\u0442\u0440\u0438\u043c \u0442\u0435\u043f\u0435\u0440\u044c \u0447\u0442\u043e \u043b\u0435\u0436\u0438\u0442 \u0432 \u0434\u0430\u0442\u0430\u0441\u0435\u0442\u0435 test. csv EDA \u0430\u043d\u0430\u043b\u0438\u0437\u0418\u0442\u0430\u043a \u043f\u043e\u0441\u043c\u043e\u0442\u0440\u0438\u043c \u043a\u0430\u043a\u0438\u0435 \u0441\u0443\u0449\u0435\u0441\u0442\u0432\u0443\u044e\u0442 \u0432\u0430\u0440\u0438\u0430\u043d\u0442\u044b \u0441\u0442\u0430\u0434\u0438\u0438 \u0432 \u043f\u0440\u043e\u0446\u0435\u043d\u0442\u043d\u043e\u043c \u0441\u043e\u043e\u0442\u043d\u043e\u0448\u0435\u043d\u0438\u0438 \u0438 \u0435\u0441\u0442\u044c \u043b\u0438 \u0437\u0430\u0432\u0438\u0441\u0438\u043c\u043e\u0441\u0442\u044c \u043f\u043e\u0440\u044f\u0434\u043a\u0430 \u043f\u043e \u043d\u043e\u043c\u0435\u0440\u0443 \u043a\u0430\u0440\u0442\u0438\u043d\u043a\u0438 \u043e\u0442 \u0441\u0442\u0430\u0434\u0438\u0438\u041a\u043e\u043d\u0435\u0447\u043d\u043e \u0436\u0435 \u0432 \u0441\u043e\u043e\u0442\u0432\u0435\u0442\u0441\u0442\u0432\u0438\u0438 \u0441\u043e \u0441\u0442\u0430\u0442\u0438\u0441\u0442\u0438\u043a\u043e\u0439 \u0437\u0430\u0431\u043e\u043b\u0435\u0432\u0430\u0435\u043c\u043e\u0441\u0442\u0438 \u043f\u0430\u0446\u0438\u0435\u043d\u0442\u043e\u0432 \u0440\u0430\u043a \u0432\u0441\u0442\u0440\u0435\u0447\u0430\u0435\u0442\u0441\u044f \u043c\u0435\u043d\u044c\u0448\u0435\u0433\u043e \u043a\u043e\u043b\u0438\u0447\u0435\u0441\u0442\u0432\u0430 \u043b\u044e\u0434\u0435\u0439 \u0437\u0434\u043e\u0440\u043e\u0432\u044b\u0445 \u043a \u0441\u0447\u0430\u0441\u0442\u044c\u044e \u0431\u043e\u043b\u044c\u0448\u0435 \u0434\u043e 3000 \u0441 1 \u0441\u0442\u0430\u0434\u0438\u0435\u0439 \u043e\u043a\u043e\u043b\u043e 2600 \u0447\u0435\u043b \u0430 \u0441 \u0440\u0430\u0437\u043d\u044b\u043c\u0438 \u0442\u044f\u0436\u0435\u043b\u044b\u043c\u0438 \u0441\u043b\u0443\u0447\u0430\u044f\u043c\u0438 \u0434\u043e 1500 \u043f\u0430\u0446\u0438\u0435\u043d\u043a\u043e\u0432 \u043d\u0430 \u043a\u0430\u0436\u0434\u0443\u044e \u0441\u0442\u0430\u0434\u0438\u044e \u0440\u0430\u043a\u0430 \u0441\u043e 2\u0439 \u043f\u043e \u0441\u0430\u043c\u0443\u044e \u0442\u044f\u0436\u0435\u043b\u0443\u044e 5\u044e \u041f\u0440\u0438 \u044d\u0442\u043e\u043c \u0431\u043e\u043b\u044c\u0448\u0435 \u0434\u0430\u043d\u043d\u044b\u0445 \u043f\u043e \u043f\u0430\u0446\u0438\u0435\u043d\u0442\u0430\u043c \u0438\u0437 \u0443\u043d\u0438\u0432\u0435\u0440\u0441\u0438\u0442\u0435\u0442\u0430 karolinska \u043f\u043e \u043a\u0430\u0436\u0434\u043e\u0439 \u0441\u0442\u0430\u0434\u0438\u0438 \u0435\u0441\u0442\u044c \u0434\u0430\u043d\u043d\u044b\u0435 \u0432 \u043f\u0440\u043e\u0446\u0435\u043d\u0442\u043d\u043e\u043c \u0441\u043e\u043e\u0442\u043d\u043e\u0448\u0435\u043d\u0438\u0438\u041f\u043e\u0441\u043c\u043e\u0442\u0440\u0438\u043c \u043f\u043e \u0442\u043e\u043c\u0443 \u0436\u0435 \u0441\u0430\u043c\u043e\u043c\u0443 \u043f\u0440\u0438\u043d\u0446\u0438\u043f\u0443 \u043d\u0430 \u0440\u0430\u0441\u043f\u0440\u0435\u0434\u0435\u043b\u0435\u043d\u0438\u0435 \u0431\u0430\u043b\u043b\u043e\u0432 \u043f\u043e \u0448\u043a\u0430\u043b\u0435 \u0413\u043b\u0438\u0441\u043e\u043d\u041f\u043e\u0441\u043a\u043e\u043b\u044c\u043a\u0443 \u0441\u0442\u0430\u0434\u0438\u044f \u0440\u0430\u043a\u0430 \u0431\u0430\u043b\u043b \u043f\u043e ISUP \u043d\u0430\u043f\u0440\u044f\u043c\u0443\u044e \u043e\u043f\u0440\u0435\u0434\u0435\u043b\u0435\u043d \u043e\u0446\u0435\u043d\u043a\u043e\u0439 \u043f\u043e \u0413\u043b\u0438\u0441\u043e\u043d\u0443 \u043c\u044b \u043f\u043e\u043b\u0443\u0447\u0438\u043b\u0438 \u043f\u0440\u0438\u043c\u0435\u0440\u043d\u043e \u0442\u0435 \u0436\u0435 \u0441\u0430\u043c\u044b\u0435 \u0433\u0440\u0430\u0444\u0438\u043a\u0438 \u0432\u0438\u0437\u0443\u0430\u043b\u0438\u0437\u0430\u0446\u0438\u0438 Image EDA\u041f\u0435\u0440\u0435\u0439\u0434\u0435\u043c \u043a \u0440\u0430\u0437\u0431\u043e\u0440\u0443 \u0438\u0437\u043e\u0431\u0440\u0430\u0436\u0435\u043d\u0438\u0439 \u0434\u043b\u044f \u043f\u043e\u0441\u043b\u0435\u0434\u0443\u044e\u0449\u0435\u0433\u043e \u0430\u043d\u0430\u043b\u0438\u0437\u0430 \u043a\u0430\u0440\u0442\u0438\u043d\u043e\u043a 1. \u0411\u043e\u043b\u0435\u0435 \u043f\u043e\u0434\u0440\u043e\u0431\u043d\u044b\u0435 \u0441\u0432\u0435\u0434\u0435\u043d\u0438\u044f \u043f\u043e \u0441\u0441\u044b\u043b\u043a\u0435 https www. \u042d\u0442\u043e \u0441\u0432\u044f\u0437\u0430\u043d\u043d\u043e \u0441 \u0442\u0435\u043c \u0447\u0442\u043e \u043f\u0435\u0440\u0432\u044b\u0439 \u0443\u0447\u0430\u0441\u0442\u043e\u043a \u0431\u0438\u043e\u043f\u0441\u0438\u0438 \u0431\u0435\u0440\u0435\u0442\u0441\u044f \u0441 \u0441\u0430\u043c\u043e\u0439 \u0431\u043e\u043b\u044c\u0448\u0435\u0439 \u043e\u043f\u0443\u0445\u043e\u043b\u0438 \u043f\u043e \u043f\u043b\u043e\u0449\u0430\u0434\u0438 \u0433\u0434\u0435 \u0431\u043e\u043b\u044c\u0448\u0435 \u0440\u0430\u043a\u043e\u0432\u044b\u0445 \u043a\u043b\u0435\u0442\u043e\u043a. BatchNorm2d planes self. \u041e\u0434\u043d\u0430\u043a\u043e \u043f\u0440\u0438 \u044d\u0442\u043e\u043c \u043b\u0438\u0448\u044c \u0441\u0442\u0430\u0434\u0438\u0438 3 4 \u0438 4 3 \u043d\u0435 \u044d\u043a\u0432\u0438\u0432\u0430\u043b\u0435\u043d\u0442\u043d\u044b \u043f\u043e\u0441\u043a\u043e\u043b\u044c\u043a\u0443 \u043f\u043e \u043f\u0435\u0440\u0432\u043e\u043c\u0443 \u0431\u043e\u043b\u044c\u0448\u0435\u043c\u0443 \u043f\u043e \u043f\u043b\u043e\u0449\u0430\u0434\u0438 \u0444\u0440\u0430\u0433\u043c\u0435\u043d\u0442\u0443 \u043e\u043f\u0443\u0445\u043e\u043b\u0438 \u043f\u0440\u0438\u0441\u0432\u043e\u0435\u043d\u0430 \u043e\u0446\u0435\u043d\u043a\u0430 \u0432 4 \u0431\u0430\u043b\u043b\u0430 \u0430 \u0432\u0442\u043e\u0440\u0438\u0447\u043d\u043e\u043c\u0443 3 \u044d\u0442\u043e \u0442\u0440\u0435\u0442\u044c\u044f \u0441\u0442\u0430\u0434\u0438\u044f \u0440\u0430\u043a\u0430 3 \u0431\u0430\u043b\u043b\u0430 \u043f\u043e ISUP. \u0420\u0430\u0437\u043c\u0435\u0440\u044b \u043a\u0430\u0436\u0434\u043e\u0433\u043e \u0443\u0440\u043e\u0432\u043d\u044f \u0440\u0430\u0437\u043b\u0438\u0447\u0430\u044e\u0442\u0441\u044f \u0432 \u0437\u0430\u0432\u0438\u0441\u0438\u043c\u043e\u0441\u0442\u0438 \u043e\u0442 \u0440\u0430\u0437\u043c\u0435\u0440\u043e\u0432 \u0438\u0441\u0445\u043e\u0434\u043d\u043e\u0433\u043e \u0438\u0437\u043e\u0431\u0440\u0430\u0436\u0435\u043d\u0438\u044f. \u042d\u0442\u0438 \u043c\u0430\u0441\u043a\u0438 \u043f\u0440\u0435\u0434\u043d\u0430\u0437\u043d\u0430\u0447\u0435\u043d\u044b \u0434\u043b\u044f \u043f\u043e\u043c\u043e\u0449\u0438 \u0432 \u0440\u0430\u0437\u0440\u0430\u0431\u043e\u0442\u043a\u0435 \u0441\u0442\u0440\u0430\u0442\u0435\u0433\u0438\u0439 \u0432\u044b\u0431\u043e\u0440\u0430 \u043d\u0430\u0438\u0431\u043e\u043b\u0435\u0435 \u043f\u043e\u043b\u0435\u0437\u043d\u044b\u0445 \u043f\u043e\u0434\u0432\u044b\u0431\u043e\u0440\u043e\u043a \u0438\u0437\u043e\u0431\u0440\u0430\u0436\u0435\u043d\u0438\u0439. \u041f\u0440\u0438 \u0440\u0430\u0437\u0432\u0438\u0442\u0438\u0438 \u0440\u0430\u043a\u0430 \u043f\u0440\u043e\u0441\u0442\u0430\u0442\u044b \u0432 \u0437\u0430\u0432\u0438\u0441\u0438\u043c\u043e\u0441\u0442\u0438 \u043e\u0442 \u0441\u0442\u0430\u0434\u0438\u0438 \u043d\u043e\u0440\u043c\u0430\u043b\u044c\u043d\u0430\u044f \u0436\u0435\u043b\u0435\u0437\u0438\u0441\u0442\u0430\u044f \u0442\u043a\u0430\u043d\u044c \u0438\u0437\u043e\u0431\u0440\u0430\u0436\u0435\u043d\u0430 \u043d\u0430 \u0440\u0438\u0441\u0443\u043d\u043a\u0435 \u0441\u043b\u0435\u0432\u0430 \u043d\u0430\u0434 \u0446\u0438\u0444\u0440\u043e\u0439 1 \u0438\u043c\u0435\u0435\u0442 \u0431\u0435\u0436\u0435\u0432\u044b\u0439 \u043e\u0442\u0442\u0435\u043d\u043e\u043a \u0434\u0435\u0444\u043e\u0440\u043c\u0438\u0440\u0443\u0435\u0442\u0441\u044f \u0438 \u043f\u043e\u0441\u0442\u0435\u043f\u0435\u043d\u043d\u043e \u0437\u0430\u043c\u0435\u043d\u044f\u0435\u0442\u0441\u044f \u0441\u043e\u0435\u0434\u0438\u043d\u0438\u0442\u0435\u043b\u044c\u043d\u043e\u0439. \u0423\u0432\u0435\u043b\u0438\u0447\u0435\u043d\u0438\u0435 \u043e\u0446\u0435\u043d\u043a\u0438 \u0443\u0447\u0430\u0441\u0442\u043a\u0430 \u043d\u0430 \u0431\u0430\u043b\u043b \u0437\u0430 \u043c\u0435\u043d\u044c\u0448\u0438\u0439 \u043e\u0431\u044a\u0435\u043c \u043f\u043b\u043e\u0449\u0430\u0434\u0438 \u043f\u043e\u0440\u0430\u0436\u0435\u043d\u043d\u044b\u0445 \u043a\u043b\u0435\u0442\u043e\u043a. \u0418\u043d\u0434\u0435\u043a\u0441\u0438\u0440\u043e\u0432\u0430\u043d\u043d\u0430\u044f \u0438 RGB \u0442. avg_pool x if self. \u0422\u0430\u043a\u0438\u043c \u043e\u0431\u0440\u0430\u0437\u043e\u043c \u0441\u0443\u043c\u043c\u0430 \u0413\u043b\u0438\u0441\u043e\u043d\u0430 \u0432\u0430\u0440\u044c\u0438\u0440\u0443\u0435\u0442 \u043e\u0442 2 1 1 \u0434\u043e 10 5 5 \u0431\u0430\u043b\u043b\u043e\u0432. \u0412 \u0441\u043e\u043e\u0442\u0432\u0435\u0442\u0441\u0442\u0432\u0438\u0438 \u0441 \u0434\u0435\u0439\u0441\u0442\u0432\u0443\u044e\u0449\u0438\u043c\u0438 \u0440\u0435\u043a\u043e\u043c\u0435\u043d\u0434\u0430\u0446\u0438\u044f\u043c\u0438 \u041c\u0435\u0436\u0434\u0443\u043d\u0430\u0440\u043e\u0434\u043d\u043e\u0433\u043e \u043e\u0431\u0449\u0435\u0441\u0442\u0432\u0430 \u0443\u0440\u043e\u043b\u043e\u0433\u0438\u0447\u0435\u0441\u043a\u043e\u0439 \u043f\u0430\u0442\u043e\u043b\u043e\u0433\u0438\u0438 ISUP \u0431\u0430\u043b\u043b\u044b \u043f\u043e \u0413\u043b\u0438\u0441\u043e\u043d\u0443 \u0441\u0443\u043c\u043c\u0438\u0440\u0443\u044e\u0442\u0441\u044f \u0432 \u0431\u0430\u043b\u043b\u044b ISUP \u0443\u043a\u0430\u0437\u044b\u0432\u0430\u044e\u0449\u0438\u0435 \u043d\u0430 \u0441\u0442\u0430\u0434\u0438\u0438 \u0440\u0430\u043a\u0430 \u043f\u043e \u0448\u043a\u0430\u043b\u0435 \u043e\u0442 1 \u0434\u043e 5 \u0432 \u0441\u043e\u043e\u0442\u0432\u0435\u0442\u0441\u0442\u0432\u0438\u0438 \u0441\u043e \u0441\u043b\u0435\u0434\u0443\u044e\u0449\u0438\u043c \u043f\u0440\u0430\u0432\u0438\u043b\u043e\u043c 3 \u0438 4 \u0431\u0430\u043b\u043b\u0430 \u043f\u043e\u0433\u0440\u0430\u043d\u0438\u0447\u043d\u044b\u0435 \u0437\u043d\u0430\u0447\u0435\u043d\u0438\u044f \u0434\u043b\u044f \u0431\u043e\u043b\u0435\u0435 \u043f\u043e\u0434\u0440\u043e\u0431\u043d\u043e\u0433\u043e \u043e\u0437\u043d\u0430\u043a\u043e\u043c\u043b\u0435\u043d\u0438\u044f \u043f\u043e \u0440\u0430\u0441\u0447\u0435\u0442\u0443 \u0431\u0430\u043b\u043b\u043e\u0432 \u043c\u043e\u0436\u043d\u043e \u0432\u043e\u0441\u043f\u043e\u043b\u044c\u0437\u043e\u0432\u0430\u0442\u044c\u0441\u044f \u0441\u0441\u044b\u043b\u043a\u043e\u0439 http www. \u0422\u043e \u0435\u0441\u0442\u044c \u043a\u0430\u0436\u0434\u0430\u044f image_id \u0438 \u043a\u0430\u0440\u0442\u0438\u043d\u043a\u0430 \u043a \u043d\u0435\u0439 \u0441\u043e\u0434\u0435\u0440\u0436\u0438\u0442 \u0441\u043a\u0430\u043d \u0442\u043a\u0430\u043d\u0438 \u043f\u0430\u0446\u0438\u0435\u043d\u0442\u0430 \u0441 \u0431\u0438\u043e\u043f\u0441\u0438\u0438 \u0432\u043e\u0437\u043c\u043e\u0436\u043d\u043e \u043e\u0442\u0441\u043d\u044f\u0442\u0430\u044f \u043f\u043e\u0434 \u0440\u0430\u0437\u043d\u044b\u043c \u0443\u0433\u043b\u043e\u043c \u0441 \u0440\u0430\u0437\u043d\u044b\u043c \u0440\u0430\u0437\u0440\u0435\u0448\u0435\u043d\u0438\u0435\u043c \u043d\u043e \u043e\u0434\u0438\u043d. com hmendonca efficientnet pytorchhttps github. expansion for i in range 1 blocks layers. Conv2d 3 64 3 stride 2 padding 1 bias False bn1 nn. relu out out self. AvgPool2d 7 stride 1 self. BatchNorm2d planes block. \u041a\u0430\u0436\u0434\u0430\u044f \u044d\u043f\u0438\u0442\u0435\u043b\u0438\u0430\u043b\u044c\u043d\u0430\u044f \u0435\u0434\u0438\u043d\u0438\u0446\u0430 \u043e\u0431\u043e\u0441\u043e\u0431\u043b\u0435\u043d\u0430 \u0438 \u0438\u043c\u0435\u0435\u0442 \u043f\u0440\u043e\u0441\u0432\u0435\u0442. Upsampling \u043f\u043e\u0432\u044b\u0448\u0430\u044e\u0449\u0430\u044f \u0434\u0438\u0441\u043a\u0440\u0435\u0442\u0438\u0437\u0430\u0446\u0438\u044f \u044d\u0442\u043e \u0443\u0432\u0435\u043b\u0438\u0447\u0435\u043d\u0438\u0435 \u043f\u0440\u043e\u0441\u0442\u0440\u0430\u043d\u0441\u0442\u0432\u0435\u043d\u043d\u043e\u0433\u043e \u0440\u0430\u0437\u0440\u0435\u0448\u0435\u043d\u0438\u044f \u043f\u0440\u0438 \u0441\u043e\u0445\u0440\u0430\u043d\u0435\u043d\u0438\u0438 2D \u043f\u0440\u0435\u0434\u0441\u0442\u0430\u0432\u043b\u0435\u043d\u0438\u044f. \u0418\u0441\u043f\u043e\u043b\u044c\u0437\u0443\u044f \u043d\u0435\u0431\u043e\u043b\u044c\u0448\u0443\u044e \u0432\u0441\u043f\u043e\u043c\u043e\u0433\u0430\u0442\u0435\u043b\u044c\u043d\u0443\u044e \u0444\u0443\u043d\u043a\u0446\u0438\u044e \u043c\u044b \u043c\u043e\u0436\u0435\u043c \u043e\u0442\u043e\u0431\u0440\u0430\u0437\u0438\u0442\u044c \u043d\u0435\u043a\u043e\u0442\u043e\u0440\u0443\u044e \u043e\u0441\u043d\u043e\u0432\u043d\u0443\u044e \u0438\u043d\u0444\u043e\u0440\u043c\u0430\u0446\u0438\u044e \u043e \u043c\u0430\u0441\u043a\u0435. \u041f\u0440\u0435\u043e\u0431\u0440\u0430\u0437\u043e\u0432\u0430\u043d\u0438\u0435 \u0438\u0437\u043e\u0431\u0440\u0430\u0436\u0435\u043d\u0438\u044f \u0441 \u043f\u043e\u043c\u043e\u0449\u044c\u044e \u0441\u0432\u0435\u0440\u0442\u043a\u0438 \u043a\u0430\u0440\u0442\u044b \u0444\u0440\u0430\u0433\u043c\u0435\u043d\u0442\u043e\u0432 \u0421\u043e\u0437\u0434\u0430\u043d\u0438\u0435 \u0438\u0437\u043e\u0431\u0440\u0430\u0436\u0435\u043d\u0438\u044f \u043f\u043e\u0441\u043b\u0435 \u0441\u0432\u0435\u0440\u0442\u043a\u0438\u043f\u0430\u0440\u0430\u043c\u0435\u0442\u0440\u044b \u043d\u043e\u0432\u043e\u0433\u043e \u0438\u0437\u043e\u0431\u0440\u0430\u0436\u0435\u043d\u0438\u044f\u0421\u043e\u0437\u0434\u0430\u0434\u0438\u043c \u043e\u0442\u0434\u0435\u043b\u044c\u043d\u044b\u0439 \u043a\u043b\u0430\u0441\u0441 \u0434\u0430\u0442\u0430\u0441\u0435\u0442\u0430 \u043f\u043e\u0434 \u0442\u0440\u0435\u043d\u0438\u0440\u043e\u0432\u043a\u0443\u0421\u043e\u0437\u0434\u0430\u0434\u0438\u043c \u043a\u043b\u0430\u0441\u0441\u0412 \u043e\u0431\u0443\u0447\u0435\u043d\u0438\u0438 \u0431\u0443\u0434\u0435\u0442 \u0443\u0447\u0430\u0441\u0442\u0432\u043e\u0432\u0430\u0442\u044c \u043c\u043e\u0434\u0435\u043b\u044c efficientnetB0_0\u0422\u0440\u0435\u043d\u0438\u0440\u0443\u0435\u043c \u043c\u043e\u0434\u0435\u043b\u044c \u043d\u0430 \u043f\u043e\u0434\u043a\u043b\u044e\u0447\u0435\u043d\u043d\u043e\u043c \u0432\u0438\u0440\u0442\u0443\u0430\u043b\u044c\u043d\u043e\u043c \u0434\u0435\u0432\u0430\u0439\u0441\u0435\u041f\u0440\u043e\u0432\u0435\u0440\u043a\u0430 \u0441\u0443\u0449\u0435\u0441\u0442\u0432\u043e\u0432\u0430\u043d\u0438\u044f \u0442\u0440\u0435\u043d\u0438\u0440\u043e\u0432\u043e\u0447\u043d\u044b\u0445 \u0438\u0437\u043e\u0431\u0440\u0430\u0436\u0435\u043d\u0438\u0439\u041f\u0440\u0438\u043c\u0435\u043d\u0435\u043d\u0438\u0435 \u043f\u0440\u0435\u0434\u043e\u0431\u0443\u0447\u0435\u043d\u043d\u043e\u0439 \u0441\u0435\u0442\u0438 \u043a \u0441\u0444\u043e\u0440\u043c\u0438\u0440\u043e\u0432\u0430\u043d\u043d\u043e\u043c\u0443 \u0434\u0430\u0442\u0430\u0441\u0435\u0442\u0443 \u043f\u043e\u0434\u0433\u043e\u0442\u043e\u0432\u043b\u0435\u043d\u043d\u044b\u0445 \u0434\u0430\u043d\u043d\u044b\u0445 \u041c\u0435\u0442\u0440\u0438\u043a\u0430 \u043a\u0430\u0447\u0435\u0441\u0442\u0432\u0430 \u043c\u043e\u0434\u0435\u043b\u0438\u0414\u043b\u044f \u043e\u0446\u0435\u043d\u043a\u0438 \u0440\u0435\u0437\u0443\u043b\u044c\u0442\u0430\u0442\u043e\u0432 \u0438\u0441\u0441\u043b\u0435\u0434\u043e\u0432\u0430\u043d\u0438\u044f \u0438\u0441\u043f\u043e\u043b\u044c\u0437\u0443\u0435\u043c Accuracy \u0438 F \u043c\u0435\u0440\u0443. \u0421\u0440\u0435\u0434\u0438 \u043c\u0443\u0436\u0447\u0438\u043d \u0441\u0442\u0430\u0440\u0448\u0435 60 \u043b\u0435\u0442 \u0431\u043e\u043b\u0435\u043d \u0443\u0436\u0435 \u043a\u0430\u0436\u0434\u044b\u0439 \u0441\u043e\u0442\u044b\u0439. Conv2d planes 2 planes 4 kernel_size 3 stride stride padding 1 groups groups bias False self. \u0418\u0442\u0430\u043a \u0447\u0442\u043e \u043d\u0430\u043c \u043d\u0443\u0436\u043d\u043e \u0441\u0434\u0435\u043b\u0430\u0442\u044c \u044d\u0442\u043e \u0432\u0437\u044f\u0442\u044c \u0444\u0430\u0439\u043b \u0438\u0437\u043e\u0431\u0440\u0430\u0436\u0435\u043d\u0438\u044f \u0434\u043b\u044f \u0447\u0442\u0435\u043d\u0438\u044f \u0441 \u043f\u043e\u043c\u043e\u0449\u044c\u044e \u043e\u0431\u044a\u0435\u043a\u0442\u0430 openslide \u0438\u0437\u0432\u043b\u0435\u0447\u044c \u0437\u043d\u0430\u0447\u0435\u043d\u0438\u044f Red Level \u0438 \u0437\u0430\u0442\u0435\u043c \u043f\u0440\u0438\u043c\u0435\u043d\u0438\u0442\u044c \u043a \u043d\u0435\u043c\u0443 cmap. mean settings mean model. \u0422\u0440\u0435\u043d\u0438\u0440\u043e\u0432\u043a\u0430 \u043c\u043e\u0434\u0435\u043b\u0438\u0411\u0430\u0437\u0430 \u0434\u0430\u043d\u043d\u044b\u0445 ImageNet \u043f\u0440\u043e\u0435\u043a\u0442 \u043f\u043e \u0441\u043e\u0437\u0434\u0430\u043d\u0438\u044e \u0438 \u0441\u043e\u043f\u0440\u043e\u0432\u043e\u0436\u0434\u0435\u043d\u0438\u044e \u043c\u0430\u0441\u0441\u0438\u0432\u043d\u043e\u0439 \u0431\u0430\u0437\u044b \u0434\u0430\u043d\u043d\u044b\u0445 \u0430\u043d\u043d\u043e\u0442\u0438\u0440\u043e\u0432\u0430\u043d\u043d\u044b\u0445 \u0438\u0437\u043e\u0431\u0440\u0430\u0436\u0435\u043d\u0438\u0439 \u043f\u0440\u0435\u0434\u043d\u0430\u0437\u043d\u0430\u0447\u0435\u043d\u043d\u0430\u044f \u0434\u043b\u044f \u043e\u0442\u0440\u0430\u0431\u043e\u0442\u043a\u0438 \u0438 \u0442\u0435\u0441\u0442\u0438\u0440\u043e\u0432\u0430\u043d\u0438\u044f \u043c\u0435\u0442\u043e\u0434\u043e\u0432 \u0440\u0430\u0441\u043f\u043e\u0437\u043d\u0430\u0432\u0430\u043d\u0438\u044f \u043e\u0431\u0440\u0430\u0437\u043e\u0432 \u0438 \u043c\u0430\u0448\u0438\u043d\u043d\u043e\u0433\u043e \u0437\u0440\u0435\u043d\u0438\u044f. expansion 4 def __init__ self inplanes planes groups reduction stride 1 downsample None super SEResNetBottleneck self. \u041e\u043d\u0438 \u043d\u0443\u0436\u043d\u044b \u043d\u0430\u043c \u0434\u043b\u044f \u0440\u0430\u0431\u043e\u0442\u044b \u0441 \u043e\u043f\u0440\u0435\u0434\u0435\u043b\u0435\u043d\u043d\u043e\u0439 \u0447\u0430\u0441\u0442\u044c\u044e \u0438\u0437\u043e\u0431\u0440\u0430\u0436\u0435\u043d\u0438\u044f \u043d\u0435\u043e\u0431\u043e\u0434\u0438\u043c\u043e \u0440\u0430\u0437\u043b\u0438\u0447\u0435\u043d\u0438\u0435 \u043a\u043b\u0435\u0442\u043e\u043a \u0436\u0435\u043b\u0435\u0437\u0438\u0441\u0442\u043e\u0439 \u0438 \u0441\u043e\u0435\u0434\u0438\u043d\u0438\u0442\u0435\u043b\u044c\u043d\u043e\u0439 \u0442\u043a\u0430\u043d\u0438 \u043d\u0430\u0441\u043a\u043e\u043b\u044c\u043a\u043e \u0438\u0445 \u043a\u043e\u043d\u0442\u0443\u0440\u044b \u043d\u0435 \u043f\u043e\u0445\u0436\u0438 \u043d\u0430 \u043d\u043e\u0440\u043c\u0430\u043b\u044c\u043d\u044b\u0435 \u043d\u0430\u0441\u043a\u043e\u043b\u044c\u043a\u043e \u0438\u0445 \u0441\u0442\u0430\u043b\u043e \u043c\u0435\u043d\u044c\u0448\u0435 \u0431\u043e\u043b\u044c\u0448\u0435 \u044d\u0442\u043e \u0438 \u0432\u044b\u044f\u0432\u0438\u0442 \u0441\u0442\u0430\u0434\u0438\u044e \u0437\u0430\u0431\u043e\u043b\u0435\u0432\u0430\u043d\u0438\u044f \u043f\u0430\u0446\u0438\u0435\u043d\u0442\u0430. \u0414\u043b\u044f \u0441\u0436\u0430\u0442\u0438\u044f \u0444\u0430\u0439\u043b\u043e\u0432 TIFF \u043c\u043e\u0436\u043d\u043e \u0438\u0441\u043f\u043e\u043b\u044c\u0437\u043e\u0432\u0430\u0442\u044c \u0440\u044f\u0434 \u043c\u0435\u0442\u043e\u0434\u043e\u0432 \u0432\u043a\u043b\u044e\u0447\u0430\u044f \u0430\u043b\u0433\u043e\u0440\u0438\u0442\u043c\u044b \u0425\u0430\u0444\u0444\u043c\u0430\u043d\u0430 \u0438 LZW. \u0414\u043b\u044f \u044d\u0442\u043e\u0433\u043e \u043c\u044b \u0437\u0430\u0433\u0440\u0443\u0436\u0430\u0435\u043c \u0438 \u043c\u0430\u0441\u043a\u0443 \u0438 \u0431\u0438\u043e\u043f\u0441\u0438\u044e \u0438 \u043e\u0431\u044a\u0435\u0434\u0438\u043d\u044f\u0435\u043c \u0438\u0445 \u0441 \u043f\u043e\u043c\u043e\u0449\u044c\u044e PIL. \u041c\u0435\u0436\u0434\u0443 \u0434\u043e\u0431\u0440\u043e\u043a\u0430\u0447\u0435\u0441\u0442\u0432\u0435\u043d\u043d\u044b\u043c\u0438 \u0436\u0435\u043b\u0435\u0437\u0430\u043c\u0438 \u0438\u043d\u0444\u0438\u043b\u044c\u0442\u0440\u0438\u0440\u0443\u044e\u0442 \u043c\u0430\u043b\u0435\u043d\u044c\u043a\u0438\u0435 \u0436\u0435\u043b\u0435\u0437\u044b. ReLU inplace True self. \u0414\u0438\u0430\u0433\u043d\u043e\u0441\u0442\u0438\u043a\u0430 \u0438\u043c\u0435\u0435\u0442 \u043e\u0447\u0435\u043d\u044c \u0432\u0430\u0436\u043d\u043e\u0435 \u0437\u043d\u0430\u0447\u0435\u043d\u0438\u0435 \u0432 \u0441\u0444\u0435\u0440\u0435 \u043b\u0435\u0447\u0435\u043d\u0438\u044f \u0440\u0430\u043a\u0430 \u0441\u0438\u0441\u0442\u0435\u043c\u044b \u0438 \u0442\u0435\u0441\u0442\u044b \u0438\u0441\u043f\u043e\u043b\u044c\u0437\u0443\u0435\u043c\u044b\u0435 \u0434\u043b\u044f \u0432\u044b\u044f\u0432\u043b\u0435\u043d\u0438\u044f \u0437\u0430\u0431\u043e\u043b\u0435\u0432\u0430\u043d\u0438\u044f \u043e\u0441\u043e\u0431\u0435\u043d\u043d\u043e \u0440\u0430\u043d\u043d\u0435\u0433\u043e \u0441\u043f\u0430\u0441\u0430\u044e\u0442 \u0436\u0438\u0437\u043d\u0438 \u043b\u044e\u0434\u0435\u0439 \u043f\u043e\u043c\u043e\u0433\u0430\u044f \u0437\u0430\u0431\u043b\u0430\u0433\u043e\u0432\u0440\u0435\u043c\u0435\u043d\u043d\u043e \u043d\u0430\u0447\u0430\u0442\u044c \u043b\u0435\u0447\u0435\u043d\u0438\u0435 \u0438 \u0434\u0430\u0432\u0430\u044f \u043f\u0430\u0446\u0438\u0435\u043d\u0442\u0430\u043c \u0433\u043e\u0440\u0430\u0437\u0434\u043e \u0431\u043e\u043b\u044c\u0448\u0435 \u0448\u0430\u043d\u0441\u043e\u0432 \u043d\u0430 \u0432\u044b\u0436\u0438\u0432\u0430\u043d\u0438\u0435. IMAGE MASKS Selecting the level SELECTING R from RGB SELECTING BG SELECTING BENIGN LABELS train. bn3 out if self. \u042d\u0442\u043e \u0434\u0430\u0435\u0442 256 \u0432\u043e\u0437\u043c\u043e\u0436\u043d\u044b\u0445 \u0443\u0440\u043e\u0432\u043d\u0435\u0439 \u0438\u043d\u0442\u0435\u043d\u0441\u0438\u0432\u043d\u043e\u0441\u0442\u0438. train_label_masks \u041c\u0430\u0441\u043a\u0438 \u0441\u0435\u0433\u043c\u0435\u043d\u0442\u0430\u0446\u0438\u0438 \u043f\u043e\u043a\u0430\u0437\u044b\u0432\u0430\u044e\u0449\u0438\u0435 \u043a\u0430\u043a\u0438\u0435 \u0447\u0430\u0441\u0442\u0438 \u0438\u0437\u043e\u0431\u0440\u0430\u0436\u0435\u043d\u0438\u044f \u043f\u0440\u0438\u0432\u0435\u043b\u0438 \u043a \u043e\u0446\u0435\u043d\u043a\u0435 ISUP. com c prostate cancer grade assessment overview additional resources \u041d\u0435\u043e\u0431\u0445\u043e\u0434\u0438\u043c\u043e \u0437\u0430\u043c\u0435\u0442\u0438\u0442\u044c \u0447\u0442\u043e \u0432 \u043d\u0430\u0448\u0435\u043c \u043f\u0440\u0438\u0437\u043d\u0430\u043a\u0435 gleason_score \u0444\u0438\u0433\u0443\u0440\u0438\u0440\u0443\u0435\u0442 \u043f\u043e\u043c\u0438\u043c\u043e 0 0 \u0440\u0430\u043a \u043e\u0442\u0441\u0443\u0442\u0441\u0442\u0432\u0443\u0435\u0442 \u0432\u0430\u0440\u0438\u0430\u043d\u0442 negative \u043f\u0440\u0438\u0447\u0435\u043c \u0442\u043e\u043b\u044c\u043a\u043e \u0434\u0430\u043d\u043d\u044b\u0435 \u0443\u0447\u0440\u0435\u0436\u0434\u0435\u043d\u0438\u044f randbound. \u0421\u043e\u0437\u0434\u0430\u0432\u0430\u044f \u0441\u043b\u0438\u0448\u043a\u043e\u043c \u0433\u043b\u0443\u0431\u043e\u043a\u0443\u044e \u0441\u043b\u043e\u0438\u0441\u0442\u0443\u044e \u0441\u0435\u0442\u044c \u043c\u044b \u043c\u043e\u0436\u0435\u043c \u0432 \u043a\u0430\u043a\u043e\u0439 \u0442\u043e \u043c\u043e\u043c\u0435\u043d\u0442 \u043f\u043e\u043b\u0443\u0447\u0438\u0442\u044c \u043d\u0435\u0432\u044b\u0441\u043e\u043a\u0438\u0435 \u0440\u0435\u0437\u0443\u043b\u044c\u0442\u0430\u0442\u044b. OpenSlide gives the resolution in centimeters so we convert this to microns. expansion 4 def __init__ self inplanes planes groups reduction stride 1 downsample None base_width 4 super SEResNeXtBottleneck self. \u041f\u043e\u0441\u043a\u043e\u043b\u044c\u043a\u0443 \u043c\u0430\u0441\u043a\u0438 \u0438\u043c\u0435\u044e\u0442 \u0442\u043e\u0442 \u0436\u0435 \u0440\u0430\u0437\u043c\u0435\u0440 \u0447\u0442\u043e \u0438 \u0441\u043b\u0430\u0439\u0434\u044b \u043c\u044b \u043c\u043e\u0436\u0435\u043c \u043d\u0430\u043a\u043b\u0430\u0434\u044b\u0432\u0430\u0442\u044c \u043c\u0430\u0441\u043a\u0438 \u043d\u0430 \u0442\u043a\u0430\u043d\u044c \u0447\u0442\u043e\u0431\u044b \u0441\u0440\u0430\u0437\u0443 \u0443\u0432\u0438\u0434\u0435\u0442\u044c \u043a\u0430\u043a\u0438\u0435 \u043e\u0431\u043b\u0430\u0441\u0442\u0438 \u044f\u0432\u043b\u044f\u044e\u0442\u0441\u044f \u0437\u043b\u043e\u043a\u0430\u0447\u0435\u0441\u0442\u0432\u0435\u043d\u043d\u044b\u043c\u0438. \u0412 \u0441\u0442\u0440\u043e\u043c\u0435 \u0432\u0438\u0434\u043d\u044b \u0440\u0430\u0441\u0441\u0435\u044f\u043d\u043d\u044b\u0435 \u0435\u0434\u0438\u043d\u0438\u0447\u043d\u044b\u0435 \u0440\u0430\u043a\u043e\u0432\u044b\u0435 \u043a\u043b\u0435\u0442\u043a\u0438. Module def __init__ self channels reduction super SEModule self. expansion kernel_size downsample_kernel_size stride stride padding downsample_padding bias False nn. logits x return x def initialize_pretrained_model model num_classes settings assert num_classes settings num_classes num_classes should be but is. se_module out residual out self. Module def __init__ self model_name se_resnext50_32x4d assert model_name in se_resnext50_32x4d super. to device models. org ru ImageNet \u043f\u043e\u0434\u0440\u043e\u0431\u043d\u043e\u0435 \u043e\u043f\u0438\u0441\u0430\u043d\u0438\u0435 EfficientNet B3 Model\u0414\u043b\u044f \u043f\u0440\u0435\u0434\u043e\u0431\u0440\u0430\u0431\u043e\u0442\u043a\u0438 \u0434\u0430\u043d\u043d\u044b\u0445 \u043c\u044b \u0438\u0441\u043f\u043e\u043b\u044c\u0437\u043e\u0432\u0430\u043b\u0438 \u0442\u0440\u0430\u043d\u0441\u0444\u0435\u0440\u043d\u043e\u0435 \u043e\u0431\u0443\u0447\u0435\u043d\u0438\u0435 \u043c\u0435\u0442\u043e\u0434 \u043c\u0430\u0448\u0438\u043d\u043d\u043e\u0433\u043e \u043e\u0431\u0443\u0447\u0435\u043d\u0438\u044f \u043f\u0440\u0438 \u043a\u043e\u0442\u043e\u0440\u043e\u043c \u0438\u0441\u043f\u043e\u043b\u044c\u0437\u0443\u044e\u0442 \u043f\u0440\u0435\u0434\u0432\u0430\u0440\u0438\u0442\u0435\u043b\u044c\u043d\u043e \u043e\u0431\u0443\u0447\u0435\u043d\u043d\u0443\u044e \u043d\u0435\u0439\u0440\u043e\u043d\u043d\u0443\u044e \u0441\u0435\u0442\u044c \u0434\u043b\u044f \u0440\u0435\u0448\u0435\u043d\u0438\u044f \u0430\u043d\u0430\u043b\u043e\u0433\u0438\u0447\u043d\u043e\u0439 \u0440\u0430\u043d\u0435\u0435 \u043f\u043e\u0441\u0442\u0430\u0432\u043b\u0435\u043d\u043d\u043e\u0439 \u043f\u0435\u0440\u0435\u0434 \u043d\u0435\u0439 \u043f\u0440\u043e\u0431\u043b\u0435\u043c\u044b. \u041e\u0431\u044b\u0447\u043d\u043e\u0435 \u0440\u0430\u0441\u0448\u0438\u0440\u0435\u043d\u0438\u0435 TIFF \u0442\u0430\u043a\u0436\u0435 \u043f\u043e\u0437\u0432\u043e\u043b\u044f\u0435\u0442 \u0438\u0441\u043f\u043e\u043b\u044c\u0437\u043e\u0432\u0430\u0442\u044c \u0438\u0437\u043e\u0431\u0440\u0430\u0436\u0435\u043d\u0438\u044f CMYK. BatchNorm2d inplanes relu1 nn. 2 inplanes 128 input_3x3 True downsample_kernel_size 3 downsample_padding 1 num_classes 1000 super SENet self. \u041d\u0430\u043f\u0440\u0438\u043c\u0435\u0440 \u0438\u0437\u043e\u0431\u0440\u0430\u0436\u0435\u043d\u0438\u0435 \u043c\u043e\u0436\u0435\u0442 \u0431\u044b\u0442\u044c \u043e\u043f\u0440\u0435\u0434\u0435\u043b\u0435\u043d\u043e \u043a\u0430\u043a uint8 8 \u0431\u0438\u0442\u043d\u043e\u0435 \u0446\u0435\u043b\u043e\u0435 \u0447\u0438\u0441\u043b\u043e \u0431\u0435\u0437 \u0437\u043d\u0430\u043a\u0430 \u0447\u0442\u043e \u043e\u0437\u043d\u0430\u0447\u0430\u0435\u0442 \u0447\u0442\u043e \u043a\u0430\u0436\u0434\u044b\u0439 \u043f\u0438\u043a\u0441\u0435\u043b\u044c \u043c\u043e\u0436\u0435\u0442 \u0438\u043c\u0435\u0442\u044c \u0437\u043d\u0430\u0447\u0435\u043d\u0438\u0435 \u0438\u043d\u0442\u0435\u043d\u0441\u0438\u0432\u043d\u043e\u0441\u0442\u044c \u043e\u0442 0 \u0434\u043e 255 \u0438 \u043a\u0430\u0436\u0434\u0430\u044f \u0438\u043d\u0442\u0435\u043d\u0441\u0438\u0432\u043d\u043e\u0441\u0442\u044c \u044f\u0432\u043b\u044f\u0435\u0442\u0441\u044f \u0446\u0435\u043b\u044b\u043c \u0447\u0438\u0441\u043b\u043e\u043c \u0446\u0435\u043b\u044b\u043c \u0447\u0438\u0441\u043b\u043e\u043c \u0432 \u044d\u0442\u043e\u043c \u0434\u0438\u0430\u043f\u0430\u0437\u043e\u043d\u0435. \u0418\u0437 \u0441\u0443\u0449\u0435\u0441\u0442\u0432\u0443\u044e\u0449\u0435\u0433\u043e \u043c\u0435\u0442\u043e\u0434\u0430 \u043f\u043e\u0434 \u043d\u0430\u0437\u0432\u0430\u043d\u0438\u0435\u043c Neural Architecture Search \u0434\u043b\u044f \u0430\u0432\u0442\u043e\u043c\u0430\u0442\u0438\u0447\u0435\u0441\u043a\u043e\u0433\u043e \u0441\u043e\u0437\u0434\u0430\u043d\u0438\u044f \u043d\u043e\u0432\u044b\u0445 \u0441\u0435\u0442\u0435\u0439 \u0438 \u0441\u0432\u043e\u0435\u0433\u043e \u0441\u043e\u0431\u0441\u0442\u0432\u0435\u043d\u043d\u043e\u0433\u043e \u043c\u0435\u0442\u043e\u0434\u0430 \u043c\u0430\u0441\u0448\u0442\u0430\u0431\u0438\u0440\u043e\u0432\u0430\u043d\u0438\u044f \u0430\u0432\u0442\u043e\u0440\u044b \u043f\u043e\u043b\u0443\u0447\u0430\u044e\u0442 \u043d\u043e\u0432\u044b\u0439 \u043a\u043b\u0430\u0441\u0441 \u043c\u043e\u0434\u0435\u043b\u0435\u0439 \u043f\u043e\u0434 \u043d\u0430\u0437\u0432\u0430\u043d\u0438\u0435\u043c EfficientNets. \u041e\u0431\u044b\u0447\u043d\u043e \u043e\u043d \u0438\u0441\u043f\u043e\u043b\u044c\u0437\u0443\u0435\u0442\u0441\u044f \u0434\u043b\u044f \u0443\u043c\u0435\u043d\u044c\u0448\u0435\u043d\u0438\u044f \u0442\u0440\u0435\u0431\u043e\u0432\u0430\u043d\u0438\u0439 \u043a \u0445\u0440\u0430\u043d\u0435\u043d\u0438\u044e \u0438 \u0438\u043b\u0438 \u043f\u0435\u0440\u0435\u0434\u0430\u0447\u0435 \u0438\u0437\u043e\u0431\u0440\u0430\u0436\u0435\u043d\u0438\u0439. DATA visualization Metrics DEBUG True \u043f\u043e\u0441\u043a\u043e\u043b\u044c\u043a\u0443 \u0442\u0435\u0441\u0442\u043e\u0432\u044b\u0435 \u043a\u0430\u0440\u0442\u0438\u043d\u043a\u0438 \u0434\u043b\u044f \u0434\u0430\u043d\u043d\u043e\u0433\u043e \u0441\u043e\u0440\u0435\u0432\u043d\u043e\u0432\u0430\u043d\u0438\u044f \u0444\u043e\u0440\u043c\u0438\u0440\u0443\u044e\u0442\u0441\u044f \u0432 debag \u0440\u0435\u0436\u0438\u043c\u0435 \u0434\u043b\u044f \u0434\u0438\u043f\u043b\u043e\u043c\u043d\u043e\u0439 \u0440\u0430\u0431\u043e\u0442\u044b \u0432\u0437\u044f\u0442\u044b \u0442\u0440\u0435\u043d\u0438\u0440\u043e\u0432\u043e\u0447\u043d\u044b\u0435 \u0432\u0441\u0435 \u0437\u0430 \u0438\u0441\u043a\u043b\u044e\u0447\u0435\u043d\u0438\u0435\u043c 500 \u043f\u043e\u0441\u043b\u0435\u0434\u043d\u0438\u0445 \u0438\u0437\u043e\u0431\u0440\u0430\u0436\u0435\u043d\u0438\u0439 \u0431\u0438\u043e\u043f\u0441\u0438\u0438 \u0434\u043b\u044f \u0442\u0435\u0441\u0442\u043e\u0432\u044b\u0445 \u043f\u043e\u0441\u043b\u0435\u0434\u043d\u0438\u0435 500 \u0438\u0437 \u044d\u0442\u043e\u0433\u043e \u0436\u0435 \u0444\u0430\u0439\u043b\u0430 \u0417\u0434\u0435\u0441\u044c \u043c\u044b \u0432\u044b\u0447\u0438\u0441\u043b\u044f\u0435\u043c \u0438\u043d\u0442\u0435\u0440\u0432\u0430\u043b \u043c\u0435\u0436\u0434\u0443 \u043f\u0438\u043a\u0441\u0435\u043b\u044f\u043c\u0438 \u0444\u0438\u0437\u0438\u0447\u0435\u0441\u043a\u0438\u0439 \u0440\u0430\u0437\u043c\u0435\u0440 \u043f\u0438\u043a\u0441\u0435\u043b\u044f \u0438\u0437\u043e\u0431\u0440\u0430\u0436\u0435\u043d\u0438\u044f. \u041f\u0440\u043e\u043c\u0435\u0436\u0443\u0442\u043e\u0447\u043d\u044b\u0435 \u0443\u0440\u043e\u0432\u043d\u0438 \u043c\u043e\u0433\u0443\u0442 \u0431\u044b\u0442\u044c \u0441\u043e\u0437\u0434\u0430\u043d\u044b \u043f\u0443\u0442\u0435\u043c \u043f\u043e\u043d\u0438\u0436\u0435\u043d\u0438\u044f \u0434\u0438\u0441\u043a\u0440\u0435\u0442\u0438\u0437\u0430\u0446\u0438\u0438 \u0441 \u0431\u043e\u043b\u0435\u0435 \u0432\u044b\u0441\u043e\u043a\u0438\u043c \u0443\u0440\u043e\u0432\u043d\u0435\u043c \u0440\u0430\u0437\u0440\u0435\u0448\u0435\u043d\u0438\u044f. \u0412\u0441\u0435 \u043e\u043d\u0438 \u0432\u043a\u043b\u044e\u0447\u0435\u043d\u044b \u0432 \u0448\u0430\u0431\u043b\u043e\u043d \u0413\u043b\u0438\u0441\u043e\u043d\u0430 4\u0445 \u0431\u0430\u043b\u043b\u043e\u0432. Conv2d channels channels reduction kernel_size 1 padding 0 self. inplanes inplanes if input_3x3 layer0_modules conv1 nn. \u0421\u043f\u0435\u0446\u0438\u0444\u0438\u043a\u0430\u0446\u0438\u044f TIFF \u043b\u0435\u0433\u043a\u043e \u0440\u0430\u0441\u0448\u0438\u0440\u044f\u0435\u0442\u0441\u044f \u0445\u043e\u0442\u044f \u044d\u0442\u043e \u043f\u0440\u043e\u0438\u0441\u0445\u043e\u0434\u0438\u0442 \u0437\u0430 \u0441\u0447\u0435\u0442 \u043d\u0435\u043a\u043e\u0442\u043e\u0440\u043e\u0439 \u043f\u0435\u0440\u0435\u043d\u043e\u0441\u0438\u043c\u043e\u0441\u0442\u0438. \u0410\u0434\u0435\u043d\u043e\u043a\u0430\u0440\u0446\u0438\u043d\u043e\u043c\u0430 \u043f\u0440\u0435\u0434\u0441\u0442\u0430\u0442\u0435\u043b\u044c\u043d\u043e\u0439 \u0436\u0435\u043b\u0435\u0437\u044b 3 \u0431\u0430\u043b\u043b\u0430 \u043f\u043e \u0448\u043a\u0430\u043b\u0435 \u0413\u043b\u0438\u0441\u043e\u043d\u0430. \u0414\u0430\u0436\u0435 \u0441\u0436\u0430\u0442\u044b\u0435 \u0444\u0430\u0439\u043b\u044b TIFF \u043e\u0431\u044b\u0447\u043d\u043e \u043d\u0430\u043c\u043d\u043e\u0433\u043e \u0431\u043e\u043b\u044c\u0448\u0435 \u0447\u0435\u043c \u0430\u043d\u0430\u043b\u043e\u0433\u0438\u0447\u043d\u044b\u0435 \u0444\u0430\u0439\u043b\u044b GIF \u0438\u043b\u0438 JPEG. avg_pool x x self. \u0421\u0432\u044f\u0437\u044c \u0431\u0438\u043e\u043f\u0441\u0438\u0438 \u0438 \u0448\u043a\u0430\u043b\u044b \u0413\u043b\u0438\u0441\u043e\u043d\u0430. \u0426\u0438\u0442\u043e\u043f\u043b\u0430\u0437\u043c\u0430 \u0447\u0430\u0441\u0442\u043e \u0442\u0435\u043c\u043d\u0430\u044f \u0430 \u044f\u0434\u0440\u0430 \u0443\u0432\u0435\u043b\u0438\u0447\u0435\u043d\u044b \u0441 \u0442\u0435\u043c\u043d\u044b\u043c \u0445\u0440\u043e\u043c\u0430\u0442\u0438\u043d\u043e\u043c \u0438 \u043d\u0435\u043a\u043e\u0442\u043e\u0440\u044b\u043c\u0438 \u0432\u044b\u0441\u0442\u0443\u043f\u0430\u044e\u0449\u0438\u043c\u0438 \u044f\u0434\u0440\u044b\u0448\u043a\u0430\u043c\u0438. \u0420\u0430\u0437\u043c\u0435\u0440\u044b \u043a\u0430\u0436\u0434\u043e\u0433\u043e \u0443\u0440\u043e\u0432\u043d\u044f \u0440\u0430\u0437\u043b\u0438\u0447\u0430\u044e\u0442\u0441\u044f \u0432 \u0437\u0430\u0432\u0438\u0441\u0438\u043c\u043e\u0441\u0442\u0438 \u043e\u0442 \u0440\u0430\u0437\u043c\u0435\u0440\u043e\u0432 \u0438\u0441\u0445\u043e\u0434\u043d\u043e\u0433\u043e \u0438\u0437\u043e\u0431\u0440\u0430\u0436\u0435\u043d\u0438\u044f. \u041e\u043d\u0430 \u0438\u0437\u043c\u0435\u0440\u044f\u0435\u0442 \u043a\u043e\u043b\u0438\u0447\u0435\u0441\u0442\u0432\u043e \u0432\u0435\u0440\u043d\u043e \u043a\u043b\u0430\u0441\u0441\u0438\u0444\u0438\u0446\u0438\u0440\u043e\u0432\u0430\u043d\u043d\u044b\u0445 \u043e\u0431\u044a\u0435\u043a\u0442\u043e\u0432 \u043e\u0442\u043d\u043e\u0441\u0438\u0442\u0435\u043b\u044c\u043d\u043e \u043e\u0431\u0449\u0435\u0433\u043e \u043a\u043e\u043b\u0438\u0447\u0435\u0441\u0442\u0432\u0430 \u0432\u0441\u0435\u0445 \u043e\u0431\u044a\u0435\u043a\u0442\u043e\u0432. def forward self x residual x out self. MaxPool2d 3 stride 2 ceil_mode True self. Dropout dropout_p if dropout_p is not None else None self. layer0 x x self. csv \u041e\u0431\u0443\u0447\u0430\u044e\u0449\u0438\u0439 \u0438 \u0442\u0435\u0441\u0442\u043e\u0432\u044b\u0439 \u0434\u0430\u0442\u0430\u0441\u0435\u0442\u044b train. \u041f\u043e\u0441\u043a\u043e\u043b\u044c\u043a\u0443 \u0444\u0430\u0439\u043b\u044b \u043e\u0447\u0435\u043d\u044c \u0431\u043e\u043b\u044c\u0448\u0438\u0435 \u0438 \u0441\u0443\u0449\u0435\u0441\u0442\u0432\u0443\u0435\u0442 \u0442\u0430\u043a \u043c\u043d\u043e\u0433\u043e \u0432\u043e\u0437\u043c\u043e\u0436\u043d\u044b\u0445 \u0432\u0430\u0440\u0438\u0430\u043d\u0442\u043e\u0432 \u043a\u0430\u0436\u0434\u043e\u0433\u043e \u0442\u0438\u043f\u0430 \u0444\u0430\u0439\u043b\u043e\u0432 TIFF \u043d\u0435\u043c\u043d\u043e\u0433\u0438\u0435 \u0432\u0435\u0431 \u0431\u0440\u0430\u0443\u0437\u0435\u0440\u044b \u043c\u043e\u0433\u0443\u0442 \u043e\u0442\u043e\u0431\u0440\u0430\u0436\u0430\u0442\u044c \u0438\u0445 \u0431\u0435\u0437 \u043f\u043e\u0434\u043a\u043b\u044e\u0447\u0430\u0435\u043c\u044b\u0445 \u043c\u043e\u0434\u0443\u043b\u0435\u0439. input_size settings input_size model. dropout is not None x self. _make_layer block planes 128 blocks layers 1 stride 2 groups groups reduction reduction downsample_kernel_size downsample_kernel_size downsample_padding downsample_padding self. model se_resnext50_32x4d pretrained None self. \u041f\u043e\u044d\u0442\u043e\u043c\u0443 \u0438\u0441\u043f\u043e\u043b\u044c\u0437\u0443\u044e\u0442 \u0443\u043c\u0435\u043d\u044c\u0448\u0435\u043d\u0438\u0435 \u0440\u0430\u0437\u0440\u0435\u0448\u0435\u043d\u0438\u044f \u0434\u043b\u044f \u0431\u043e\u043b\u044c\u0448\u0438\u0445 \u0432\u043e\u0437\u043c\u043e\u0436\u043d\u043e\u0441\u0442\u0435\u0439 \u0440\u0430\u0441\u043f\u043e\u0437\u043d\u0430\u0432\u0430\u043d\u0438\u044f \u0438 \u0440\u0430\u0431\u043e\u0442\u044b \u0441 \u0434\u0430\u043d\u043d\u044b\u0435\u043c\u0438. org ru ImageNet \u043f\u043e\u0434\u0440\u043e\u0431\u043d\u043e\u0435 \u043e\u043f\u0438\u0441\u0430\u043d\u0438\u0435EfficientNet \u043a\u043b\u0430\u0441\u0441 \u043d\u043e\u0432\u044b\u0445 \u043c\u043e\u0434\u0435\u043b\u0435\u0439 \u043a\u043e\u0442\u043e\u0440\u044b\u0439 \u043f\u043e\u043b\u0443\u0447\u0438\u043b\u0441\u044f \u0438\u0437 \u0438\u0437\u0443\u0447\u0435\u043d\u0438\u044f \u043c\u0430\u0441\u0448\u0442\u0430\u0431\u0438\u0440\u043e\u0432\u0430\u043d\u0438\u044f \u0441\u043a\u0435\u0439\u043b\u0438\u043d\u0433 scaling \u043c\u043e\u0434\u0435\u043b\u0435\u0439 \u0438 \u0431\u0430\u043b\u0430\u043d\u0441\u0438\u0440\u043e\u0432\u0430\u043d\u0438\u044f \u043c\u0435\u0436\u0434\u0443 \u0441\u043e\u0431\u043e\u0439 \u0433\u043b\u0443\u0431\u0438\u043d\u044b \u0438 \u0448\u0438\u0440\u0438\u043d\u044b \u043a\u043e\u043b\u0438\u0447\u0435\u0441\u0442\u0432\u0430 \u043a\u0430\u043d\u0430\u043b\u043e\u0432 \u0441\u0435\u0442\u0438 \u0430 \u0442\u0430\u043a\u0436\u0435 \u0440\u0430\u0437\u0440\u0435\u0448\u0435\u043d\u0438\u044f \u0438\u0437\u043e\u0431\u0440\u0430\u0436\u0435\u043d\u0438\u0439 \u0432 \u0441\u0435\u0442\u0438. \u0422\u0435\u043f\u0435\u0440\u044c \u043f\u043e\u0441\u043c\u043e\u0442\u0440\u0438\u043c \u043a\u0430\u043a\u0443\u044e \u0438\u043d\u0444\u043e\u0440\u043c\u0430\u0446\u0438\u044e \u043c\u044b \u043c\u043e\u0436\u0435\u043c \u043f\u043e\u043b\u0443\u0447\u0438\u0442\u044c \u0438\u0437 \u0438\u0437\u043e\u0431\u0440\u0430\u0436\u0435\u043d\u0438\u044f \u043f\u043e\u0441\u043b\u0435 \u0441\u043e\u0437\u0434\u0430\u043d\u0438\u044f \u043e\u0431\u044a\u0435\u043a\u0442\u0430 Openslide. \u041f\u043e\u0441\u043c\u043e\u0442\u0440\u0438\u043c \u0442\u0435\u043f\u0435\u0440\u044c \u043d\u0430 1 \u0441\u0442\u0430\u0434\u0438\u044e \u0440\u0430\u043a\u0430\u041e\u043f\u044f\u0442 \u0432\u0438\u0434\u0438\u043c \u0437\u043d\u0430\u0447\u0438\u0442\u0435\u043b\u044c\u043d\u044b\u0435 \u0440\u0430\u0437\u043b\u0438\u0447\u0438\u044f \u0432 \u0446\u0432\u0435\u0442\u0435 \u043f\u043e \u043f\u043e\u0441\u0442\u0430\u0432\u0449\u0438\u043a\u0443 \u0438\u043d\u0444\u043e\u0440\u043c\u0430\u0446\u0438\u0438. relu x x self. F1 score F \u043c\u0435\u0440\u0430 \u0441\u0440\u0435\u0434\u043d\u0435\u0435 \u0433\u0430\u0440\u043c\u043e\u043d\u0438\u0447\u0435\u0441\u043a\u043e\u0435 precision \u0438 recall. ", "id": "natalyayurina/kernel4a3b468030", "size": "25886", "language": "python", "html_url": "https://www.kaggle.com/code/natalyayurina/kernel4a3b468030", "git_url": "https://www.kaggle.com/code/natalyayurina/kernel4a3b468030", "script": "torch.utils.data sklearn.metrics __init__ display _make_layer se_resnext101_32x4d look_canser EfficientNetB0(nn.Module) torch.utils.model_zoo CustomSEResNeXt(nn.Module) tqdm_notebook image_info PANDADataset(Dataset) OrderedDict logits DataLoader check_for_images_dir forward SEModule(nn.Module) torch.nn collections mask_vizual seaborn numpy models graph_objs tqdm_notebook as tqdm EfficientNet config __getitem__ efficientnet_pytorch Bottleneck(nn.Module) write_image PIL torchvision plotly plotly.express mask_info SENet(nn.Module) plotly.figure_factory f1_score Image matplotlib.pyplot get_tiles pandas SEResNeXtBottleneck(Bottleneck) SEBottleneck(Bottleneck) Dataset EfficientNetB3(nn.Module) __len__ accuracy_score tqdm SEResNetBottleneck(Bottleneck) find_canser torch.nn.functional carnser_or_normal transforms features initialize_pretrained_model graph_objs as go IPython.display se_resnext50_32x4d ", "entities": "(('\u041e\u0431\u044b\u0447\u043d\u043e\u0435', '\u0438\u0437\u043e\u0431\u0440\u0430\u0436\u0435\u043d\u0438\u044f \u043f\u043e\u0437\u0432\u043e\u043b\u044f\u0435\u0442 \u0438\u0441\u043f\u043e\u043b\u044c\u0437\u043e\u0432\u0430\u0442\u044c CMYK'), '\u0440\u0430\u0441\u0448\u0438\u0440\u0435\u043d\u0438\u0435') (('we', '\u0417\u0430\u0433\u0440\u0443\u0436\u043a\u0430 \u0438\u0437\u043e\u0431\u0440\u0430\u0436\u0435\u043d\u0438\u044f \u043a\u043e\u043d\u0435\u0447\u043d\u043e\u0433\u043e class SEModule 1024 3 nn'), 'image') (('that', 'forward method'), 'class') (('5 \u0431\u0430\u043b\u043b\u043e\u0432', '\u043b\u0438\u0441\u0442\u044b \u0438\u043b\u0438 \u043d\u0438\u0442\u0438 \u0440\u0430\u043a\u043e\u0432\u044b\u0445 \u0442\u0430\u043a\u0436\u0435 \u0441\u043e\u0434\u0435\u0440\u0436\u0430\u0442\u044c \u0442\u0432\u0435\u0440\u0434\u044b\u0435 \u043a\u043b\u0435\u0442\u043e\u043a'), '\u0413\u043b\u0438\u0441\u043e\u043d\u0430') (('\u0414\u043b\u044f \u0432\u0438\u0437\u0443\u0430\u043b\u0438\u0437\u0430\u0446\u0438\u0438 \u043a\u043e\u043d\u0442\u0443\u0440\u043e\u0432 \u0436\u0435\u043b\u0435\u0437\u0438\u0441\u0442\u043e\u0439 \u0442\u043a\u0430\u043d\u0438 \u043c\u0430\u0442\u0435\u0440\u0438\u0430\u043b \u043f\u0430\u0446\u0438\u0435\u043d\u0442\u0430 \u043e\u043a\u0440\u0430\u0448\u0438\u0432\u0430\u044e\u0442', '\u0438 \u044d\u043e\u0437\u0438\u043d\u043e\u043c H E \u0421\u043e\u0435\u0434\u0438\u043d\u0438\u0442\u0435\u043b\u044c\u043d\u0430\u044f \u0442\u043a\u0430\u043d\u044c \u043f\u0440\u0438\u043e\u0431\u0440\u0435\u0442\u0430\u0435\u0442 \u043e\u0442\u0442\u0435\u043d\u043a\u0438 \u0446\u0432\u0435\u0442\u0430 \u043e\u0441\u0442\u0430\u0435\u0442\u0441\u044f \u0431\u0435\u043b\u044b\u043c\u0438 \u0438 \u043f\u043e\u043b\u0443\u043f\u0440\u043e\u0437\u0440\u0430\u0447\u043d\u044b\u043c\u0438 \u0434\u044b\u0440\u0430\u043c\u0438 \u0436\u0435\u043b\u0435\u0437\u0438\u0441\u0442\u0430\u044f \u0430'), '\u0433\u0435\u043c\u0430\u0442\u043e\u043a\u0441\u0438\u043b\u0438\u043d\u043e\u043c') (('\u043f\u043e\u0434\u0433\u043e\u0442\u043e\u0432\u043b\u0435\u043d\u043d\u044b\u0445 \u0434\u0430\u043d\u043d\u044b\u0445 \u041c\u0435\u0442\u0440\u0438\u043a\u0430', '\u043c\u043e\u0434\u0435\u043b\u0438\u0414\u043b\u044f \u043e\u0446\u0435\u043d\u043a\u0438 \u0440\u0435\u0437\u0443\u043b\u044c\u0442\u0430\u0442\u043e\u0432 \u0438\u0441\u0441\u043b\u0435\u0434\u043e\u0432\u0430\u043d\u0438\u044f \u0438\u0441\u043f\u043e\u043b\u044c\u0437\u0443\u0435\u043c Accuracy \u0438 F \u043c\u0435\u0440\u0443'), '\u0438\u0437\u043e\u0431\u0440\u0430\u0436\u0435\u043d\u0438\u044f') (('_ make_layer block', 'groups groups reduction downsample_padding downsample_padding 1 stride 2 self'), 'plane') (('\u0434\u0432\u0443\u0445\u0443\u0440\u043e\u0432\u043d\u0435\u0432\u044b\u0439 \u0447\u0435\u0440\u043d\u044b\u0439', '\u0447\u0435\u0442\u044b\u0440\u0435 \u0442\u0438\u043f\u0430 \u0438\u0437\u043e\u0431\u0440\u0430\u0436\u0435\u043d\u0438\u0439 \u0414\u043e\u0441\u0442\u0443\u043f\u043d\u044b \u0431\u0430\u0437\u043e\u0432\u044b\u0445 TIFF'), '\u0442') (('\u0412 \u0441\u0442\u0440\u043e\u043c\u0435 \u0432\u0438\u0434\u043d\u044b \u0440\u0430\u0441\u0441\u0435\u044f\u043d\u043d\u044b\u0435', '\u0440\u0430\u043a\u043e\u0432\u044b\u0435 \u043a\u043b\u0435\u0442\u043a\u0438'), '\u0435\u0434\u0438\u043d\u0438\u0447\u043d\u044b\u0435') (('ImageNet Large Scale Visual Recognition Challenge \u043f\u043e \u0448\u0438\u0440\u043e\u043a\u043e\u043c\u0430\u0441\u0448\u0442\u0430\u0431\u043d\u043e\u043c\u0443 \u0440\u0430\u0441\u043f\u043e\u0437\u043d\u0430\u0432\u0430\u043d\u0438\u044e', '\u0432'), '\u041a\u0430\u043c\u043f\u0430\u043d\u0438\u044f') (('\u0410', '4 3 3 2 \u0441\u0442\u0430\u0434\u0438\u044f \u0440\u0430\u043a\u0430 4 3 \u0441\u0442\u0430\u0434\u0438\u044f \u0440\u0430\u043a\u0430'), '\u0438\u043c\u0435\u043d\u043d\u043e') (('BG', 'LABELS BENIGN train'), 'MASKS') (('num_classes num_classes', 'num_classes settings'), 'logit') (('\u043f\u0440\u0438\u0447\u0435\u043c \u0442\u043e\u043b\u044c\u043a\u043e \u0434\u0430\u043d\u043d\u044b\u0435 negative \u0443\u0447\u0440\u0435\u0436\u0434\u0435\u043d\u0438\u044f', 'gleason_score \u043f\u0440\u0438\u0437\u043d\u0430\u043a\u0435 \u043f\u043e\u043c\u0438\u043c\u043e'), 'overview') (('\u0433\u0434\u0435 \u0431\u0430\u043b\u043b\u0430 3 \u0441\u0442\u0430\u0434\u0438\u044f \u0440\u0430\u043a\u0430 \u043f\u043e 4 3 \u0441 4 \u0431\u0430\u043b\u043b\u0430 \u043f\u0435\u0440\u0432\u044b\u0439 \u0444\u0440\u0430\u0433\u043c\u0435\u043d\u0442 3 \u0432\u0442\u043e\u0440\u043e\u0439', '\u0435\u0441\u0442\u044c'), '\u0422\u043e') (('OpenSlide \u0434\u0430\u0435\u0442', '\u0432 \u0441\u0430\u043d\u0442\u0438\u043c\u0435\u0442\u0440\u0430\u0445'), '\u0440\u0430\u0437\u0440\u0435\u0448\u0435\u043d\u0438\u0435') (('\u041f\u043e\u0441\u043c\u043e\u0442\u0440\u0438\u043c \u0442\u0435\u043f\u0435\u0440\u044c', '\u0440\u0430\u043a\u0430\u041e\u043f\u044f\u0442 1 \u0432\u0438\u0434\u0438\u043c'), '\u0441\u0442\u0430\u0434\u0438\u044e') (('\u041f\u0440\u0438 \u044d\u0442\u043e\u043c', '0 \u0438 \u0434\u0430\u043d\u043d\u044b\u0435 train \u043f\u0440\u043e\u0432\u0435\u0440\u0435\u043d\u044b \u043f\u0430\u0442\u043e\u043b\u043e\u0433\u0430\u043c\u0438'), 'isup') (('\u0421\u0440\u0435\u0434\u0438', '\u0431\u043e\u043b\u0435\u043d \u0443\u0436\u0435 \u043a\u0430\u0436\u0434\u044b\u0439 60 \u043b\u0435\u0442 \u0441\u043e\u0442\u044b\u0439'), '\u043c\u0443\u0436\u0447\u0438\u043d') (('\u042d\u0442\u0438 \u043c\u0430\u0441\u043a\u0438 \u043f\u0440\u0435\u0434\u043d\u0430\u0437\u043d\u0430\u0447\u0435\u043d\u044b \u0434\u043b\u044f \u0432 \u0440\u0430\u0437\u0440\u0430\u0431\u043e\u0442\u043a\u0435 \u0441\u0442\u0440\u0430\u0442\u0435\u0433\u0438\u0439', '\u043f\u043e\u043b\u0435\u0437\u043d\u044b\u0445 \u043d\u0430\u0438\u0431\u043e\u043b\u0435\u0435 \u043f\u043e\u0434\u0432\u044b\u0431\u043e\u0440\u043e\u043a \u0438\u0437\u043e\u0431\u0440\u0430\u0436\u0435\u043d\u0438\u0439'), '\u043f\u043e\u043c\u043e\u0449\u0438') (('groups 3 1 groups', 'False self'), 'plane') (('\u0411\u0438\u043e\u043f\u0441\u0438\u0438 \u043c\u043e\u0433\u0443\u0442 \u0431\u044b\u0442\u044c', '\u0432 \u0440\u0430\u0437\u043d\u044b\u0445 \u0440\u0430\u0441\u043f\u043e\u043b\u043e\u0436\u0435\u043d\u0438\u044f\u0445'), '\u043f\u0440\u0435\u0434\u0441\u0442\u0430\u0432\u043b\u0435\u043d\u0430') (('\u041f\u043e\u0441\u043a\u043e\u043b\u044c\u043a\u0443 \u043c\u0430\u0441\u043a\u0438 \u0438\u043c\u0435\u044e\u0442', '\u0440\u0430\u0437\u043c\u0435\u0440 \u0447\u0442\u043e \u0438'), '\u0442\u043e\u0442') (('\u043f\u043e\u0442\u043e\u043c\u0443 \u0447\u0442\u043e', '\u0434\u043e\u043c\u0438\u043d\u0438\u0440\u0443\u044e\u0449\u0435\u0433\u043e \u0442\u0438\u043f\u0430 \u0440\u0430\u043a\u043e\u0432\u044b\u0445 \u043a\u043b\u0435\u0442\u043e\u043a \u0432\u0442\u043e\u0440\u0430\u044f \u0432\u0442\u043e\u0440\u0438\u0447\u043d\u043e\u043c\u0443 \u0438\u043c\u0435\u044e\u0442 \u043f\u043b\u043e\u0449\u0430\u0434\u0438 \u043f\u0435\u0440\u0432\u0430\u044f \u043f\u0440\u0438\u0441\u0432\u0430\u0438\u0432\u0430\u0435\u0442\u0441\u044f \u0441\u043e\u0441\u0440\u0435\u0434\u043e\u0442\u043e\u0447\u0435\u043d\u0438\u044f'), '\u0432\u0441\u0435\u0433\u043e') (('_ make_layer block blocks groups groups reduction 512 layers 3 stride 2 reduction', 'downsample_padding downsample_padding self'), 'plane') (('\u0418\u0437\u043e\u0431\u0440\u0430\u0436\u0435\u043d\u0438\u044f', '\u0446\u0438\u0444\u0440\u043e\u0432\u043e\u0439 \u043f\u0430\u0442\u043e\u043b\u043e\u0433\u0438\u0435\u0439'), '\u043d\u0430\u0437\u044b\u0432\u0430\u044e\u0442') (('\u043f\u0440\u0438\u0447\u0438\u043d\u0430\u043c', '\u0444\u0440\u0430\u0433\u043c\u0435\u043d\u0442\u0443 \u0443\u0432\u0435\u043b\u0438\u0447\u0438\u0432\u0430\u0435\u0442\u0441\u044f \u043d\u0430 \u043e\u0434\u0438\u043d 5 \u0432\u0442\u043e\u0440\u043e\u043c\u0443 \u0431\u0430\u043b\u043b'), '\u0441\u043e\u0441\u0442\u0430\u0432\u043b\u044f\u0442\u044c') (('csv \u0441\u043e\u0434\u0435\u0440\u0436\u0438\u0442\u0441\u044f \u0438\u043d\u0444\u043e\u0440\u043c\u0430\u0446\u0438\u044f \u0434\u0432\u0443\u043c \u043f\u043e \u0413\u043b\u0438\u0441\u043e\u043d', '\u0443\u0447\u0430\u0441\u0442\u043a\u0430\u043c \u0441\u0443\u043c\u043c\u044b \u043f\u0440\u0435\u0434\u0441\u0442\u0430\u0432\u043b\u044f\u0435\u0442\u0441\u044f \u0432 \u0432\u0438\u0434\u0435 \u0431\u0430\u043b\u043b\u043b\u043e\u0432'), '\u0441\u0440\u0430\u0437\u0443') (('\u0432\u043e\u0441\u043f\u043e\u043b\u044c\u0437\u043e\u0432\u0430\u0442\u044c\u0441\u044f \u0441\u0441\u044b\u043b\u043a\u043e\u0439', 'www'), '\u0441\u043e\u043e\u0442\u0432\u0435\u0442\u0441\u0442\u0432\u0438\u0438') (('\u0420\u0435\u0448\u0435\u043d\u0438\u0435 \u043c\u0435\u0434\u0438\u0446\u0438\u043d\u0441\u043a\u0438\u0445', '\u043f\u043e\u043c\u043e\u0449\u044c\u044e \u043d\u0435\u0439\u0440\u043e\u0441\u0435\u0442\u0435\u0439'), '\u0437\u0430\u0434\u0430\u0447') (('\u043f\u0430\u043c\u044f\u0442\u044c \u0432\u0441\u0435', '\u0434\u043b\u044f \u0440\u0430\u0431\u043e\u0442\u044b'), '\u0438\u043d\u0441\u0442\u0440\u0443\u043c\u0435\u043d\u0442\u043e\u043c') (('Conv2d inplanes', 'bias 2 kernel_size 1 False self'), 'plane') (('\u0427\u0442\u043e\u0431\u044b \u0443\u043f\u0440\u043e\u0441\u0442\u0438\u0442\u044c \u043f\u0440\u043e\u0432\u0435\u0440\u043a\u0443', '\u0441\u043e\u043f\u043e\u0441\u0442\u0430\u0432\u043b\u044f\u0435\u043c \u043c\u0435\u0442\u043a\u0438 int'), '\u043c\u0430\u0441\u043e\u043a') (('\u0415\u0432\u0440\u043e\u043f\u0435\u0439\u0441\u043a\u043e\u0433\u043e', '\u0431\u0438\u043e\u0438\u043d\u0444\u043e\u0440\u043c\u0430\u0442\u0438\u043a\u0438 EMBL EBI \u041c\u043e\u0440\u0438\u0446 \u0413\u0435\u0440\u0448\u0442\u0443\u043d\u0433'), '\u0441\u0442\u0430\u043d\u0434\u0430\u0440\u0442\u043e\u043c') (('\u0438 \u0432\u044b\u044f\u0432\u0438\u0442', '\u0437\u0430\u0431\u043e\u043b\u0435\u0432\u0430\u043d\u0438\u044f \u043f\u0430\u0446\u0438\u0435\u043d\u0442\u0430'), '\u0440\u0430\u0431\u043e\u0442\u044b') (('\u0432 \u0440\u0430\u0437\u0434\u0435\u043b\u0435 \u043f\u043e \u0434\u0430\u043d\u043d\u044b\u0445 \u0448\u043a\u0430\u043b\u0430 \u0413\u043b\u0438\u0441\u043e\u043d \u043f\u0440\u0438 \u0438\u043c\u0435\u0435\u0442 \u0440\u0430\u0437\u043d\u044b\u0435 \u043f\u0440\u043e\u0431\u043b\u0435\u043c\u0430\u043c 3 4 4 3 \u0437\u043d\u0430\u0447\u0435\u043d\u0438\u044f', 'ISUP \u0432\u0440\u0435\u043c\u044f \u043f\u043e \u0432 \u0442\u043e \u043a\u0430\u043a'), '\u043c\u044b') (('\u0433\u043b\u0443\u0431\u0438\u043d\u0443', '\u0444\u0438\u043a\u0441\u0438\u0440\u043e\u0432\u0430\u043d\u043d\u044b\u043c\u0438 \u043f\u0440\u043e\u043f\u043e\u0440\u0446\u0438\u044f\u043c\u0438 \u043c\u0435\u0436\u0434\u0443 \u043d\u0438\u043c\u0438'), 'compound') (('\u0438\u0445 \u043f\u043e\u043d\u0438\u043c\u0430\u044e\u0442 \u0431\u043e\u043b\u044c\u0448\u0438\u043d\u0441\u0442\u0432\u043e', '\u0441\u0438\u0441\u0442\u0435\u043c \u0438 \u0442\u0435\u043a\u0441\u0442\u043e\u0432\u044b\u0445 \u0440\u0435\u0434\u0430\u043a\u0442\u043e\u0440\u043e\u0432'), '\u043f\u0435\u0440\u0435\u043d\u043e\u0441\u0438\u043c\u044b') (('\u043d\u0430', '\u0432 \u0430\u043d\u043d\u043e\u0442\u0430\u0446\u0438\u044f\u0445 \u043f\u0435\u0440\u0435\u0447\u0438\u0441\u043b\u044f\u043b\u0438\u0441\u044c \u043e\u0431\u044a\u0435\u043a\u0442\u044b ImageNet \u043f\u043e\u043f\u0430\u0432\u0448\u0438\u0435'), '\u0441\u043e\u0441\u0442\u043e\u044f\u043d\u0438\u044e') (('\u0442\u043e\u043b\u044c\u043a\u043e \u043b\u044e\u0434\u0435\u0439 \u043e\u0431\u043b\u0430\u0434\u0430\u044e\u0449\u0438\u0445 \u0437\u043d\u0430\u0447\u0438\u0442\u0435\u043b\u044c\u043d\u044b\u043c\u0438', '\u0440\u0435\u0441\u0443\u0440\u0441\u0430\u043c\u0438'), '\u043d\u043e\u0432\u044b\u0435') (('\u0414\u043e\u0431\u0440\u043e\u043a\u0430\u0447\u0435\u0441\u0442\u0432\u0435\u043d\u043d\u044b\u0435 \u043f\u0440\u0435\u0434\u0441\u0442\u0430\u0442\u0435\u043b\u044c\u043d\u044b\u0435', '\u0441\u043a\u043b\u0430\u0434\u0447\u0430\u0442\u044b\u043c \u044d\u043f\u0438\u0442\u0435\u043b\u0438\u0435\u043c'), '\u0436\u0435\u043b\u0435\u0437\u044b') (('\u0438 \u044d\u043f\u0438\u0442\u0435\u043b\u0438\u0439 \u0437\u043b\u043e\u043a\u0430\u0447\u0435\u0441\u0442\u0432\u0435\u043d\u043d\u0430\u044f \u0442\u043a\u0430\u043d\u044c \u0438 \u044d\u043f\u0438\u0442\u0435\u043b\u0438\u0439 \u0432\u043c\u0435\u0441\u0442\u0435 \u043d\u0430 \u043d\u0438\u0431\u0443\u0434\u044c \u0418\u043d\u0444\u043e\u0440\u043c\u0430\u0446\u0438\u044f \u043c\u0435\u0442\u043a\u0438 \u0445\u0440\u0430\u043d\u0438\u0442\u0441\u044f \u0432 \u043a\u0440\u0430\u0441\u043d\u043e\u043c R \u043a\u0430\u043d\u0430\u043b\u0435 \u0434\u0440\u0443\u0433\u0438\u0435 \u043a\u0430\u043d\u0430\u043b\u044b \u043d\u0430 \u043d\u043e\u043b\u044c \u0438 \u0441\u0442\u0440\u043e\u043c\u0430 3 \u0441\u0442\u0440\u043e\u043c\u0430 \u043c\u043e\u0433\u0443\u0442', '\u0434\u043e\u0431\u0440\u043e\u043a\u0430\u0447\u0435\u0441\u0442\u0432\u0435\u043d\u043d\u0430\u044f \u0414\u043e\u043f\u0443\u0441\u0442\u0438\u043c\u044b\u0435 \u0437\u043d\u0430\u0447\u0435\u043d\u0438\u044f 1 \u0442\u043a\u0430\u043d\u044c \u0438\u043b\u0438 \u043d\u0435\u0438\u0437\u0432\u0435\u0441\u0442\u043d\u043e 2 \u0442\u043a\u0430\u043d\u044c'), '\u043d\u0435') (('\u0437\u043d\u0430\u0447\u0435\u043d\u0438\u044f\u043c\u0438 \u043e\u0441\u043d\u043e\u0432\u0430\u043d\u043d\u044b\u043c\u0438 \u043d\u0430', '\u0440\u0430\u0437\u043b\u0438\u0447\u043d\u044b\u0435 6 \u043f\u0440\u0435\u0434\u0441\u0442\u0430\u0432\u043b\u044f\u044f \u043c\u0435\u0442\u043a\u0438'), '\u0441\u043e\u0431\u043e\u0439') (('\u041f\u0430\u043b\u0438\u0442\u0440\u0430 \u0438 \u043f\u043e\u043b\u0443\u0442\u043e\u043d\u043e\u0432\u044b\u0435 \u0438\u0437\u043e\u0431\u0440\u0430\u0436\u0435\u043d\u0438\u044f', '\u0438\u043b\u0438 256 \u0446\u0432\u0435\u0442\u0430\u043c\u0438 \u043e\u0442\u0442\u0435\u043d\u043a\u0430\u043c\u0438'), '\u043e\u0433\u0440\u0430\u043d\u0438\u0447\u0435\u043d\u044b') (('latter', 'ResNet'), 'follow') (('append model \u0440\u0430\u0437\u0431\u0438\u0432\u0430\u0435\u043c', '\u0431\u0438\u043e\u043f\u0441\u0438\u0438 \u043d\u0430 16 \u0447\u0430\u0441\u0442\u0435\u0439'), '\u0438\u0437\u043e\u0431\u0440\u0430\u0436\u0435\u043d\u0438\u0435') (('\u043a\u043e\u0442\u043e\u0440\u043e\u043c \u0438\u0441\u043f\u043e\u043b\u044c\u0437\u0443\u044e\u0442', '\u043f\u043e\u0441\u0442\u0430\u0432\u043b\u0435\u043d\u043d\u043e\u0439 \u043f\u0435\u0440\u0435\u0434 \u043d\u0435\u0439 \u0430\u043d\u0430\u043b\u043e\u0433\u0438\u0447\u043d\u043e\u0439 \u043f\u0440\u043e\u0431\u043b\u0435\u043c\u044b'), 'ru') (('\u0440\u0430\u0441\u0442\u0440\u043e\u0432\u043e\u0433\u043e \u043f\u0435\u0440\u0435\u043c\u0435\u043d\u043d\u044b\u043c \u0440\u0430\u0437\u0440\u0435\u0448\u0435\u043d\u0438\u0435\u043c \u0440\u0430\u0437\u0440\u0430\u0431\u043e\u0442\u0430\u043d\u043d\u044b\u0439 Aldus', '\u041a\u0430\u043a\u043e\u0439 \u0438\u0437\u043e\u0431\u0440\u0430\u0436\u0435\u043d\u0438\u0439 \u043d\u0430\u043c \u0444\u043e\u0440\u043c\u0430\u0442 \u043f\u0440\u0435\u0434\u043e\u0441\u0442\u0430\u0432\u043b\u0435\u043d'), '\u043a\u0430\u043a') (('\u043f\u043e 5 \u0431\u0430\u043b\u043b\u043e\u0432 \u0448\u043a\u0430\u043b\u0435', '\u043f\u0440\u0435\u0434\u0441\u0442\u0430\u0442\u0435\u043b\u044c\u043d\u043e\u0439 \u0436\u0435\u043b\u0435\u0437\u044b'), '\u0410\u0434\u0435\u043d\u043e\u043a\u0430\u0440\u0446\u0438\u043d\u043e\u043c\u0430') (('\u0423\u0417\u0418 \u0423\u043b\u044c\u0442\u0440\u0430\u0437\u0432\u0443\u043a\u043e\u0432\u043e\u0435', '\u0442\u043a\u0430\u043d\u0435\u0439 \u043f\u0440\u043e\u0441\u0442\u0430\u0442\u044b\u0411\u0438\u043e\u043f\u0441\u0438\u044f \u0437\u0430\u0431\u043e\u0440\u0430 \u043f\u0440\u043e\u0432\u043e\u0434\u0438\u0442\u0441\u044f'), '\u0443\u0441\u0442\u0430\u043d\u043e\u0432\u0438\u0442\u044c') (('\u041f\u043e\u044d\u0442\u043e\u043c\u0443 \u0438\u0441\u043f\u043e\u043b\u044c\u0437\u0443\u044e\u0442', '\u0438 \u0440\u0430\u0431\u043e\u0442\u044b'), '\u0443\u043c\u0435\u043d\u044c\u0448\u0435\u043d\u0438\u0435') (('pretrained', 'num_classes 1 downsample_padding 0 num_classes'), 'pretraine') (('pretrained', 'num_classes 1 downsample_padding 0 num_classes'), 'setting') (('TIFF', '\u043f\u0440\u0438\u043b\u043e\u0436\u0435\u043d\u0438\u044f \u0434\u043b\u044f \u043c\u0430\u043a\u0435\u0442\u0430 \u0441\u0442\u0440\u0430\u043d\u0438\u0446\u044b'), '\u043e\u0447\u0435\u043d\u044c') (('\u0422\u043e\u0447\u043d\u043e', '\u0434\u0432\u0430 \u0443\u0440\u043e\u0432\u043d\u044f \u0438 \u0431\u0435\u043b\u044b\u0439'), '\u0447\u0435\u0440\u043d\u044b\u0439') (('\u0441\u043a\u0430\u043d \u0442\u043a\u0430\u043d\u0438 \u0441 \u0431\u0438\u043e\u043f\u0441\u0438\u0438 \u0432\u043e\u0437\u043c\u043e\u0436\u043d\u043e \u043f\u043e\u0434 \u043a\u0430\u0440\u0442\u0438\u043d\u043a\u0430 \u043a \u043d\u0435\u0439 \u0441\u043e\u0434\u0435\u0440\u0436\u0438\u0442 \u0440\u0430\u0437\u043d\u044b\u043c', '\u0440\u0430\u0437\u043d\u044b\u043c \u0440\u0430\u0437\u0440\u0435\u0448\u0435\u043d\u0438\u0435\u043c \u043d\u043e \u043e\u0434\u0438\u043d'), '\u0442\u043e') (('_ make_layer block', 'stride groups groups reduction downsample_padding downsample_padding 2 2 self'), 'plane') (('\u043a\u043b\u0430\u0441\u0441\u0438\u0444\u0438\u0446\u0438\u0440\u043e\u0432\u0430\u043d\u043d\u044b\u0445 \u043e\u0431\u044a\u0435\u043a\u0442\u043e\u0432', '\u0432\u0441\u0435\u0445 \u043e\u0431\u0449\u0435\u0433\u043e \u043a\u043e\u043b\u0438\u0447\u0435\u0441\u0442\u0432\u0430 \u043e\u0431\u044a\u0435\u043a\u0442\u043e\u0432'), '\u043a\u043e\u043b\u0438\u0447\u0435\u0441\u0442\u0432\u043e') (('inplanes planes groups reduction', 'nn'), 'return') (('\u0421\u043f\u0435\u0446\u0438\u0444\u0438\u043a\u0430\u0446\u0438\u044f TIFF', '\u0441\u0447\u0435\u0442 \u043d\u0435\u043a\u043e\u0442\u043e\u0440\u043e\u0439 \u0437\u0430 \u043f\u0435\u0440\u0435\u043d\u043e\u0441\u0438\u043c\u043e\u0441\u0442\u0438'), '\u043b\u0435\u0433\u043a\u043e') (('\u0421\u0430\u043c\u0430\u044f \u0432\u044b\u0441\u043e\u043a\u0430\u044f', '\u0432\u0441\u0435\u0433\u0434\u0430 \u0434\u043e\u043b\u0436\u043d\u0430 \u0431\u044b\u0442\u044c \u0447\u0430\u0441\u0442\u044c\u044e \u043e\u0446\u0435\u043d\u043a\u0438'), '\u043e\u0446\u0435\u043d\u043a\u0430') (('\u0438 \u043d\u0435\u043a\u043e\u0442\u043e\u0440\u044b\u0435', '\u0436\u0435\u043b\u0435\u0437\u044b'), '\u043c\u0430\u043b\u0435\u043d\u044c\u043a\u0438\u0435') (('\u0440\u0430\u043a\u0430 \u0415\u0441\u043b\u0438 5 \u0441\u0442\u0430\u0434\u0438\u044f \u0440\u0430\u043a\u0430', '\u043e\u0431\u043d\u0430\u0440\u0443\u0436\u0435\u043d\u043e ISUP \u0441\u0442\u0430\u0434\u0438\u044f \u0440\u0430\u043a\u0430 \u0438\u043c\u0435\u0435\u0442'), '\u0431\u0430\u043b\u043b\u043e\u0432') (('Conv2d', '4 planes'), 'plane') (('\u0422\u0435\u0441\u0442\u043e\u0432\u044b\u043c\u0438 \u0434\u0430\u043d\u043d\u044b\u043c\u0438 \u044f\u0432\u043b\u044f\u044e\u0442\u0441\u044f', '\u0442\u0440\u0435\u043d\u0438\u0440\u043e\u0432\u043e\u0447\u043d\u044b\u043c\u0438 \u043e\u0441\u0442\u0430\u043b\u044c\u043d\u044b\u0435 500 \u0441\u0442\u0440\u043e\u043a \u0431\u043e\u043b\u0435\u0435'), '\u043f\u043e\u0441\u043b\u0435\u0434\u043d\u0438\u0435') (('\u043f\u043e\u0440\u0430\u0436\u0435\u043d\u043d\u044b\u0445', '\u043e\u0446\u0435\u043d\u043a\u0438 \u0443\u0447\u0430\u0441\u0442\u043a\u0430 \u043d\u0430 \u0431\u0430\u043b\u043b'), '\u043a\u043b\u0435\u0442\u043e\u043a') (('\u0442\u0430\u043a \u043c\u043d\u043e\u0433\u043e \u0432\u043e\u0437\u043c\u043e\u0436\u043d\u044b\u0445 \u0432\u0430\u0440\u0438\u0430\u043d\u0442\u043e\u0432 \u043a\u0430\u0436\u0434\u043e\u0433\u043e \u0442\u0438\u043f\u0430 \u0444\u0430\u0439\u043b\u043e\u0432 TIFF', '\u043c\u043e\u0433\u0443\u0442 \u0431\u0435\u0437 \u0432\u0435\u0431 \u0431\u0440\u0430\u0443\u0437\u0435\u0440\u044b \u043e\u0442\u043e\u0431\u0440\u0430\u0436\u0430\u0442\u044c \u0438\u0445 \u043f\u043e\u0434\u043a\u043b\u044e\u0447\u0430\u0435\u043c\u044b\u0445 \u043c\u043e\u0434\u0443\u043b\u0435\u0439'), '\u0441\u0443\u0449\u0435\u0441\u0442\u0432\u0443\u0435\u0442') (('\u043a\u0430\u0436\u0434\u043e\u0435', '\u0431\u043b\u0438\u0437\u043a\u043e'), '\u043f\u044b\u0442\u0430\u0435\u0442\u0435\u0441\u044c') (('Conv2d planes', '4 kernel_size 1 bias'), 'plane') (('\u0438\u0437\u043e\u0431\u0440\u0430\u0436\u0435\u043d\u0438\u044f', '\u043f\u0440\u0438\u043d\u0430\u0434\u043b\u0435\u0436\u0430\u0442 \u043f\u0440\u043e\u0435\u043a\u0442\u0443'), '\u0430\u043d\u043d\u043e\u0442\u0430\u0446\u0438\u0435\u0439') (('\u0422\u043a\u0430\u043d\u044c \u043f\u0440\u043e\u0441\u0442\u0430\u0442\u044b \u0441\u043e\u0441\u0442\u043e\u0438\u0442 \u0438 \u043f\u0440\u0435\u0438\u043c\u0443\u0449\u0435\u0441\u0442\u0432\u0435\u043d\u043d\u043e \u043c\u044b\u0448\u0435\u0447\u043d\u044b\u0445 \u0436\u0435\u043b\u0435\u0437\u0438\u0441\u0442\u044b\u0445', '\u0438\u0437 \u0441\u043e\u0435\u0434\u0438\u043d\u0438\u0442\u0435\u043b\u044c\u043d\u043e\u0439 \u0442\u0430\u043a\u0436\u0435 \u0442\u043a\u0430\u043d\u0438'), '\u0438\u0437') (('\u0413\u043b\u0438\u0441\u043e\u043d\u041f\u043e\u0441\u043a\u043e\u043b\u044c\u043a\u0443 \u0441\u0442\u0430\u0434\u0438\u044f \u0440\u0430\u043a\u0430 ISUP \u043d\u0430\u043f\u0440\u044f\u043c\u0443\u044e \u043c\u044b', 'EDA\u041f\u0435\u0440\u0435\u0439\u0434\u0435\u043c'), 'EDA') (('\u044d\u0442\u043e 3 \u0441\u0442\u0430\u0434\u0438\u044f \u0440\u0430\u043a\u0430', '\u043f\u043e 3 ISUP'), '\u0441\u0442\u0430\u0434\u0438\u0438') (('\u0431\u0435\u0437 \u0443\u043d\u0438\u0432\u0435\u0440\u0441\u0438\u0442\u0435\u0442\u0430\u043c\u0426\u0432\u0435\u0442\u0430 \u0440\u0430\u043a\u0430 \u0438', '\u0434\u0432\u0443\u043c \u0443\u043d\u0438\u0432\u0435\u0440\u0441\u0438\u0442\u0435\u0442\u0430\u043c \u0442\u043a\u0430\u043d\u0435\u0439 \u043f\u043e \u043e\u0442\u043b\u0438\u0447\u0430\u044e\u0442\u0441\u044f'), '\u0441\u043b\u0430\u0439\u0434\u044b') (('\u0414\u043b\u044f', '\u0440\u044f\u0434 \u043c\u0435\u0442\u043e\u0434\u043e\u0432 \u0432\u043a\u043b\u044e\u0447\u0430\u044f \u0430\u043b\u0433\u043e\u0440\u0438\u0442\u043c\u044b \u0425\u0430\u0444\u0444\u043c\u0430\u043d\u0430 \u0438 \u0438\u0441\u043f\u043e\u043b\u044c\u0437\u043e\u0432\u0430\u0442\u044c LZW'), '\u0441\u0436\u0430\u0442\u0438\u044f') (('\u0431\u043e\u043b\u044c\u0448\u0435 \u043d\u0430', '\u0437\u0430\u0431\u043b\u0430\u0433\u043e\u0432\u0440\u0435\u043c\u0435\u043d\u043d\u043e \u043d\u0430\u0447\u0430\u0442\u044c \u043e\u0441\u043e\u0431\u0435\u043d\u043d\u043e \u0440\u0430\u043d\u043d\u0435\u0433\u043e \u0441\u043f\u0430\u0441\u0430\u044e\u0442 \u0436\u0438\u0437\u043d\u0438 \u043b\u044e\u0434\u0435\u0439 \u043f\u043e\u043c\u043e\u0433\u0430\u044f \u0434\u0430\u0432\u0430\u044f \u0433\u043e\u0440\u0430\u0437\u0434\u043e'), '\u0437\u043d\u0430\u0447\u0435\u043d\u0438\u0435') (('pixel', 'image'), '\u044d\u043a\u0440\u0430\u043d') (('\u0444\u0438\u0447 \u043f\u043e\u043b\u0443\u0447\u0430\u0435\u043c\u044b\u0445 \u043d\u0430 \u0432\u044b\u0445\u043e\u0434\u0435 \u043f\u043e\u0441\u043b\u0435 \u0441\u0432\u0435\u0440\u0442\u043a\u0438', '\u041f\u043e\u0441\u043c\u043e\u0442\u0440\u0438\u043c \u043d\u0430 \u043e\u0441\u043d\u043e\u0432\u043d\u043e\u0439 \u0434\u0430\u0442\u0430\u0441\u0435\u0442 train'), '\u0432\u0441\u0435\u0445') (('\u0442\u0438\u043f\u0430 RGB \u043a\u0440\u0430\u0441\u043d\u044b\u0439 \u0437\u0435\u043b\u0435\u043d\u044b\u0439 \u0418\u0437\u043e\u0431\u0440\u0430\u0436\u0435\u043d\u0438\u0435 \u0441\u0438\u043d\u0438\u0439', '\u043e\u043f\u0440\u0435\u0434\u0435\u043b\u044f\u0435\u0442 \u043a\u0440\u0443\u043f\u043d\u043e\u043c\u0430\u0441\u0448\u0442\u0430\u0431\u043d\u043e\u0435 \u0438\u0437\u043e\u0431\u0440\u0430\u0436\u0435\u043d\u0438\u0435 \u043d\u0435\u043a\u043e\u0442\u043e\u0440\u044b\u0435 \u0442\u0438\u043f\u044b \u0438\u0437\u043e\u0431\u0440\u0430\u0436\u0435\u043d\u0438\u0439 \u0441\u043e\u0434\u0435\u0440\u0436\u0430\u0442 \u0431\u043e\u043b\u0435\u0435'), '\u0438\u0441\u043f\u043e\u043b\u044c\u0437\u0443\u0435\u0442') (('\u041c\u0430\u0441\u043a\u0438', '\u044f\u0432\u043b\u044f\u044e\u0442\u0441\u044f \u0434\u0430\u043d\u043d\u044b\u043c\u0438 \u0438\u0437\u043e\u0431\u0440\u0430\u0436\u0435\u043d\u0438\u044f \u043a\u0430\u043a WSI'), '\u043d\u0435') (('\u043e\u043d\u0438', '\u0432 \u0413\u043b\u0438\u0441\u043e\u043d\u0430 4\u0445 \u0448\u0430\u0431\u043b\u043e\u043d \u0431\u0430\u043b\u043b\u043e\u0432'), '\u0432\u043a\u043b\u044e\u0447\u0435\u043d\u044b') (('\u0437\u0430\u0433\u0440\u0443\u0437\u0438\u0442\u044c', '\u0441\u043e\u043e\u0442\u0432\u0435\u0442\u0441\u0442\u0432\u0443\u0435\u0442 \u043f\u043e\u043d\u0438\u0436\u0435\u043d\u0438\u044e'), '\u0441\u043b\u0430\u0439\u0434') (('\u041d\u0430 \u044d\u0442\u043e\u0439 \u043c\u0438\u043a\u0440\u043e\u0444\u043e\u0442\u043e\u0433\u0440\u0430\u0444\u0438\u0438 \u0432\u0438\u0434\u0435\u043d \u043d\u0435\u043f\u0440\u0430\u0432\u0438\u043b\u044c\u043d\u044b\u0439 \u0440\u0435\u0448\u0435\u0442\u0447\u0430\u0442\u044b\u0439 \u0440\u0430\u043a', '\u0435\u0441\u0442\u044c \u044d\u043f\u0438\u0442\u0435\u043b\u0438\u0430\u043b\u044c\u043d\u044b\u0435'), '\u0442\u043e') (('\u0440\u0438\u0441\u0443\u043d\u043a\u0435', '\u0446\u0438\u0444\u0440\u043e\u0439'), '\u043f\u0440\u0438') (('\u043d\u0435\u043c\u0443 \u0438\u0434\u0435\u0442 \u043f\u043e\u0441\u043b\u0435 \u0441\u0438\u043c\u0432\u043e\u043b\u0430', '\u0441\u043e\u0435\u0434\u0438\u043d\u0438\u0442\u0435\u043b\u044c\u043d\u043e\u0439 \u0442\u043a\u0430\u043d\u0435\u0439 \u0438 \u043f\u043e \u043f\u0435\u0440\u0432\u0438\u0447\u043d\u044b\u043c \u0443\u0447\u0430\u0441\u0442\u043a\u043e\u043c \u0438 \u043d\u0435\u043c\u0443 \u0438 \u0431\u043e\u043b\u044c\u0448\u0438\u0439 \u043f\u043e \u043f\u043b\u043e\u0449\u0430\u0434\u0438 \u0441\u043e\u043e\u0442\u0432\u0435\u0442\u0441\u0442\u0432\u0435\u043d\u043d\u043e \u043f\u043b\u043e\u0449\u0430\u0434\u0438 \u0441\u0447\u0438\u0442\u0430\u0435\u0442\u0441\u044f \u043f\u043e \u0432'), '\u044d\u0442\u043e\u043c') (('\u041f\u043e\u0441\u043c\u043e\u0442\u0440\u0438\u043c \u0441\u043a\u043e\u043b\u044c\u043a\u043e \u043f\u0430\u0446\u0438\u0435\u043d\u0442\u043e\u0432', '\u041f\u043e\u0441\u043c\u043e\u0442\u0440\u0438\u043c \u0442\u0435\u043f\u0435\u0440\u044c \u0432 \u043f\u0443\u0442\u0430\u0442\u044c \u043c\u043e\u0434\u0435\u043b\u044c \u0447\u0442\u043e \u043b\u0435\u0436\u0438\u0442 \u0434\u0430\u0442\u0430\u0441\u0435\u0442\u0435 test'), '\u0441\u0443\u0449\u0435\u0441\u0442\u0432\u0443\u0435\u0442') (('Module def _ _ init _ _ self block layers groups', 'dropout_p'), 'reduction') (('efficientnet hmendonca pytorchhttps', 'github'), 'com') (('\u0438\u0445 \u0440\u044f\u0434\u043e\u043c \u0434\u0430\u0432\u0430\u0439\u0442\u0435 \u043d\u0430\u043b\u043e\u0436\u0438\u043c \u0438\u0445 \u0434\u0440\u0443\u0433 \u043d\u0430', '\u0438 \u043e\u0442\u043e\u0431\u0440\u0430\u0436\u0430\u0442\u044c'), '\u043a\u043e\u0442\u043e\u0440\u044b\u0435') (('\u043d\u0430\u043c\u0438 \u043c\u0435\u0442\u043e\u0434 \u043f\u043e\u043a\u0430\u0437\u044b\u0432\u0430\u0435\u0442 \u0447\u0442\u043e \u043a\u043e\u043c\u043f\u044c\u044e\u0442\u0435\u0440\u043d\u043e\u0435 \u041f\u0440\u0435\u0434\u043b\u043e\u0436\u0435\u043d\u043d\u044b\u0439 \u0437\u0440\u0435\u043d\u0438\u0435', '\u0434\u0438\u0430\u0433\u043d\u043e\u0441\u0442\u0438\u043a\u0435 \u0440\u0430\u043a\u0430'), '\u043d\u0430\u0440\u044f\u0434\u0443') (('py\u0421\u043e\u0437\u0434\u0430\u0434\u0438\u043c \u043e\u0442\u0434\u0435\u043b\u044c\u043d\u044b\u0435 \u0432 \u043a\u043e\u0442\u043e\u0440\u044b\u0445 \u0431\u0443\u0434\u0435\u043c \u043f\u043e', '\u044d\u043a\u0437\u0435\u043c\u043f\u043b\u044f\u0440\u0430\u043c \u043c\u043e\u0434\u0435\u043b\u0435\u0439 \u0434\u0430\u043d\u043d\u043e\u0439 \u0442\u0440\u0430\u043d\u0441\u0444\u0435\u0440\u043d\u043e\u0439 \u0441\u0435\u0442\u0438'), '\u043a\u043b\u0430\u0441\u0441\u044b') (('Conv2d 3 inplanes', '2 3 bias'), 'kernel_size') (('\u0438', '\u0431\u044b\u0442\u044c'), '\u043d\u0435') (('org ImageNet \u043f\u043e\u0434\u0440\u043e\u0431\u043d\u043e\u0435', '\u043a\u043b\u0430\u0441\u0441 \u043d\u043e\u0432\u044b\u0445 \u043c\u043e\u0434\u0435\u043b\u0435\u0439'), 'ru') (('\u0432\u044b\u0447\u0438\u0441\u043b\u044f\u0435\u043c \u043c\u0435\u0436\u0434\u0443 \u043f\u0438\u043a\u0441\u0435\u043b\u044f\u043c\u0438 \u0438\u043d\u0442\u0435\u0440\u0432\u0430\u043b \u0444\u0438\u0437\u0438\u0447\u0435\u0441\u043a\u0438\u0439', '\u043f\u0438\u043a\u0441\u0435\u043b\u044f \u0438\u0437\u043e\u0431\u0440\u0430\u0436\u0435\u043d\u0438\u044f'), 'visualization') (('\u041f\u0440\u043e\u043c\u0435\u0436\u0443\u0442\u043e\u0447\u043d\u044b\u0435 \u0443\u0440\u043e\u0432\u043d\u0438', '\u043c\u043e\u0433\u0443\u0442 \u0431\u044b\u0442\u044c \u0441\u043e\u0437\u0434\u0430\u043d\u044b \u043f\u0443\u0442\u0435\u043c \u0441 \u0431\u043e\u043b\u0435\u0435 \u0443\u0440\u043e\u0432\u043d\u0435\u043c \u0432\u044b\u0441\u043e\u043a\u0438\u043c \u0440\u0430\u0437\u0440\u0435\u0448\u0435\u043d\u0438\u044f'), '\u0434\u0438\u0441\u043a\u0440\u0435\u0442\u0438\u0437\u0430\u0446\u0438\u0438') (('\u0442\u0438\u043f \u0413\u043b\u0438\u0441\u043e\u043d\u0443 \u0434\u043e\u043b\u0436\u043d\u0430 3 \u043d\u0430 5 \u043f\u043e\u043b\u0443\u0447\u0438\u0442\u044c', '4 5 9'), '\u0441\u043e\u0434\u0435\u0440\u0436\u0430\u0449\u0430\u044f') (('\u041c\u0435\u0436\u0434\u0443 \u0434\u043e\u0431\u0440\u043e\u043a\u0430\u0447\u0435\u0441\u0442\u0432\u0435\u043d\u043d\u044b\u043c\u0438 \u0436\u0435\u043b\u0435\u0437\u0430\u043c\u0438 \u0438\u043d\u0444\u0438\u043b\u044c\u0442\u0440\u0438\u0440\u0443\u044e\u0442', '\u0436\u0435\u043b\u0435\u0437\u044b'), '\u043c\u0430\u043b\u0435\u043d\u044c\u043a\u0438\u0435') (('layers Sequential def', 'self self'), 'feature') (('\u042d\u0442\u0438 \u043c\u0430\u0441\u043a\u0438', '\u0447\u0430\u0441\u0442\u0438 \u0442\u043a\u0430\u043d\u0438 \u044f\u0432\u043b\u044f\u044e\u0442\u0441\u044f \u0437\u0434\u043e\u0440\u043e\u0432\u044b\u043c\u0438 \u0430 \u0443\u043a\u0430\u0437\u044b\u0432\u0430\u044e\u0442 \u043a\u0430\u043a\u0438\u0435 \u043a\u0430\u043a\u0438\u0435 \u0437\u043b\u043e\u043a\u0430\u0447\u0435\u0441\u0442\u0432\u0435\u043d\u043d\u044b\u043c\u0438'), '\u043f\u0440\u044f\u043c\u043e') (('\u0438', '\u0430\u043d\u043d\u043e\u0442\u0438\u0440\u043e\u0432\u0430\u043d\u043d\u044b\u0445 \u043c\u0430\u0441\u0441\u0438\u0432\u043d\u043e\u0439 \u0431\u0430\u0437\u044b \u0438\u0437\u043e\u0431\u0440\u0430\u0436\u0435\u043d\u0438\u0439'), '\u0434\u0430\u043d\u043d\u044b\u0445') (('\u0415\u0441\u043b\u0438', '\u0441\u0438\u0442\u0443\u0430\u0446\u0438\u044f \u043e\u0431\u0440\u0430\u0442\u043d\u0430\u044f \u0438 \u0432\u0442\u043e\u0440\u0438\u0447\u043d\u0430\u044f'), '\u043e\u0435\u043d\u043a\u0443') (('kernel_size', '1 0 self'), 'padding') (('se_resnext50_32x4d', 'None self'), 'pretraine') (('image_mask data_provider karolinska', 'CANCEROUS LABELS elif train'), 'select') (('\u0411\u0430\u043b\u043b\u044b \u043f\u043e', '\u043a\u0430\u0436\u0434\u043e\u043c\u0443 \u0438\u0437'), '\u0441\u043a\u043b\u0430\u0434\u044b\u0432\u0430\u044e\u0442\u0441\u044f') (('ReLU True', 'conv1 else nn'), 'inplace') (('so we', 'microns'), 'give') (('\u041e\u0431\u044b\u0447\u043d\u043e', '\u0438\u0441\u043f\u043e\u043b\u044c\u0437\u0443\u0435\u0442\u0441\u044f \u0434\u043b\u044f \u0443\u043c\u0435\u043d\u044c\u0448\u0435\u043d\u0438\u044f \u0442\u0440\u0435\u0431\u043e\u0432\u0430\u043d\u0438\u0439 \u043e\u043d \u043a'), '\u0438\u0437\u043e\u0431\u0440\u0430\u0436\u0435\u043d\u0438\u0439') (('SEModule', 'reduction reduction 4 self'), 'plane') (('blocks groups groups reduction 64 layers 0 reduction', '1 downsample_padding 0 self'), 'plane') (('Conv2d', 'False bn1 nn'), 'padding') (('Conv2d', 'False stride'), 'inplanes') (('\u041c\u0413\u0423', '\u041b\u043e\u043c\u043e\u043d\u043e\u0441\u043e\u0432\u0430'), '\u0444\u043e\u0442\u043e\u0441\u043d\u0438\u043c\u043a\u0430\u043c') (('\u0426\u0438\u0442\u043e\u043f\u043b\u0430\u0437\u043c\u0430 \u0447\u0430\u0441\u0442\u043e \u0442\u0435\u043c\u043d\u0430\u044f \u0430', '\u0442\u0435\u043c\u043d\u044b\u043c \u0438 \u043d\u0435\u043a\u043e\u0442\u043e\u0440\u044b\u043c\u0438 \u0432\u044b\u0441\u0442\u0443\u043f\u0430\u044e\u0449\u0438\u043c\u0438 \u0443\u0432\u0435\u043b\u0438\u0447\u0435\u043d\u044b \u0441 \u0445\u0440\u043e\u043c\u0430\u0442\u0438\u043d\u043e\u043c \u044f\u0434\u0440\u044b\u0448\u043a\u0430\u043c\u0438'), '\u044f\u0434\u0440\u0430') (('\u041c\u043d\u043e\u0433\u0438\u0435 \u043f\u0440\u0438\u043b\u043e\u0436\u0435\u043d\u0438\u044f', '\u0440\u044f\u0434 \u043e\u0442 \u043f\u0440\u0438\u043b\u043e\u0436\u0435\u043d\u0438\u0439'), '\u0432') (('groups 1 groups', 'False self'), 'pad') (('1000 super SENet', '3 downsample_padding 1 num_classes'), 'inplanes') (('\u0438', '\u0440\u0430\u043a\u0430'), '\u0434\u0430\u043d\u043d\u043e\u043c') (('\u044d\u0442\u043e \u0432\u0437\u044f\u0442\u044c \u0444\u0430\u0439\u043b \u0434\u043b\u044f \u043f\u043e\u043c\u043e\u0449\u044c\u044e \u0438\u0437\u0432\u043b\u0435\u0447\u044c \u0437\u043d\u0430\u0447\u0435\u043d\u0438\u044f Red \u0438 \u0441\u0434\u0435\u043b\u0430\u0442\u044c openslide \u0437\u0430\u0442\u0435\u043c', '\u043a \u043d\u0435\u043c\u0443 cmap'), '\u0447\u0442\u043e') (('_ _ se_resnext50_32x4d', 'se_resnext50_32x4d'), 'assert') (('com ru company', 'Accuracy 328372 Metric'), 'ods') (('\u043d\u0430', '\u0431\u043e\u043b\u044c\u0448\u043e\u043c \u043a\u0430\u0434\u0440\u0435'), '\u0438\u0441\u043f\u043e\u043b\u044c\u0437\u0443\u0435\u0442\u0441\u044f') (('\u043e\u043f\u0443\u0445\u043e\u043b\u0435\u0439', '\u0444\u0440\u0430\u0433\u043c\u0435\u043d\u0442\u0430'), '\u043e\u0441\u043e\u0431\u0435\u043d\u043d\u043e\u0441\u0442\u0438') (('\u042d\u0442\u043e \u043d\u0430\u043b\u043e\u0436\u0435\u043d\u0438\u0435', '\u0440\u0430\u0437\u043b\u0438\u0447\u043d\u044b\u0435 \u043c\u043e\u0434\u0435\u043b\u0438 \u0440\u043e\u0441\u0442\u0430'), '\u043f\u043e\u043c\u043e\u0436\u0435\u0442') (('Precision \u043a\u0430\u043a \u043e\u0431\u044a\u0435\u043a\u0442\u043e\u0432 \u043d\u0430\u0437\u0432\u0430\u043d\u043d\u044b\u0445 \u043f\u043e\u043b\u043e\u0436\u0438\u0442\u0435\u043b\u044c\u043d\u044b\u043c\u0438 \u0438 \u043c\u043e\u0436\u043d\u043e \u0438\u043d\u0442\u0435\u0440\u043f\u0440\u0435\u0442\u0438\u0440\u043e\u0432\u0430\u0442\u044c \u043f\u0440\u0438', '\u044f\u0432\u043b\u044f\u044e\u0449\u0438\u043c\u0438\u0441\u044f \u043f\u043e\u043b\u043e\u0436\u0438\u0442\u0435\u043b\u044c\u043d\u044b\u043c\u0438 \u0430 recall \u043f\u043e\u043a\u0430\u0437\u044b\u0432\u0430\u0435\u0442 \u043a\u0430\u043a\u0443\u044e \u0434\u0435\u0439\u0441\u0442\u0432\u0438\u0442\u0435\u043b\u044c\u043d\u043e \u0434\u043e\u043b\u044e'), '\u044d\u0442\u043e\u043c') (('\u043e\u043f\u0443\u0445\u043e\u043b\u044c', '\u0441\u0444\u043e\u0440\u043c\u0438\u0440\u043e\u0432\u0430\u0442\u044c \u043f\u043e\u043b\u043d\u043e\u0446\u0435\u043d\u043d\u044b\u0435 \u0445\u043e\u0440\u043e\u0448\u043e \u0440\u0430\u0437\u0432\u0438\u0442\u044b\u0435 \u0436\u0435\u043b\u0435\u0437\u044b'), '\u043f\u0440\u043e\u0441\u0432\u0435\u0442') (('\u0444\u043e\u0440\u043c\u0430\u0442\u0430\u0445 \u0438\u0437\u043e\u0431\u0440\u0430\u0436\u0435\u043d\u0438\u0439 \u0434\u0430\u043d\u043d\u044b\u0435 \u0438\u0437\u043e\u0431\u0440\u0430\u0436\u0435\u043d\u0438\u044f \u0438\u043c\u0435\u044e\u0442 \u0412 \u043d\u0435\u043a\u043e\u0442\u043e\u0440\u044b\u0445 \u0444\u0438\u043a\u0441\u0438\u0440\u043e\u0432\u0430\u043d\u043d\u043e\u0435', '\u0432\u043e\u0437\u043c\u043e\u0436\u043d\u044b\u0445 \u0437\u043d\u0430\u0447\u0435\u043d\u0438\u0439 \u0438\u043d\u0442\u0435\u043d\u0441\u0438\u0432\u043d\u043e\u0441\u0442\u0438'), '\u043a\u043e\u043b\u0438\u0447\u0435\u0441\u0442\u0432\u043e') (('\u043a\u043b\u0430\u0441\u0441\u0438\u0444\u0438\u043a\u0430\u0446\u0438\u0438 Accuracy Metric \u0442\u0430\u043a \u043a\u0430\u043a \u043e\u043d\u0430 \u0438\u043d\u0442\u0443\u0438\u0442\u0438\u0432\u043d\u043e', '\u0438 \u043e\u0447\u0435\u0432\u0438\u0434\u043d\u0430 \u0434\u043e\u043b\u044f \u043f\u0440\u0430\u0432\u0438\u043b\u044c\u043d\u044b\u0445 \u043e\u0442\u0432\u0435\u0442\u043e\u0432 \u043d\u0430\u043c\u0438 \u0441\u043e\u0437\u0434\u0430\u043d\u043d\u043e\u0433\u043e \u0430\u043b\u0433\u043e\u0440\u0438\u0442\u043c\u0430'), '\u043c\u0435\u0442\u0440\u0438\u043a\u0443') (('Conv2d channels channels reduction kernel_size', '1 0 self'), 'padding') (('\u043a\u0430\u0436\u0434\u043e\u043c\u0443 \u0443\u0447\u0430\u0441\u0442\u043a\u043e\u0432 \u0442\u043a\u0430\u043d\u0438 \u043d\u0430 \u0431\u0438\u043e\u043f\u0441\u0438\u0438 \u0438\u0437 \u0434\u0432\u0443\u0445 \u0442\u043e\u043b\u044c\u043a\u043e', '\u0438 3 4 5'), '\u0432\u044b\u0433\u043b\u044f\u0434\u0438\u0442') (('\u041c\u0435\u0436\u0434\u0443 \u0431\u0438\u043e\u043f\u0441\u0438\u044f\u043c\u0438 \u043d\u0430\u0431\u043b\u044e\u0434\u0430\u044e\u0442\u0441\u044f', '\u0437\u0430\u043c\u0435\u0442\u043d\u044b\u0435 \u0412\u044b\u0432\u0435\u0434\u0435\u043c \u0432 \u0446\u0432\u0435\u0442\u0435 \u0441\u0440\u0430\u0437\u0443 \u043d\u0435\u0441\u043a\u043e\u043b\u044c\u043a\u043e \u0438\u0437\u043e\u0431\u0440\u0430\u0436\u0435\u043d\u0438\u0439'), '\u0440\u0430\u0437\u043b\u0438\u0447\u0438\u044f') (('ISUP \u043c\u043e\u0433\u0443\u0442 3 6 3 1 \u0441\u0442\u0430\u0434\u0438\u044f \u0440\u0430\u043a\u0430', '5 10 5 5 \u0441\u0442\u0430\u0434\u0438\u044f \u0440\u0430\u043a\u0430'), '\u043e\u0446\u0435\u043d\u043a\u0438') (('\u0438', '\u043e\u0434\u043d\u0443 \u0438\u0437 \u0431\u0438\u043e\u043f\u0441\u0438\u0439'), '\u0437\u0430\u0433\u0440\u0443\u0437\u0438\u0442\u044c') (('255 \u0438 \u043a\u0430\u0436\u0434\u0430\u044f \u044f\u0432\u043b\u044f\u0435\u0442\u0441\u044f \u0446\u0435\u043b\u044b\u043c \u0447\u0438\u0441\u043b\u043e\u043c \u0438\u043d\u0442\u0435\u043d\u0441\u0438\u0432\u043d\u043e\u0441\u0442\u044c \u0446\u0435\u043b\u044b\u043c', '\u0432 \u044d\u0442\u043e\u043c \u0434\u0438\u0430\u043f\u0430\u0437\u043e\u043d\u0435'), '\u0447\u0438\u0441\u043b\u043e\u043c') (('stride groups 4 kernel_size 3 1 groups', 'False self'), 'plane') (('Conv2d', '64 3 stride 1 padding 1 bias'), 'inplane') (('\u0437\u043b\u043e\u043a\u0430\u0447\u0435\u0441\u0442\u0432\u0435\u043d\u043d\u0430\u044f', '\u0442\u0435\u043c \u0431\u043e\u043b\u044c\u0448\u0430\u044f \u0441\u0442\u0430\u0434\u0438\u044f \u0437\u0430\u0431\u043e\u043b\u0435\u0432\u0430\u043d\u0438\u044f \u0440\u0430\u043a\u043e\u043c'), '\u043a\u043b\u0435\u0442\u043e\u043a') (('\u043e\u0446\u0435\u043d\u0435\u043d \u0432\u043e 4 3 \u0432\u0442\u043e\u0440\u0443\u044e', '\u0440\u0430\u043a\u0430'), '\u0435\u0449\u0435') (('\u0432\u0441\u0435 \u043e\u0441\u0442\u0430\u043b\u044c\u043d\u044b\u0435 \u0441\u0442\u0430\u0434\u0438\u0438 \u0440\u0430\u043a\u0430 \u041a\u0430\u0436\u0434\u044b\u0439 \u0441\u043b\u0430\u0439\u0434 \u0432\u044b \u043c\u043e\u0436\u0435\u0442\u0435 \u0442\u0430\u043a\u0436\u0435 3 \u0441\u043b\u043e\u044f \u0437\u0430\u0433\u0440\u0443\u0437\u0438\u0442\u044c', '\u0441\u043e\u043e\u0442\u0432\u0435\u0442\u0441\u0442\u0432\u0443\u0435\u0442 \u043f\u043e\u043d\u0438\u0436\u0435\u043d\u0438\u044e'), '\u0438\u043c\u0435\u0435\u0442') (('\u043e\u043f\u0440\u0435\u0434\u0435\u043b\u044f\u044e\u0442 \u043e\u043d\u0438 \u0446\u0432\u0435\u0442', '\u044d\u0442\u0438\u0445 \u043f\u0438\u043a\u0441\u0435\u043b\u0435\u0439'), '\u0438\u043d\u0442\u0435\u043d\u0441\u0438\u0432\u043d\u043e\u0441\u0442\u0438') (('\u043f\u0440\u0438\u0441\u0443\u0442\u0441\u0442\u0432\u0443\u044e\u0449\u0435\u0439 \u0432 \u0444\u0430\u0439\u043b\u0435 csv \u043f\u043e\u0447\u0442\u0438 \u0432\u0441\u0435', '\u0434\u043e\u043f\u043e\u043b\u043d\u0438\u0442\u0435\u043b\u044c\u043d\u043e\u0439 \u0438\u043d\u0444\u043e\u0440\u043c\u0430\u0446\u0438\u0435\u0439 \u0441 \u043c\u0435\u0442\u043a\u0438'), '\u0441\u043b\u0430\u0439\u0434\u0430') (('model num_classes initialize_pretrained_model settings', 'return model class CustomSEResNeXt nn'), 'pretraine') (('\u0438 \u043a\u043b\u0435\u0442\u043a\u0438 \u043f\u0440\u0438\u043e\u0431\u0440\u0435\u0442\u0430\u044e\u0442', '\u0440\u0430\u0437\u043c\u0430\u0437\u0430\u043d\u043d\u044b\u0435 \u043a\u043e\u043d\u0442\u0443\u0440\u044b'), '\u0441\u0442\u0440\u0443\u043a\u0442\u0443\u0440\u0430') (('expansion kernel_size', 'stride stride padding downsample_padding bias False nn'), 'downsample_kernel_size') (('\u0426\u0438\u0442\u043e\u043f\u043b\u0430\u0437\u043c\u0430 \u0431\u043b\u0435\u0434\u043d\u0430\u044f \u044f\u0434\u0440\u0430', '\u0438 \u043f\u0440\u0430\u0432\u0438\u043b\u044c\u043d\u044b\u0435'), '\u043c\u0430\u043b\u0435\u043d\u044c\u043a\u0438\u0435') (('\u0414\u0430\u0436\u0435 \u0441\u0436\u0430\u0442\u044b\u0435', '\u043d\u0430\u043c\u043d\u043e\u0433\u043e \u0430\u043d\u0430\u043b\u043e\u0433\u0438\u0447\u043d\u044b\u0435 \u0444\u0430\u0439\u043b\u044b \u0438\u043b\u0438 \u0431\u043e\u043b\u044c\u0448\u0435 \u0447\u0435\u043c GIF JPEG'), '\u043e\u0431\u044b\u0447\u043d\u043e') ", "extra": "['test', 'bag']", "label": "Perfect_files", "potential_description_queries": ["api", "append", "assessment", "background", "blob", "block", "blog", "cancer", "company", "compound", "compute", "config", "convert", "csv", "def", "device", "downsample", "efficientnet", "ensemble", "floor", "format", "forward", "grade", "http", "image", "imagenet", "implementation", "input", "int", "kaggle", "karolinska", "latter", "level", "load", "mask", "mean", "method", "model", "negative", "not", "num_classes", "open", "openslide", "out", "overview", "padding", "part", "pixel", "post", "precision", "pretrained", "prostate", "python", "pytorch", "radboud", "range", "recall", "residual", "resolution", "return", "scaling", "score", "shape", "sigmoid", "size", "std", "stride", "tiff", "torchvision", "train", "train_images", "type", "url", "validation", "visualization", "width"], "potential_description_queries_len": 76, "potential_script_queries": ["display", "nn", "numpy", "plotly", "seaborn", "torch", "tqdm"], "potential_script_queries_len": 7, "potential_entities_queries": ["csv", "init", "negative", "openslide", "recall", "train"], "potential_entities_queries_len": 6, "potential_extra_queries": ["bag"], "potential_extra_queries_len": 1, "all_components_potential_queries_len": 81}