{"name": "pneumonia classification 97 recall ", "full_name": " h1 Image recognition from chest X Rays to classify if Patients have pneumonia h2 Find the best model h1 Table of contents h3 1 Data preprocessing and visualization h3 2 Load the Images with a generator and Data Augmentation h3 3 Test 27 canned architectures with pre trained weights h3 4 Train the best architecture h3 5 Examples of prediction h2 Context h2 Content h2 Acknowledgements h2 Inspiration h1 1 Data preprocessing and visualization h1 2 Load the Images with a generator and Data Augmentation h1 3 Test 27 canned architectures with pre trained weights h1 5 Examples of prediction ", "stargazers_count": 0, "forks_count": 0, "description": "Load the Images with a generator and Data Augmentation 3. Load the Images with a generator and Data Augmentation 2 3. For the analysis of chest x ray images all chest radiographs were initially screened for quality control by removing all low quality or unreadable scans. AcknowledgementsLicense CC BY 4. Train the best architecture 4 5. There are 5 863 X Ray images JPEG and 2 categories Pneumonia Normal. Examples of prediction 5 Context Chest X RayChest X Rays https i. All chest X ray imaging was performed as part of patients routine clinical care. In order to account for any grading errors the evaluation set was also checked by a third expert. Illustrative Examples of Chest X Rays in Patients with Pneumonia Related to Figure 6The normal chest X ray left panel depicts clear lungs without any areas of abnormal opacification in the image. org api_docs python tf keras applications hl en 5. applications https www. Data preprocessing and visualization 1 2. 15 width_shift_range 0. The diagnoses for the images were then graded by two expert physicians before being cleared for training the AI system. Data preprocessing and visualization 2. Test 27 canned architectures with pre trained weightsMore info about the architectures under Module tf. 2 height_shift_range 0. 2 shear_range 0. org api_docs python tf keras applications hl enhttps www. png InspirationAutomated methods to detect and classify human diseases from medical images. Examples of prediction Print with Markdowns Create a list with the filepaths for training and testing Concatenate filepaths and labels Shuffle the DataFrame and reset index Combine train_df and val_df The DataFrame with the filepaths in one column and the labels in the other one Display the number of pictures of each category in the training set Display some pictures of the dataset Load the Images with a generator and Data Augmentation rotation_range 30 Uncomment to use data augmentation zoom_range 0. Test 27 canned architectures with pre trained weights 3 4. 15 horizontal_flip True fill_mode nearest rotation_range 30 Uncomment to use data augmentation on the validation set zoom_range 0. Bacterial pneumonia middle typically exhibits a focal lobar consolidation in this case in the right upper lobe white arrows whereas viral pneumonia right manifests with a more diffuse interstitial pattern in both lungs. ContentThe dataset is organized into 3 folders train test val and contains subfolders for each image category Pneumonia Normal. Chest X ray images anterior posterior were selected from retrospective cohorts of pediatric patients of one to five years old from Guangzhou Women and Children s Medical Center Guangzhou. Image recognition from chest X Rays to classify if Patients have pneumonia Find the best model Table of contents 1. 15 horizontal_flip True fill_mode nearest Load the pretained model Dictionary with the models Create the generators Fit the models Get the model Fit the model Sav the duration and the val_accuracy Predict the label of the test_images Map the label Create a DataFrame with the results Predict the labels of the test_images for the best model Map the label Display a confusion matrix Display picture of the dataset with their labels. ", "id": "databeru/pneumonia-classification-97-recall", "size": "2603", "language": "python", "html_url": "https://www.kaggle.com/code/databeru/pneumonia-classification-97-recall", "git_url": "https://www.kaggle.com/code/databeru/pneumonia-classification-97-recall", "script": "sklearn.metrics get_model proc_img display Markdown perf_counter Path seaborn numpy pathlib time confusion_matrix sklearn.model_selection matplotlib.pyplot tensorflow pandas classification_report accuracy_score printmd create_gen train_test_split IPython.display ", "entities": "(('Chest X ray images anterior posterior', 'Guangzhou one to five years old Women'), 'select') (('white viral pneumonia', 'lungs'), 'exhibit') (('chest X normal ray left panel', 'image'), 'Examples') (('diagnoses', 'AI system'), 'grade') (('pneumonia', 'contents'), 'find') (('label', 'labels'), 'fill_mode') (('org api_docs', '5'), 'python') (('evaluation set', 'also third expert'), 'in') (('ContentThe dataset', 'image category'), 'organize') (('chest radiographs', 'low quality'), 'screen') (('pictures', 'data 30 augmentation'), 'create') (('chest X ray imaging', 'clinical care'), 'perform') ", "extra": "['biopsy of the greater curvature', 'disease', 'patient', 'test', 'lung']", "label": "Perfect_files", "potential_description_queries": ["account", "architecture", "augmentation", "best", "case", "category", "chest", "classify", "clear", "column", "confusion", "control", "data", "dataset", "detect", "duration", "en", "evaluation", "focal", "generator", "grading", "human", "image", "index", "info", "initially", "label", "left", "list", "matrix", "medical", "middle", "model", "nearest", "normal", "number", "order", "panel", "part", "pattern", "picture", "pneumonia", "png", "pre", "prediction", "preprocessing", "python", "reset", "right", "routine", "selected", "set", "test", "testing", "tf", "train", "training", "under", "upper", "val", "validation", "visualization"], "potential_description_queries_len": 62, "potential_script_queries": ["display", "numpy", "pathlib", "seaborn", "sklearn", "tensorflow", "time"], "potential_script_queries_len": 7, "potential_entities_queries": ["normal"], "potential_entities_queries_len": 1, "potential_extra_queries": ["biopsy", "lung"], "potential_extra_queries_len": 2, "all_components_potential_queries_len": 71}